Workbook

Sheet Students
A1: student_id | B1: full_name | C1: gender | D1: date_of_birth | E1: email | F1: phone | G1: program | H1: major | I1: department | J1: year_of_study | K1: gpa | L1: credit_hours_earned | M1: status | N1: nationality | O1: enrollment_date | P1: expected_graduation | Q1: Student Type | R1: Programme Level | S1: Journey Stage | T1: Current Semester | U1: Fees Status | V1: Fees Balance (KES) | W1: Academic Standing | X1: Last Standing Review | Y1: Dissertation Title | Z1: Dissertation Status | AA1: Graduation Clearance | AB1: Actual Graduation Date
A2: TU-2021-0001 | B2: Amelia Odhiambo | C2: Female | D2: 2001-03-12 | E2: a.odhiambo@templumis.ac | F2: +254712345001 | G2: BSc | H2: Computer Science | I2: School of Computing | J2: Year 3 | K2: 3.78 | L2: 96 | M2: Active | N2: Kenyan | O2: 2021-09-05 | P2: 2025-06-30 | Q2: Undergraduate | R2: BSc | S2: 3. Progressing — Year 3 | T2: Sem 6 | U2: Paid | V2: 0 | W2: Good Standing | X2: 2024-01-15 | Y2: N/A | Z2: N/A | AA2: Not Yet
A3: TU-2022-0002 | B3: Brian Mwangi | C3: Male | D3: 2002-07-22 | E3: b.mwangi@templumis.ac | F3: +254712345002 | G3: BA | H3: Economics | I3: School of Business | J3: Year 2 | K3: 3.12 | L3: 64 | M3: Active | N3: Kenyan | O3: 2022-09-05 | P3: 2026-06-30 | Q3: Undergraduate | R3: BA | S3: 2. Progressing — Year 2 | T3: Sem 4 | U3: Paid | V3: 0 | W3: Good Standing | X3: 2024-01-15 | Y3: N/A | Z3: N/A | AA3: Not Yet
A4: TU-2020-0003 | B4: Claire Nakato | C4: Female | D4: 2000-11-05 | E4: c.nakato@templumis.ac | F4: +256712345003 | G4: BSc | H4: Civil Engineering | I4: School of Engineering | J4: Year 4 | K4: 3.55 | L4: 128 | M4: Active | N4: Ugandan | O4: 2020-09-07 | P4: 2024-06-30 | Q4: Undergraduate | R4: BSc | S4: 4. Final Year — Pre-Clearance | T4: Sem 8 | U4: Paid | V4: 0 | W4: Good Standing | X4: 2024-01-15 | Y4: N/A | Z4: N/A | AA4: In Progress
A5: TU-2019-0004 | B5: David Mensah | C5: Male | D5: 1999-04-18 | E5: d.mensah@templumis.ac | F5: +233712345004 | G5: BSc | H5: Nursing | I5: School of Health Sciences | J5: Year 4 | K5: 3.9 | L5: 132 | M5: Graduated | N5: Ghanaian | O5: 2019-09-02 | Q5: Undergraduate | R5: BSc | S5: 6. Graduated ✓ | T5: Completed | U5: Cleared | V5: 0 | W5: Cleared | X5: 2024-01-15 | Y5: N/A | Z5: N/A | AA5: Approved | AB5: 2023-11-10
A6: TU-2023-0005 | B6: Esther Wanjiku | C6: Female | D6: 2003-09-30 | E6: e.wanjiku@templumis.ac | F6: +254712345005 | G6: BSc | H6: Mathematics | I6: School of Science | J6: Year 1 | K6: 2.45 | L6: 32 | M6: Probation | N6: Kenyan | O6: 2023-09-04 | P6: 2027-06-30 | Q6: Undergraduate | R6: BSc | S6: ⚠ Academic Review — Probation | T6: Sem 2 | U6: Partial | V6: 35000 | W6: Probation | X6: 2023-12-01 | Y6: N/A | Z6: N/A | AA6: Blocked
A7: TU-2021-0006 | B7: Felix Otieno | C7: Male | D7: 2001-01-14 | E7: f.otieno@templumis.ac | F7: +254712345006 | G7: BEd | H7: Education | I7: School of Education | J7: Year 3 | K7: 3.22 | L7: 98 | M7: Active | N7: Kenyan | O7: 2021-09-05 | P7: 2025-06-30 | Q7: Undergraduate | R7: BEd | S7: 3. Progressing — Year 3 | T7: Sem 6 | U7: Paid | V7: 0 | W7: Good Standing | X7: 2024-01-15 | Y7: N/A | Z7: N/A | AA7: Not Yet
A8: TU-2022-0007 | B8: Grace Auma | C8: Female | D8: 2002-06-08 | E8: g.auma@templumis.ac | F8: +254712345007 | G8: BSc | H8: Biochemistry | I8: School of Science | J8: Year 2 | K8: 3.68 | L8: 66 | M8: Active | N8: Kenyan | O8: 2022-09-06 | P8: 2026-06-30 | Q8: Undergraduate | R8: BSc | S8: 2. Progressing — Year 2 | T8: Sem 4 | U8: Paid | V8: 0 | W8: Good Standing | X8: 2024-01-15 | Y8: N/A | Z8: N/A | AA8: Not Yet
A9: TU-2020-0008 | B9: Hassan Abdi | C9: Male | D9: 2000-12-20 | E9: h.abdi@templumis.ac | F9: +252712345008 | G9: LLB | H9: Law | I9: School of Law | J9: Year 4 | K9: 3.1 | L9: 120 | M9: Active | N9: Somali | O9: 2020-09-07 | P9: 2024-06-30 | Q9: Undergraduate | R9: LLB | S9: 4. Final Year — Pre-Clearance | T9: Sem 8 | U9: Paid | V9: 0 | W9: Good Standing | X9: 2024-01-15 | Y9: N/A | Z9: N/A | AA9: In Progress
A10: TU-2021-0009 | B10: Ivy Njeri | C10: Female | D10: 2001-08-03 | E10: i.njeri@templumis.ac | F10: +254712345009 | G10: BComm | H10: Accounting | I10: School of Business | J10: Year 3 | K10: 2.8 | L10: 90 | M10: On Leave | N10: Kenyan | O10: 2021-09-05 | P10: 2025-06-30 | Q10: Undergraduate | R10: BComm | S10: ⏸ Deferred — On Leave | T10: Sem 6 | U10: Deferred | V10: 0 | W10: Good Standing | X10: 2024-01-15 | Y10: N/A | Z10: N/A | AA10: Not Yet
A11: TU-2023-0010 | B11: James Kibaki | C11: Male | D11: 2003-02-25 | E11: j.kibaki@templumis.ac | F11: +254712345010 | G11: BSc | H11: Information Technology | I11: School of Computing | J11: Year 1 | K11: 3.4 | L11: 30 | M11: Active | N11: Kenyan | O11: 2023-09-04 | P11: 2027-06-30 | Q11: Undergraduate | R11: BSc | S11: 1. Enrolled & Orientated | T11: Sem 2 | U11: Paid | V11: 0 | W11: Good Standing | X11: 2024-01-15 | Y11: N/A | Z11: N/A | AA11: Not Yet
A12: TU-2022-0011 | B12: Kezia Moraa | C12: Female | D12: 2002-10-11 | E12: k.moraa@templumis.ac | F12: +254712345011 | G12: BSc | H12: Environmental Science | I12: School of Science | J12: Year 2 | K12: 3.05 | L12: 60 | M12: Active | N12: Kenyan | O12: 2022-09-06 | P12: 2026-06-30 | Q12: Undergraduate | R12: BSc | S12: 2. Progressing — Year 2 | T12: Sem 4 | U12: Paid | V12: 0 | W12: Good Standing | X12: 2024-01-15 | Y12: N/A | Z12: N/A | AA12: Not Yet
A13: TU-2019-0012 | B13: Liam Okonkwo | C13: Male | D13: 1999-05-17 | E13: l.okonkwo@templumis.ac | F13: +234712345012 | G13: BSc | H13: Electrical Engineering | I13: School of Engineering | J13: Year 4 | K13: 2.6 | L13: 124 | M13: Graduated | N13: Nigerian | O13: 2019-09-02 | Q13: Undergraduate | R13: BSc | S13: 6. Graduated ✓ | T13: Completed | U13: Cleared | V13: 0 | W13: Cleared | X13: 2024-01-15 | Y13: N/A | Z13: N/A | AA13: Approved | AB13: 2023-11-10
A14: TU-2021-0013 | B14: Mary Adhiambo | C14: Female | D14: 2001-07-29 | E14: m.adhiambo@templumis.ac | F14: +254712345013 | G14: BA | H14: Sociology | I14: School of Social Sciences | J14: Year 3 | K14: 3.5 | L14: 94 | M14: Active | N14: Kenyan | O14: 2021-09-05 | P14: 2025-06-30 | Q14: Undergraduate | R14: BA | S14: 3. Progressing — Year 3 | T14: Sem 6 | U14: Paid | V14: 0 | W14: Good Standing | X14: 2024-01-15 | Y14: N/A | Z14: N/A | AA14: Not Yet
A15: TU-2020-0014 | B15: Noel Kiprotich | C15: Male | D15: 2000-03-06 | E15: n.kiprotich@templumis.ac | F15: +254712345014 | G15: BPharm | H15: Pharmacy | I15: School of Health Sciences | J15: Year 4 | K15: 1.9 | L15: 112 | M15: Suspended | N15: Kenyan | O15: 2020-09-07 | P15: 2024-06-30 | Q15: Undergraduate | R15: BPharm | S15: ⚠ Academic Hold — Suspended | T15: Sem 8 | U15: Overdue | V15: 75000 | W15: Suspended | X15: 2023-12-01 | Y15: N/A | Z15: N/A | AA15: Blocked
A16: TU-2023-0015 | B16: Olivia Achieng | C16: Female | D16: 2003-11-15 | E16: o.achieng@templumis.ac | F16: +254712345015 | G16: BA | H16: Communication | I16: School of Arts | J16: Year 1 | K16: 3.82 | L16: 34 | M16: Active | N16: Kenyan | O16: 2023-09-04 | P16: 2027-06-30 | Q16: Undergraduate | R16: BA | S16: 1. Enrolled & Orientated | T16: Sem 2 | U16: Paid | V16: 0 | W16: Good Standing | X16: 2024-01-15 | Y16: N/A | Z16: N/A | AA16: Not Yet
A17: TU-2022-0016 | B17: Patrick Owino | C17: Male | D17: 2002-04-02 | E17: p.owino@templumis.ac | F17: +254712345016 | G17: BSc | H17: Statistics | I17: School of Science | J17: Year 2 | K17: 2.95 | L17: 58 | M17: Active | N17: Kenyan | O17: 2022-09-06 | P17: 2026-06-30 | Q17: Undergraduate | R17: BSc | S17: 2. Progressing — Year 2 | T17: Sem 4 | U17: Paid | V17: 0 | W17: Good Standing | X17: 2024-01-15 | Y17: N/A | Z17: N/A | AA17: Not Yet
A18: TU-2021-0017 | B18: Queenie Mugo | C18: Female | D18: 2001-09-19 | E18: q.mugo@templumis.ac | F18: +254712345017 | G18: BSc | H18: Computer Science | I18: School of Computing | J18: Year 3 | K18: 3.95 | L18: 100 | M18: Active | N18: Kenyan | O18: 2021-09-05 | P18: 2025-06-30 | Q18: Undergraduate | R18: BSc | S18: 3. Progressing — Year 3 | T18: Sem 6 | U18: Paid | V18: 0 | W18: Good Standing | X18: 2024-01-15 | Y18: N/A | Z18: N/A | AA18: Not Yet
A19: TU-2020-0018 | B19: Robert Dlamini | C19: Male | D19: 2000-06-23 | E19: r.dlamini@templumis.ac | F19: +268712345018 | G19: BEd | H19: Science Education | I19: School of Education | J19: Year 4 | K19: 3.3 | L19: 118 | M19: Active | N19: Swazi | O19: 2020-09-07 | P19: 2024-06-30 | Q19: Undergraduate | R19: BEd | S19: 4. Final Year — Pre-Clearance | T19: Sem 8 | U19: Paid | V19: 0 | W19: Good Standing | X19: 2024-01-15 | Y19: N/A | Z19: N/A | AA19: In Progress
A20: TU-2023-0019 | B20: Sandra Chebet | C20: Female | D20: 2003-01-08 | E20: s.chebet@templumis.ac | F20: +254712345019 | G20: BSc | H20: Nutrition | I20: School of Health Sciences | J20: Year 1 | K20: 3.15 | L20: 28 | M20: Active | N20: Kenyan | O20: 2023-09-04 | P20: 2027-06-30 | Q20: Undergraduate | R20: BSc | S20: 1. Enrolled & Orientated | T20: Sem 2 | U20: Paid | V20: 0 | W20: Good Standing | X20: 2024-01-15 | Y20: N/A | Z20: N/A | AA20: Not Yet
A21: TU-2022-0020 | B21: Tunde Adeyemi | C21: Male | D21: 2002-08-14 | E21: t.adeyemi@templumis.ac | F21: +234712345020 | G21: LLB | H21: Law | I21: School of Law | J21: Year 2 | K21: 3.6 | L21: 62 | M21: Active | N21: Nigerian | O21: 2022-09-06 | P21: 2026-06-30 | Q21: Undergraduate | R21: LLB | S21: 2. Progressing — Year 2 | T21: Sem 4 | U21: Paid | V21: 0 | W21: Good Standing | X21: 2024-01-15 | Y21: N/A | Z21: N/A | AA21: Not Yet
A22: TU-2021-0021 | B22: Uchenna Eze | C22: Male | D22: 2001-12-01 | E22: u.eze@templumis.ac | F22: +234712345021 | G22: BA | H22: Political Science | I22: School of Social Sciences | J22: Year 3 | K22: 2.75 | L22: 88 | M22: On Leave | N22: Nigerian | O22: 2021-09-05 | P22: 2025-06-30 | Q22: Undergraduate | R22: BA | S22: ⏸ Deferred — On Leave | T22: Sem 6 | U22: Deferred | V22: 0 | W22: Good Standing | X22: 2024-01-15 | Y22: N/A | Z22: N/A | AA22: Not Yet
A23: TU-2019-0022 | B23: Vivian Kamau | C23: Female | D23: 1999-07-27 | E23: v.kamau@templumis.ac | F23: +254712345022 | G23: BSc | H23: Biochemistry | I23: School of Science | J23: Year 4 | K23: 3.88 | L23: 134 | M23: Graduated | N23: Kenyan | O23: 2019-09-02 | Q23: Undergraduate | R23: BSc | S23: 6. Graduated ✓ | T23: Completed | U23: Cleared | V23: 0 | W23: Cleared | X23: 2024-01-15 | Y23: N/A | Z23: N/A | AA23: Approved | AB23: 2023-11-10
A24: TU-2023-0023 | B24: William Barasa | C24: Male | D24: 2003-05-10 | E24: w.barasa@templumis.ac | F24: +254712345023 | G24: BComm | H24: Finance | I24: School of Business | J24: Year 1 | K24: 2.2 | L24: 26 | M24: Probation | N24: Kenyan | O24: 2023-09-04 | P24: 2027-06-30 | Q24: Undergraduate | R24: BComm | S24: ⚠ Academic Review — Probation | T24: Sem 2 | U24: Partial | V24: 35000 | W24: Probation | X24: 2023-12-01 | Y24: N/A | Z24: N/A | AA24: Blocked
A25: TU-2022-0024 | B25: Xena Mutua | C25: Female | D25: 2002-02-18 | E25: x.mutua@templumis.ac | F25: +254712345024 | G25: BSc | H25: Information Technology | I25: School of Computing | J25: Year 2 | K25: 3.42 | L25: 68 | M25: Active | N25: Kenyan | O25: 2022-09-06 | P25: 2026-06-30 | Q25: Undergraduate | R25: BSc | S25: 2. Progressing — Year 2 | T25: Sem 4 | U25: Paid | V25: 0 | W25: Good Standing | X25: 2024-01-15 | Y25: N/A | Z25: N/A | AA25: Not Yet
A26: TU-2023-0025 | B26: Stephen Gaita Gaikia | C26: Male | D26: 2003-06-17 | E26: s.gaikia@templumis.ac | F26: +254712345025 | G26: BSc | H26: Computer Science | I26: School of Computing | J26: Year 1 | K26: 3.65 | L26: 32 | M26: Active | N26: Kenyan | O26: 2023-09-04 | P26: 2027-06-30 | Q26: Undergraduate | R26: BSc | S26: 1. Enrolled & Orientated | T26: Sem 2 | U26: Paid | V26: 0 | W26: Good Standing | X26: 2024-01-15 | Y26: N/A | Z26: N/A | AA26: Not Yet
A27: TU-PG-2022-0026 | B27: Amara Diallo | C27: Female | D27: 1996-03-15 | E27: a.diallo@templumis.ac | F27: +221712345026 | G27: MSc | H27: Data Science | I27: School of Computing | J27: Year 2 | K27: 3.72 | L27: 48 | M27: Active | N27: Senegalese | O27: 2022-09-05 | P27: 2024-06-30 | Q27: Postgraduate | R27: MSc (Coursework) | S27: 3. PG Final Semester — Pre-Graduation | T27: Sem 4 | U27: Paid | V27: 0 | W27: Good Standing | X27: 2024-01-15 | Y27: N/A | Z27: N/A | AA27: In Progress
A28: TU-PG-2023-0027 | B28: Benjamin Kamto | C28: Male | D28: 1994-07-22 | E28: b.kamto@templumis.ac | F28: +237712345027 | G28: MBA | H28: Business Administration | I28: School of Business | J28: Year 1 | K28: 3.41 | L28: 24 | M28: Active | N28: Cameroonian | O28: 2023-09-04 | P28: 2025-06-30 | Q28: Postgraduate | R28: MBA (Coursework) | S28: 1. PG Enrolled — Coursework Phase | T28: Sem 2 | U28: Paid | V28: 0 | W28: Good Standing | X28: 2024-01-15 | Y28: N/A | Z28: N/A | AA28: Not Yet
A29: TU-PG-2022-0028 | B29: Celestine Awino | C29: Female | D29: 1995-11-05 | E29: c.awino@templumis.ac | F29: +254712345028 | G29: MA | H29: Economics | I29: School of Business | J29: Year 2 | K29: 3.55 | L29: 52 | M29: Graduated | N29: Kenyan | O29: 2022-09-05 | Q29: Postgraduate | R29: MA (Coursework) | S29: 4. Graduated ✓ | T29: Completed | U29: Cleared | V29: 0 | W29: Cleared | X29: 2023-11-01 | Y29: N/A | Z29: N/A | AA29: Approved | AB29: 2023-11-10
A30: TU-PG-2023-0029 | B30: Derrick Ssempa | C30: Male | D30: 1997-04-18 | E30: d.ssempa@templumis.ac | F30: +256712345029 | G30: MSc | H30: Environmental Science | I30: School of Science | J30: Year 1 | K30: 2.81 | L30: 20 | M30: Probation | N30: Ugandan | O30: 2023-09-04 | P30: 2025-06-30 | Q30: Postgraduate | R30: MSc (Coursework) | S30: ⚠ Academic Review — Probation | T30: Sem 2 | U30: Partial | V30: 35000 | W30: Probation | X30: 2023-12-01 | Y30: N/A | Z30: N/A | AA30: Blocked
A31: TU-PG-2022-0030 | B31: Faith Onyango | C31: Female | D31: 1996-09-30 | E31: f.onyango@templumis.ac | F31: +254712345030 | G31: MA | H31: Communication | I31: School of Arts | J31: Year 2 | K31: 3.65 | L31: 46 | M31: Active | N31: Kenyan | O31: 2022-09-05 | P31: 2024-06-30 | Q31: Postgraduate | R31: MA (Coursework) | S31: 3. PG Final Semester — Pre-Graduation | T31: Sem 4 | U31: Paid | V31: 0 | W31: Good Standing | X31: 2024-01-15 | Y31: N/A | Z31: N/A | AA31: In Progress
A32: TU-PG-2023-0031 | B32: George Nkosi | C32: Male | D32: 1993-02-14 | E32: g.nkosi@templumis.ac | F32: +27712345031 | G32: MBA | H32: Strategic Management | I32: School of Business | J32: Year 1 | K32: 3.22 | L32: 24 | M32: Active | N32: South African | O32: 2023-09-04 | P32: 2025-06-30 | Q32: Postgraduate | R32: MBA (Coursework) | S32: 1. PG Enrolled — Coursework Phase | T32: Sem 2 | U32: Paid | V32: 0 | W32: Good Standing | X32: 2024-01-15 | Y32: N/A | Z32: N/A | AA32: Not Yet
A33: TU-PG-2021-0032 | B33: Helen Mutuku | C33: Female | D33: 1995-07-03 | E33: h.mutuku@templumis.ac | F33: +254712345032 | G33: MSc by Research | H33: Biochemistry | I33: School of Science | J33: Year 3 | K33: 3.82 | L33: 36 | M33: Active | N33: Kenyan | O33: 2021-09-06 | P33: 2024-06-30 | Q33: Postgraduate | R33: MSc by Research | S33: 4. Thesis Writing Phase | T33: Research Year 3 | U33: Paid | V33: 0 | W33: Good Standing | X33: 2024-01-15 | Y33: Novel Enzyme Inhibitors in Malaria Parasite Metabolism | Z33: Writing | AA33: Not Yet
A34: TU-PG-2022-0033 | B34: Ibrahim Hassan | C34: Male | D34: 1996-12-20 | E34: i.hassan@templumis.ac | F34: +251712345033 | G34: MSc by Research | H34: Computer Science | I34: School of Computing | J34: Year 2 | K34: 3.61 | L34: 24 | M34: Active | N34: Ethiopian | O34: 2022-09-05 | P34: 2025-06-30 | Q34: Postgraduate | R34: MSc by Research | S34: 3. Data Collection & Analysis Phase | T34: Research Year 2 | U34: Paid | V34: 0 | W34: Good Standing | X34: 2024-01-15 | Y34: AI-Based Crop Disease Detection Using UAV Imagery | Z34: Data Collection | AA34: Not Yet
A35: TU-PG-2021-0034 | B35: Janet Akinyi | C35: Female | D35: 1994-08-11 | E35: j.akinyi@templumis.ac | F35: +254712345034 | G35: MA by Research | H35: Education | I35: School of Education | J35: Year 3 | K35: 3.48 | L35: 36 | M35: Active | N35: Kenyan | O35: 2021-09-06 | P35: 2024-06-30 | Q35: Postgraduate | R35: MA by Research | S35: 4. Thesis Writing Phase | T35: Research Year 3 | U35: Paid | V35: 0 | W35: Good Standing | X35: 2024-01-15 | Y35: Digital Pedagogy & Learning Outcomes in Kenyan Secondary Schools | Z35: Writing | AA35: Not Yet
A36: TU-PG-2022-0035 | B36: Kenneth Osei | C36: Male | D36: 1995-05-17 | E36: k.osei@templumis.ac | F36: +233712345035 | G36: MSc by Research | H36: Mechanical Engineering | I36: School of Engineering | J36: Year 2 | K36: 3.31 | L36: 18 | M36: On Leave | N36: Ghanaian | O36: 2022-09-05 | P36: 2026-06-30 | Q36: Postgraduate | R36: MSc by Research | S36: ⏸ Deferred — On Leave (Research) | T36: Research Year 2 | U36: Deferred | V36: 0 | W36: Good Standing | X36: 2024-01-15 | Y36: Low-Cost Solar Desalination for Rural East Africa | Z36: Proposal Approved | AA36: Not Yet
A37: TU-PG-2020-0036 | B37: Lydia Cheptoo | C37: Female | D37: 1993-06-23 | E37: l.cheptoo@templumis.ac | F37: +254712345036 | G37: MSc by Research | H37: Public Health | I37: School of Health Sciences | J37: Year 4 | K37: 3.91 | L37: 48 | M37: Graduated | N37: Kenyan | O37: 2020-09-07 | Q37: Postgraduate | R37: MSc by Research | S37: 6. Graduated ✓ (Research) | T37: Completed | U37: Cleared | V37: 0 | W37: Cleared | X37: 2023-11-01 | Y37: Community-Based Interventions for Maternal Health in Western Kenya | Z37: Defended & Approved | AA37: Approved | AB37: 2023-11-10
A38: TU-PG-2023-0037 | B38: Moses Waweru | C38: Male | D38: 1997-01-08 | E38: m.waweru@templumis.ac | F38: +254712345037 | G38: MSc by Research | H38: Computer Science | I38: School of Computing | J38: Year 1 | K38: 3.52 | L38: 12 | M38: Active | N38: Kenyan | O38: 2023-09-04 | P38: 2026-06-30 | Q38: Postgraduate | R38: MSc by Research | S38: 2. Research Proposal Phase | T38: Research Year 1 | U38: Paid | V38: 0 | W38: Good Standing | X38: 2024-01-15 | Y38: Machine Learning for Swahili NLP Applications | Z38: Proposal Submitted | AA38: Not Yet

Sheet Courses
A1: course_code | B1: title | C1: department | D1: instructor | E1: credits | F1: enrolled_count | G1: type | H1: schedule | I1: room | J1: status
A2: CS301 | B2: Data Structures & Algorithms | C2: School of Computing | D2: Dr. Kamande Njoroge | E2: 4 | F2: 18 | G2: Core | H2: Mon/Wed 8–10am | I2: LH-201 | J2: Active
A3: CS201 | B3: Object-Oriented Programming | C3: School of Computing | D3: Dr. Kamande Njoroge | E3: 3 | F3: 22 | G3: Core | H3: Tue/Thu 10–12pm | I3: LH-202 | J3: Active
A4: ECO201 | B4: Microeconomics | C4: School of Business | D4: Prof. Wambua Simiyu | E4: 3 | F4: 35 | G4: Core | H4: Mon/Wed 2–4pm | I4: BH-101 | J4: Active
A5: ACC301 | B5: Intermediate Accounting | C5: School of Business | D5: Ms. Ruth Kariuki | E5: 4 | F5: 28 | G5: Core | H5: Tue/Thu 8–10am | I5: BH-102 | J5: Active
A6: CE401 | B6: Structural Engineering | C6: School of Engineering | D6: Dr. Oloo Otiende | E6: 4 | F6: 15 | G6: Core | H6: Mon 8–12pm | I6: EH-301 | J6: Active
A7: EE401 | B7: Power Systems | C7: School of Engineering | D7: Prof. James Mwema | E7: 4 | F7: 12 | G7: Core | H7: Wed 8–12pm | I7: EH-302 | J7: Active
A8: LAW301 | B8: Contract Law | C8: School of Law | D8: Prof. Adhiambo Orengo | E8: 4 | F8: 20 | G8: Core | H8: Tue/Thu 2–4pm | I8: LW-101 | J8: Active
A9: BCH201 | B9: Biochemistry I | C9: School of Science | D9: Dr. Mwangi Kiarie | E9: 3 | F9: 24 | G9: Core | H9: Mon/Wed 10–12pm | I9: SC-201 | J9: Active
A10: NUR301 | B10: Clinical Nursing Practice | C10: School of Health Sciences | D10: Dr. Atieno Ouma | E10: 5 | F10: 18 | G10: Core | H10: Fri 8am–2pm | I10: HS-401 | J10: Active
A11: EDU201 | B11: Curriculum Development | C11: School of Education | D11: Mr. Barasa Wekesa | E11: 3 | F11: 20 | G11: Core | H11: Tue/Thu 12–2pm | I11: ED-101 | J11: Active
A12: SOC201 | B12: Sociological Theory | C12: School of Social Sciences | D12: Dr. Zawadi Amani | E12: 3 | F12: 26 | G12: Core | H12: Mon/Wed 12–2pm | I12: SS-101 | J12: Active
A13: COM101 | B13: Introduction to Mass Media | C13: School of Arts | D13: Ms. Abigael Ndungu | E13: 3 | F13: 30 | G13: Core | H13: Mon/Wed 4–6pm | I13: AR-101 | J13: Active
... A21: GEN101 | B21: Communication Skills | C21: School of Arts | D21: Ms. Abigael Ndungu | E21: 2 | F21: 80 | G21: Core | H21: Fri 2–4pm | I21: AR-201 | J21: Active

Sheet Enrolments
A1: enrolment_id | B1: student_id | C1: student_name | D1: course_code | E1: course_title | F1: enrol_date | G1: status | H1: midterm_score | I1: current_grade
A2: ENR-0001 | B2: TU-2021-0001 | C2: Amelia Odhiambo | D2: CS301 | E2: Data Structures & Algorithms | F2: 2023-09-05 | G2: Enrolled | H2: 82 | I2: 85
A3: ENR-0002 | B3: TU-2021-0001 | C3: Amelia Odhiambo | D3: CS201 | E3: Object-Oriented Programming | F3: 2023-09-05 | G3: Enrolled | H3: 88 | I3: 87
A4: ENR-0003 | B4: TU-2021-0001 | C4: Amelia Odhiambo | D4: MATH201 | E4: Calculus II | F4: 2023-09-05 | G4: Enrolled | H4: 75 | I4: 78
A5: ENR-0004 | B5: TU-2021-0001 | C5: Amelia Odhiambo | D5: GEN101 | E5: Communication Skills | F5: 2023-09-05 | G5: Enrolled | H5: 90 | I5: 91
A6: ENR-0005 | B6: TU-2022-0002 | C6: Brian Mwangi | D6: ECO201 | E6: Microeconomics | F6: 2023-09-05 | G6: Enrolled | H6: 72 | I6: 74
A7: ENR-0006 | B7: TU-2022-0002 | C7: Brian Mwangi | D7: FIN201 | E7: Principles of Finance | F7: 2023-09-05 | G7: Enrolled | H7: 68 | I7: 70
A8: ENR-0007 | B8: TU-2022-0002 | C8: Brian Mwangi | D8: MATH201 | E8: Calculus II | F8: 2023-09-05 | G8: Enrolled | H8: 65 | I8: 67
A9: ENR-0008 | B9: TU-2022-0002 | C9: Brian Mwangi | D9: GEN101 | E9: Communication Skills | F9: 2023-09-05 | G9: Enrolled | H9: 78 | I9: 77
A10: ENR-0009 | B10: TU-2020-0003 | C10: Claire Nakato | D10: CE401 | E10: Structural Engineering | F10: 2023-09-07 | G10: Enrolled | H10: 80 | I10: 82
A11: ENR-0010 | B11: TU-2020-0003 | C11: Claire Nakato | D11: MATH201 | E11: Calculus II | F11: 2023-09-07 | G11: Enrolled | H11: 76 | I11: 78
A12: ENR-0011 | B12: TU-2020-0003 | C12: Claire Nakato | D12: ENV201 | E12: Environmental Ecology | F12: 2023-09-07 | G12: Enrolled | H12: 83 | I12: 84
A13: ENR-0012 | B13: TU-2020-0003 | C13: Claire Nakato | D13: GEN101 | E13: Communication Skills | F13: 2023-09-07 | G13: Enrolled | H13: 88 | I13: 89
... A82: ENR-0081 | B82: TU-2023-0025 | C82: Stephen Gaita Gaikia | D82: GEN101 | E82: Communication Skills | F82: 2023-09-04 | G82: Enrolled | H82: 87 | I82: 88

Sheet Grades
A1: grade_id | B1: student_id | C1: student_name | D1: course_code | E1: assignment_1 | F1: assignment_2 | G1: midterm | H1: final | I1: total | J1: letter_grade
A2: GRD-0001 | B2: TU-2021-0001 | C2: Amelia Odhiambo | D2: CS301 | E2: 85 | F2: 88 | G2: 82 | J2: B
A3: GRD-0002 | B3: TU-2021-0001 | C3: Amelia Odhiambo | D3: CS201 | E3: 90 | F3: 87 | G3: 88 | J3: B
A4: GRD-0003 | B4: TU-2021-0001 | C4: Amelia Odhiambo | D4: MATH201 | E4: 78 | F4: 80 | G4: 75 | J4: B
A5: GRD-0004 | B5: TU-2021-0001 | C5: Amelia Odhiambo | D5: GEN101 | E5: 92 | F5: 91 | G5: 90 | J5: A
A6: GRD-0005 | B6: TU-2019-0004 | C6: David Mensah | D6: NUR301 | E6: 94 | F6: 93 | G6: 91 | H6: 95 | I6: 93 | J6: A
A7: GRD-0006 | B7: TU-2019-0004 | C7: David Mensah | D7: BCH201 | E7: 91 | F7: 90 | G7: 88 | H7: 91 | I7: 90 | J7: A
A8: GRD-0007 | B8: TU-2023-0005 | C8: Esther Wanjiku | D8: MATH201 | E8: 52 | F8: 55 | G8: 48 | J8: D
A9: GRD-0008 | B9: TU-2021-0017 | C9: Queenie Mugo | D9: CS301 | E9: 97 | F9: 96 | G9: 95 | J9: A
A10: GRD-0009 | B10: TU-2020-0014 | C10: Noel Kiprotich | D10: BCH201 | E10: 48 | F10: 46 | G10: 45 | J10: F
A11: GRD-0010 | B11: TU-2022-0020 | C11: Tunde Adeyemi | D11: LAW301 | E11: 86 | F11: 85 | G11: 84 | J11: B
A12: GRD-0011 | B12: TU-2023-0015 | C12: Olivia Achieng | D12: COM101 | E12: 91 | F12: 90 | G12: 89 | J12: A
A13: GRD-0012 | B13: TU-2019-0022 | C13: Vivian Kamau | D13: BCH201 | E13: 93 | F13: 92 | G13: 90 | H13: 94 | I13: 93 | J13: A
A14: GRD-0013 | B14: TU-2023-0025 | C14: Stephen Gaita Gaikia | D14: CS101 | E14: 88 | F14: 85 | G14: 84 | J14: B
A15: GRD-0014 | B15: TU-2023-0025 | C15: Stephen Gaita Gaikia | D15: IT201 | E15: 80 | F15: 79 | G15: 78 | J15: B
A16: GRD-0015 | B16: TU-2023-0025 | C16: Stephen Gaita Gaikia | D16: MATH201 | E16: 83 | F16: 82 | G16: 81 | J16: B
A17: GRD-0016 | B17: TU-2023-0025 | C17: Stephen Gaita Gaikia | D17: GEN101 | E17: 89 | F17: 88 | G17: 87 | J17: B

Sheet Attendance
A1: attendance_id | B1: student_id | C1: student_name | D1: course_code | E1: course_title | F1: total_sessions | G1: present | H1: absent | I1: late | J1: attendance_pct | K1: risk_level
A2: ATT-0001 | B2: TU-2021-0001 | C2: Amelia Odhiambo | D2: CS301 | E2: Data Structures & Algorithms | F2: 28 | G2: 26 | H2: 2 | I2: 1 | J2: =ROUND(G2/F2*100,0) | K2: Good
A3: ATT-0002 | B3: TU-2021-0001 | C3: Amelia Odhiambo | D3: CS201 | E3: Object-Oriented Programming | F3: 26 | G3: 25 | H3: 1 | I3: 2 | J3: =ROUND(G3/F3*100,0) | K3: Good
A4: ATT-0003 | B4: TU-2023-0005 | C4: Esther Wanjiku | D4: MATH201 | E4: Calculus II | F4: 30 | G4: 17 | H4: 13 | I4: 3 | J4: =ROUND(G4/F4*100,0) | K4: At Risk
A5: ATT-0004 | B5: TU-2020-0014 | C5: Noel Kiprotich | D5: BCH201 | E5: Biochemistry I | F5: 26 | G5: 14 | H5: 12 | I5: 2 | J5: =ROUND(G5/F5*100,0) | K5: At Risk
A6: ATT-0005 | B6: TU-2021-0017 | C6: Queenie Mugo | D6: CS301 | E6: Data Structures & Algorithms | F6: 28 | G6: 28 | H6: 0 | I6: 0 | J6: =ROUND(G6/F6*100,0) | K6: Good
A7: ATT-0006 | B7: TU-2022-0002 | C7: Brian Mwangi | D7: ECO201 | E7: Microeconomics | F7: 26 | G7: 21 | H7: 5 | I7: 2 | J7: =ROUND(G7/F7*100,0) | K7: Good
A8: ATT-0007 | B8: TU-2023-0023 | C8: William Barasa | D8: FIN201 | E8: Principles of Finance | F8: 26 | G8: 16 | H8: 10 | I8: 3 | J8: =ROUND(G8/F8*100,0) | K8: Warning
A9: ATT-0008 | B9: TU-2023-0015 | C9: Olivia Achieng | D9: COM101 | E9: Introduction to Mass Media | F9: 24 | G9: 24 | H9: 0 | I9: 1 | J9: =ROUND(G9/F9*100,0) | K9: Good
A10: ATT-0009 | B10: TU-2020-0008 | C10: Hassan Abdi | D10: LAW301 | E10: Contract Law | F10: 26 | G10: 22 | H10: 4 | I10: 1 | J10: =ROUND(G10/F10*100,0) | K10: Good
A11: ATT-0010 | B11: TU-2021-0009 | C11: Ivy Njeri | D11: ACC301 | E11: Intermediate Accounting | F11: 26 | G11: 16 | H11: 10 | I11: 2 | J11: =ROUND(G11/F11*100,0) | K11: Warning
A12: ATT-0011 | B12: TU-2021-0021 | C12: Uchenna Eze | D12: SOC201 | E12: Sociological Theory | F12: 24 | G12: 15 | H12: 9 | I12: 2 | J12: =ROUND(G12/F12*100,0) | K12: Warning
A13: ATT-0012 | B13: TU-2022-0024 | C13: Xena Mutua | D13: IT201 | E13: Database Management Systems | F13: 24 | G13: 22 | H13: 2 | I13: 1 | J13: =ROUND(G13/F13*100,0) | K13: Good
... A17: ATT-0016 | B17: TU-2023-0025 | C17: Stephen Gaita Gaikia | D17: GEN101 | E17: Communication Skills | F17: 24 | G17: 23 | H17: 1 | I17: 0 | J17: =ROUND(G17/F17*100,0) | K17: Good

Sheet Fee Records
A1: Templumis University — Student Fee Records
A2: Academic Year 2023/24 · Semester 1 | All amounts in KES
A4: Fee Record ID | B4: Student ID | C4: Student Name | D4: Programme | E4: Department | F4: Student Type | G4: Current Semester | H4: Sem Fee (KES) | I4: Reg Fee (KES) | J4: Total Billed (KES) | K4: Amount Paid (KES) | L4: Balance (KES) | M4: Fee Status
A5: FR-0001 | B5: TU-2021-0001 | C5: Amelia Odhiambo | D5: BSc | E5: School of Computing | F5: Undergraduate | G5: Sem 6 | H5: 75000 | I5: 5000 | J5: =H5+I5 | K5: 80000 | L5: =J5-K5 | M5: Paid
A6: FR-0002 | B6: TU-2022-0002 | C6: Brian Mwangi | D6: BA | E6: School of Business | F6: Undergraduate | G6: Sem 4 | H6: 65000 | I6: 5000 | J6: =H6+I6 | K6: 70000 | L6: =J6-K6 | M6: Paid
A7: FR-0003 | B7: TU-2020-0003 | C7: Claire Nakato | D7: BSc | E7: School of Engineering | F7: Undergraduate | G7: Sem 8 | H7: 75000 | I7: 5000 | J7: =H7+I7 | K7: 80000 | L7: =J7-K7 | M7: Paid
A8: FR-0004 | B8: TU-2019-0004 | C8: David Mensah | D8: BSc | E8: School of Health Sciences | F8: Undergraduate | G8: Completed | H8: 75000 | I8: 5000 | J8: =H8+I8 | K8: 80000 | L8: =J8-K8 | M8: Paid
A9: FR-0005 | B9: TU-2023-0005 | C9: Esther Wanjiku | D9: BSc | E9: School of Science | F9: Undergraduate | G9: Sem 2 | H9: 75000 | I9: 5000 | J9: =H9+I9 | K9: 45000 | L9: =J9-K9 | M9: Partial
A10: FR-0006 | B10: TU-2021-0006 | C10: Felix Otieno | D10: BEd | E10: School of Education | F10: Undergraduate | G10: Sem 6 | H10: 60000 | I10: 5000 | J10: =H10+I10 | K10: 65000 | L10: =J10-K10 | M10: Paid
A11: FR-0007 | B11: TU-2022-0007 | C11: Grace Auma | D11: BSc | E11: School of Science | F11: Undergraduate | G11: Sem 4 | H11: 75000 | I11: 5000 | J11: =H11+I11 | K11: 80000 | L11: =J11-K11 | M11: Paid
A12: FR-0008 | B12: TU-2020-0008 | C12: Hassan Abdi | D12: LLB | E12: School of Law | F12: Undergraduate | G12: Sem 8 | H12: 70000 | I12: 5000 | J12: =H12+I12 | K12: 75000 | L12: =J12-K12 | M12: Paid
A13: FR-0009 | B13: TU-2021-0009 | C13: Ivy Njeri | D13: BComm | E13: School of Business | F13: Undergraduate | G13: Sem 6 | H13: 65000 | I13: 5000 | J13: =H13+I13 | K13: 0 | L13: =J13-K13 | M13: Deferred
A14: FR-0010 | B14: TU-2023-0010 | C14: James Kibaki | D14: BSc | E14: School of Computing | F14: Undergraduate | G14: Sem 2 | H14: 75000 | I14: 5000 | J14: =H14+I14 | K14: 80000 | L14: =J14-K14 | M14: Paid
A15: FR-0011 | B15: TU-2022-0011 | C15: Kezia Moraa | D15: BSc | E15: School of Science | F15: Undergraduate | G15: Sem 4 | H15: 75000 | I15: 5000 | J15: =H15+I15 | K15: 80000 | L15: =J15-K15 | M15: Paid
A16: FR-0012 | B16: TU-2019-0012 | C16: Liam Okonkwo | D16: BSc | E16: School of Engineering | F16: Undergraduate | G16: Completed | H16: 75000 | I16: 5000 | J16: =H16+I16 | K16: 80000 | L16: =J16-K16 | M16: Paid
... A41: FR-0037 | B41: TU-PG-2023-0037 | C41: Moses Waweru | D41: MSc by Research | E41: School of Computing | F41: Postgraduate | G41: Research Year 1 | H41: 80000 | I41: 5000 | J41: =H41+I41 | K41: 85000 | L41: =J41-K41 | M41: Paid
A42: TOTALS | H42: =SUM(H5:H41) | I42: =SUM(I5:I41) | J42: =SUM(J5:J41) | K42: =SUM(K5:K41) | L42: =SUM(L5:L41)

Sheet Payments
A1: Templumis University — Payment Transactions
A2: Academic Year 2023/24 · Semester 1 | All amounts in KES
A4: Payment ID | B4: Fee Record ID | C4: Student ID | D4: Student Name | E4: Payment Date | F4: Payment Method | G4: Reference No. | H4: Amount (KES) | I4: Payment Type | J4: Processed By | K4: Receipt No. | L4: Status
A5: PAY-0001 | B5: FR-0001 | C5: TU-2021-0001 | D5: Amelia Odhiambo | E5: 2023-09-08 | F5: M-Pesa | G5: REF529696 | H5: 80000 | I5: Tuition & Registration | J5: Bursar | K5: RCT-0001 | L5: Confirmed
A6: PAY-0002 | B6: FR-0002 | C6: TU-2022-0002 | D6: Brian Mwangi | E6: 2023-09-11 | F6: M-Pesa | G6: REF184441 | H6: 70000 | I6: Tuition & Registration | J6: Finance Office | K6: RCT-0002 | L6: Confirmed
A7: PAY-0003 | B7: FR-0003 | C7: TU-2020-0003 | D7: Claire Nakato | E7: 2023-09-04 | F7: Bank Transfer | G7: REF600208 | H7: 80000 | I7: Tuition & Registration | J7: Bursar | K7: RCT-0003 | L7: Confirmed
A8: PAY-0004 | B8: FR-0004 | C8: TU-2019-0004 | D8: David Mensah | E8: 2023-09-13 | F8: Bank Transfer | G8: REF749605 | H8: 80000 | I8: Tuition & Registration | J8: Finance Office | K8: RCT-0004 | L8: Confirmed
A9: PAY-0005 | B9: FR-0005 | C9: TU-2023-0005 | D9: Esther Wanjiku | E9: 2023-09-02 | F9: M-Pesa | G9: REF404242 | H9: 45000 | I9: Partial Tuition | J9: Finance Office | K9: RCT-0005 | L9: Confirmed
A10: PAY-0006 | B10: FR-0006 | C10: TU-2021-0006 | D10: Felix Otieno | E10: 2023-09-07 | F10: Bank Transfer | G10: REF432622 | H10: 65000 | I10: Tuition & Registration | J10: Bursar | K10: RCT-0006 | L10: Confirmed
A11: PAY-0007 | B11: FR-0007 | C11: TU-2022-0007 | D11: Grace Auma | E11: 2023-09-02 | F11: Bank Transfer | G11: REF503029 | H11: 80000 | I11: Tuition & Registration | J11: Bursar | K11: RCT-0007 | L11: Confirmed
A12: PAY-0008 | B12: FR-0008 | C12: TU-2020-0008 | D12: Hassan Abdi | E12: 2023-09-14 | F12: M-Pesa | G12: REF650659 | H12: 75000 | I12: Tuition & Registration | J12: Finance Office | K12: RCT-0008 | L12: Confirmed
A13: PAY-0009 | B13: FR-0009 | C13: TU-2021-0009 | D13: Ivy Njeri | E13: 2023-09-02 | F13: — | G13: — | H13: 0 | I13: Deferred — Leave of Absence | J13: Registrar | K13: RCT-0009 | L13: Deferred
A14: PAY-0010 | B14: FR-0010 | C14: TU-2023-0010 | D14: James Kibaki | E14: 2023-09-04 | F14: Bank Transfer | G14: REF890008 | H14: 80000 | I14: Tuition & Registration | J14: Bursar | K14: RCT-0010 | L14: Confirmed
A15: PAY-0011 | B15: FR-0011 | C15: TU-2022-0011 | D15: Kezia Moraa | E15: 2023-09-10 | F15: Bank Transfer | G15: REF723142 | H15: 80000 | I15: Tuition & Registration | J15: Bursar | K15: RCT-0011 | L15: Confirmed
A16: PAY-0012 | B16: FR-0012 | C16: TU-2019-0012 | D16: Liam Okonkwo | E16: 2023-09-11 | F16: Bank Transfer | G16: REF746509 | H16: 80000 | I16: Tuition & Registration | J16: Bursar | K16: RCT-0012 | L16: Confirmed
... A41: PAY-0037 | B41: FR-0037 | C41: TU-PG-2023-0037 | D41: Moses Waweru | E41: 2023-09-02 | F41: Bank Transfer | G41: REF361964 | H41: 85000 | I41: Tuition & Registration | J41: Finance Office | K41: RCT-0037 | L41: Confirmed
A42: TOTAL PAYMENTS RECEIVED | H42: =SUM(H5:H41)

Sheet Scholarships
A1: Templumis University — Scholarship Programmes
A2: Active & Available Scholarships · Academic Year 2023/24
A4: Scholarship ID | B4: Scholarship Name | C4: Type | D4: Criteria | E4: Value (KES) | F4: Coverage | G4: Slots Available | H4: Slots Filled | I4: Status
A5: SCH-001 | B5: Vice Chancellor's Merit Award | C5: Merit | D5: Top 5% GPA; minimum GPA 3.80 | E5: 100000 | F5: Full Tuition | G5: 5 | H5: 2 | I5: Active
A6: SCH-002 | B6: Dean's Excellence Bursary | C6: Merit | D6: GPA 3.50–3.79; Good Standing | E6: 50000 | F6: 50% Tuition | G6: 10 | H6: 4 | I6: Active
A7: SCH-003 | B7: STEM Advancement Fund | C7: Merit + Need | D7: BSc/MSc programmes; GPA ≥ 3.20 | E7: 40000 | F7: 40% Tuition | G7: 8 | H7: 3 | I7: Active
A8: SCH-004 | B8: Pan-African Diversity Grant | C8: Diversity | D8: Non-Kenyan international students | E8: 30000 | F8: Partial Tuition | G8: 15 | H8: 7 | I8: Active
A9: SCH-005 | B9: Women in Science Scholarship | C9: Equity | D9: Female students in Science/Engineering | E9: 35000 | F9: Partial Tuition | G9: 6 | H9: 2 | I9: Active
A10: SCH-006 | B10: Bursary for Needy Students | C10: Need-Based | D10: Demonstrated financial hardship; GPA ≥ 2.50 | E10: 25000 | F10: Partial Tuition | G10: 10 | H10: 3 | I10: Active
A11: SCH-007 | B11: Postgraduate Research Fellowship | C11: Research | D11: MSc/MA by Research students; supervisor endorsement | E11: 60000 | F11: Full Tuition + Stipend | G11: 4 | H11: 2 | I11: Active
A12: SCH-008 | B12: Community Leaders Award | C12: Leadership | D12: Community engagement evidence; essay required | E12: 20000 | F12: Flat Grant | G12: 5 | H12: 1 | I12: Active
A13: SCH-009 | B13: Health Sciences Sponsorship | C13: Sectoral | D13: BSc Nursing / BPharm / BSc Nutrition students | E13: 45000 | F13: 50% Tuition | G13: 4 | H13: 2 | I13: Active
A14: SCH-010 | B14: Law & Justice Fund | C14: Sectoral | D14: LLB students; moot court participation | E14: 30000 | F14: 40% Tuition | G14: 4 | H14: 1 | I14: Active

Sheet Scholarship Apps
A1: Templumis University — Scholarship Applications
A2: Academic Year 2023/24 · Semester 1 | All submitted applications
A4: Application ID | B4: Student ID | C4: Student Name | D4: Programme | E4: GPA | F4: Scholarship ID | G4: Scholarship Name | H4: Applied Date | I4: Status | J4: Award Amount (KES) | K4: Reviewed By | L4: Decision Date | M4: Notes
A5: APP-0001 | B5: TU-2021-0017 | C5: Queenie Mugo | D5: BSc | E5: 3.95 | F5: SCH-001 | G5: Vice Chancellor's Merit Award | H5: 2023-08-04 | I5: Awarded | J5: 100000 | K5: Dr. M. Kamande | L5: 2023-09-18 | M5: Highest GPA in cohort; full award granted
A6: APP-0002 | B6: TU-2021-0001 | C6: Amelia Odhiambo | D6: BSc | E6: 3.78 | F6: SCH-002 | G6: Dean's Excellence Bursary | H6: 2023-08-30 | I6: Awarded | J6: 50000 | K6: Fin. Office | L6: 2023-09-29 | M6: GPA meets criteria; good standing confirmed
A7: APP-0003 | B7: TU-2022-0007 | C7: Grace Auma | D7: BSc | E7: 3.68 | F7: SCH-002 | G7: Dean's Excellence Bursary | H7: 2023-08-11 | I7: Awarded | J7: 50000 | K7: Scholarship Cttee | L7: 2023-09-26 | M7: GPA within range; Good Standing
A8: APP-0004 | B8: TU-2019-0022 | C8: Vivian Kamau | D8: BSc | E8: 3.88 | F8: SCH-001 | G8: Vice Chancellor's Merit Award | H8: 2023-09-08 | I8: Awarded | J8: 100000 | K8: Scholarship Cttee | L8: 2023-10-09 | M8: Graduated; historical award 2022/23
A9: APP-0005 | B9: TU-2023-0015 | C9: Olivia Achieng | D9: BA | E9: 3.82 | F9: SCH-001 | G9: Vice Chancellor's Merit Award | H9: 2023-09-01 | I9: Under Review | J9: — | K9: Pending | M9: GPA qualifies; panel review pending
A10: APP-0006 | B10: TU-PG-2021-0032 | C10: Helen Mutuku | D10: MSc by Research | E10: 3.82 | F10: SCH-007 | G10: Postgraduate Research Fellowship | H10: 2023-08-05 | I10: Awarded | J10: 60000 | K10: Fin. Office | L10: 2023-10-13 | M10: Supervisor-endorsed; novel malaria research
A11: APP-0007 | B11: TU-PG-2020-0036 | C11: Lydia Cheptoo | D11: MSc by Research | E11: 3.91 | F11: SCH-007 | G11: Postgraduate Research Fellowship | H11: 2023-09-05 | I11: Awarded | J11: 60000 | K11: Scholarship Cttee | L11: 2023-10-13 | M11: Graduated; awarded 2022/23
A12: APP-0008 | B12: TU-PG-2022-0033 | C12: Ibrahim Hassan | D12: MSc by Research | E12: 3.61 | F12: SCH-007 | G12: Postgraduate Research Fellowship | H12: 2023-09-02 | I12: Under Review | J12: — | K12: Pending | M12: AI/UAV crop research — supervisor endorsed
A13: APP-0009 | B13: TU-PG-2022-0026 | C13: Amara Diallo | D13: MSc (Coursework) | E13: 3.72 | F13: SCH-004 | G13: Pan-African Diversity Grant | H13: 2023-09-08 | I13: Awarded | J13: 30000 | K13: Dr. M. Kamande | L13: 2023-09-20 | M13: Senegalese national; international criteria met
A14: APP-0010 | B14: TU-PG-2023-0027 | C14: Benjamin Kamto | D14: MBA (Coursework) | E14: 3.41 | F14: SCH-004 | G14: Pan-African Diversity Grant | H14: 2023-08-05 | I14: Awarded | J14: 30000 | K14: Scholarship Cttee | L14: 2023-10-16 | M14: Cameroonian national; criteria met
A15: APP-0011 | B15: TU-PG-2023-0031 | C15: George Nkosi | D15: MBA (Coursework) | E15: 3.22 | F15: SCH-004 | G15: Pan-African Diversity Grant | H15: 2023-08-07 | I15: Awarded | J15: 30000 | K15: Scholarship Cttee | L15: 2023-09-19 | M15: South African national; criteria met
A16: APP-0012 | B16: TU-PG-2023-0029 | C16: Derrick Ssempa | D16: MSc (Coursework) | E16: 2.81 | F16: SCH-004 | G16: Pan-African Diversity Grant | H16: 2023-09-01 | I16: Rejected | J16: — | K16: Scholarship Cttee | L16: 2023-10-13 | M16: GPA 2.81 on probation; eligibility suspended
A17: APP-0013 | B17: TU-2023-0005 | C17: Esther Wanjiku | D17: BSc | E17: 2.45 | F17: SCH-006 | G17: Bursary for Needy Students | H17: 2023-08-06 | I17: Under Review | J17: — | K17: Pending | M17: Financial hardship evidenced; GPA borderline at 2.45
A18: APP-0014 | B18: TU-2023-0023 | C18: William Barasa | D18: BComm | E18: 2.2 | F18: SCH-006 | G18: Bursary for Needy Students | H18: 2023-08-21 | I18: Rejected | J18: — | K18: Prof. W. Simiyu | L18: 2023-10-08 | M18: GPA 2.20 below minimum threshold of 2.50
A19: APP-0015 | B19: TU-2019-0004 | C19: David Mensah | D19: BSc | E19: 3.9 | F19: SCH-009 | G19: Health Sciences Sponsorship | H19: 2023-08-15 | I19: Awarded | J19: 45000 | K19: Scholarship Cttee | L19: 2023-09-20 | M19: Graduated; historical award 2022/23
A20: APP-0016 | B20: TU-2023-0019 | C20: Sandra Chebet | D20: BSc | E20: 3.15 | F20: SCH-009 | G20: Health Sciences Sponsorship | H20: 2023-08-13 | I20: Awarded | J20: 45000 | K20: Scholarship Cttee | L20: 2023-09-17 | M20: BSc Nutrition; criteria met
A21: APP-0017 | B21: TU-2020-0008 | C21: Hassan Abdi | D21: LLB | E21: 3.1 | F21: SCH-010 | G21: Law & Justice Fund | H21: 2023-08-12 | I21: Awarded | J21: 30000 | K21: Dr. M. Kamande | L21: 2023-10-15 | M21: LLB Year 4; moot court participation confirmed
A22: APP-0018 | B22: TU-2022-0020 | C22: Tunde Adeyemi | D22: LLB | E22: 3.6 | F22: SCH-010 | G22: Law & Justice Fund | H22: 2023-08-26 | I22: Under Review | J22: — | K22: Pending | M22: LLB Year 2; moot court participation pending
A23: APP-0019 | B23: TU-2022-0007 | C23: Grace Auma | D23: BSc | E23: 3.68 | F23: SCH-005 | G23: Women in Science Scholarship | H23: 2023-08-26 | I23: Awarded | J23: 35000 | K23: Prof. W. Simiyu | L23: 2023-09-22 | M23: Female BSc Science; dual award with Dean's Bursary
A24: APP-0020 | B24: TU-2019-0022 | C24: Vivian Kamau | D24: BSc | E24: 3.88 | F24: SCH-005 | G24: Women in Science Scholarship | H24: 2023-09-08 | I24: Awarded | J24: 35000 | K24: Dr. M. Kamande | L24: 2023-10-03 | M24: Graduated; historical award
A25: APP-0021 | B25: TU-2020-0003 | C25: Claire Nakato | D25: BSc | E25: 3.55 | F25: SCH-005 | G25: Women in Science Scholarship | H25: 2023-08-12 | I25: Under Review | J25: — | K25: Pending | M25: Female BSc Engineering; under panel consideration
A26: APP-0022 | B26: TU-2023-0025 | C26: Stephen Gaita Gaikia | D26: BSc | E26: 3.65 | F26: SCH-003 | G26: STEM Advancement Fund | H26: 2023-09-09 | I26: Awarded | J26: 40000 | K26: Dr. M. Kamande | L26: 2023-10-15 | M26: BSc Computing; GPA 3.65 qualifies
A27: APP-0023 | B27: TU-2022-0024 | C27: Xena Mutua | D27: BSc | E27: 3.42 | F27: SCH-003 | G27: STEM Advancement Fund | H27: 2023-08-27 | I27: Awarded | J27: 40000 | K27: Fin. Office | L27: 2023-09-29 | M27: BSc Computing; GPA 3.42 qualifies
A28: APP-0024 | B28: TU-2023-0010 | C28: James Kibaki | D28: BSc | E28: 3.4 | F28: SCH-003 | G28: STEM Advancement Fund | H28: 2023-09-01 | I28: Under Review | J28: — | K28: Pending | M28: BSc IT Year 1; GPA 3.40 borderline
A29: APP-0025 | B29: TU-2021-0013 | C29: Mary Adhiambo | D29: BA | E29: 3.5 | F29: SCH-008 | G29: Community Leaders Award | H29: 2023-09-15 | I29: Awarded | J29: 20000 | K29: Dr. A. Ouma | L29: 2023-10-07 | M29: Community outreach documented; essay strong
A30: APP-0026 | B30: TU-2021-0006 | C30: Felix Otieno | D30: BEd | E30: 3.22 | F30: SCH-008 | G30: Community Leaders Award | H30: 2023-08-25 | I30: Under Review | J30: — | K30: Pending | M30: BEd student; community teaching programme
A31: TOTAL AWARDS GRANTED | I31: Awarded: 17 | Under Review: 7 | Rejected: 2

Sheet Dashboard
A1: Templumis University — LMS & SIS Dashboard
A2: Academic Year 2023/24 · Semester 1
A4: Students | C4: Courses & Enrolments
A5: Total Students | B5: 37 | C5: Total Courses | D5: =COUNTA(Courses!A2:A1000)
A6: Active | B6: 25 | C6: Active Courses | D6: =COUNTIF(Courses!J2:J1000,"Active")
A7: On Probation | B7: 3 | C7: Total Enrolments | D7: =COUNTA(Enrolments!A2:A1000)
A8: Graduated | B8: 5 | C8: Currently Enrolled | D8: =COUNTIF(Enrolments!G2:G1000,"Enrolled")
A9: Suspended | B9: 1 | C9: Completed | D9: =COUNTIF(Enrolments!G2:G1000,"Completed")
A10: On Leave | B10: 3 | C10: Dropped | D10: =COUNTIF(Enrolments!G2:G1000,"Dropped")
A11: Average GPA | B11: 3.32 | C11: Avg Current Grade | D11: =ROUND(AVERAGE(Enrolments!I2:I1000),1)&"%"
A12: Total Credit Hours | B12: =SUM(Students!L2:L1000) | C12: Grade A Count | D12: =COUNTIF(Grades!J2:J1000,"A")
A14: ── Postgraduate Summary ── | C14: Student Lookup
A15: PG Students | B15: 12 | C15: Enter Student ID → | D15: TU-2023-0025
A16: MSc Coursework | B16: 6 | C16: Name | D16: =IFERROR(VLOOKUP(D15,Students!A:B,2,0),"-")
A17: MSc by Research | B17: 6 | C17: Program | D17: =IFERROR(VLOOKUP(D15,Students!A:H,8,0),"-")
A18: At Risk | B18: =COUNTIF(Attendance!K2:K1000,"At Risk") | C18: GPA | D18: =IFERROR(VLOOKUP(D15,Students!A:K,11,0),"-")
A19: Avg Attendance % | B19: =ROUND(AVERAGE(Attendance!J2:J1000),0)&"%" | C19: Status | D19: =IFERROR(VLOOKUP(D15,Students!A:M,13,0),"-")

Sheet Journey Tracker
A1: A. STUDENT PROFILE | G1: B. ACADEMIC PROGRESSION | L1: C. ACADEMIC STANDING | O1: D. FINANCIAL CLEARANCE | R1: E. RESEARCH / THESIS | V1: F. GRADUATION
A2: Student ID | B2: Full Name | C2: Student Type | D2: Programme Level | E2: Department | F2: Enrolment Date | G2: Current Year/Sem | H2: Sem 1 Status | I2: Sem 2 Status | J2: Year 2 Progression | K2: Year 3+ Progression | L2: GPA | M2: Academic Standing | N2: Last Review Date | O2: Fees — Sem 1 | P2: Fees — Sem 2 | Q2: Fees Balance (KES) | R2: Proposal Status | S2: Data/Coursework Phase | T2: Thesis Submission | U2: Thesis Defence | V2: Graduation Clearance | W2: Clearance Date | X2: Graduation Date | Y2: Journey Stage
A3: TU-2021-0001 | B3: Amelia Odhiambo | C3: Undergraduate | D3: BSc | E3: School of Computing | F3: 2021-09-05 | G3: Sem 6 | H3: Complete | I3: Complete | J3: Complete | K3: In Progress | L3: 3.78 | M3: Good Standing | N3: 2024-01-15 | O3: Paid | P3: Paid | Q3: 0 | R3: N/A | S3: Sem Year 3 | T3: N/A | U3: N/A | V3: Not Yet | Y3: 3. Progressing — Year 3
A4: TU-2022-0002 | B4: Brian Mwangi | C4: Undergraduate | D4: BA | E4: School of Business | F4: 2022-09-05 | G4: Sem 4 | H4: Complete | I4: Complete | J4: In Progress | K4: Pending | L4: 3.12 | M4: Good Standing | N4: 2024-01-15 | O4: Paid | P4: Paid | Q4: 0 | R4: N/A | S4: Sem Year 2 | T4: N/A | U4: N/A | V4: Not Yet | Y4: 2. Progressing — Year 2
A5: TU-2020-0003 | B5: Claire Nakato | C5: Undergraduate | D5: BSc | E5: School of Engineering | F5: 2020-09-07 | G5: Sem 8 | H5: Complete | I5: Complete | J5: Complete | K5: Complete | L5: 3.55 | M5: Good Standing | N5: 2024-01-15 | O5: Paid | P5: Paid | Q5: 0 | R5: N/A | S5: Sem Year 4 | T5: N/A | U5: N/A | V5: In Progress | Y5: 4. Final Year — Pre-Clearance
A6: TU-2019-0004 | B6: David Mensah | C6: Undergraduate | D6: BSc | E6: School of Health Sciences | F6: 2019-09-02 | G6: Completed | H6: Complete | I6: Complete | J6: Complete | K6: Complete | L6: 3.9 | M6: Cleared | N6: 2024-01-15 | O6: Paid | P6: Cleared | Q6: 0 | R6: N/A | S6: Sem Year 4 | T6: N/A | U6: N/A | V6: Approved | W6: 2024-01-15 | X6: 2023-11-10 | Y6: 6. Graduated ✓
A7: TU-2023-0005 | B7: Esther Wanjiku | C7: Undergraduate | D7: BSc | E7: School of Science | F7: 2023-09-04 | G7: Sem 2 | H7: In Progress | I7: In Progress | J7: Pending | K7: Pending | L7: 2.45 | M7: Probation | N7: 2023-12-01 | O7: Partial | P7: Partial | Q7: 35000 | R7: N/A | S7: Sem Year 1 | T7: N/A | U7: N/A | V7: Blocked | Y7: ⚠ Academic Review — Probation
A8: TU-2021-0006 | B8: Felix Otieno | C8: Undergraduate | D8: BEd | E8: School of Education | F8: 2021-09-05 | G8: Sem 6 | H8: Complete | I8: Complete | J8: Complete | K8: In Progress | L8: 3.22 | M8: Good Standing | N8: 2024-01-15 | O8: Paid | P8: Paid | Q8: 0 | R8: N/A | S8: Sem Year 3 | T8: N/A | U8: N/A | V8: Not Yet | Y8: 3. Progressing — Year 3
A9: TU-2022-0007 | B9: Grace Auma | C9: Undergraduate | D9: BSc | E9: School of Science | F9: 2022-09-06 | G9: Sem 4 | H9: Complete | I9: Complete | J9: In Progress | K9: Pending | L9: 3.68 | M9: Good Standing | N9: 2024-01-15 | O9: Paid | P9: Paid | Q9: 0 | R9: N/A | S9: Sem Year 2 | T9: N/A | U9: N/A | V9: Not Yet | Y9: 2. Progressing — Year 2
A10: TU-2020-0008 | B10: Hassan Abdi | C10: Undergraduate | D10: LLB | E10: School of Law | F10: 2020-09-07 | G10: Sem 8 | H10: Complete | I10: Complete | J10: Complete | K10: Complete | L10: 3.1 | M10: Good Standing | N10: 2024-01-15 | O10: Paid | P10: Paid | Q10: 0 | R10: N/A | S10: Sem Year 4 | T10: N/A | U10: N/A | V10: In Progress | Y10: 4. Final Year — Pre-Clearance
A11: TU-2021-0009 | B11: Ivy Njeri | C11: Undergraduate | D11: BComm | E11: School of Business | F11: 2021-09-05 | G11: Sem 6 | H11: Complete | I11: Complete | J11: Complete | K11: In Progress | L11: 2.8 | M11: Good Standing | N11: 2024-01-15 | O11: Deferred | P11: Deferred | Q11: 0 | R11: N/A | S11: Sem Year 3 | T11: N/A | U11: N/A | V11: Not Yet | Y11: ⏸ Deferred — On Leave
A12: TU-2023-0010 | B12: James Kibaki | C12: Undergraduate | D12: BSc | E12: School of Computing | F12: 2023-09-04 | G12: Sem 2 | H12: In Progress | I12: In Progress | J12: Pending | K12: Pending | L12: 3.4 | M12: Good Standing | N12: 2024-01-15 | O12: Paid | P12: Paid | Q12: 0 | R12: N/A | S12: Sem Year 1 | T12: N/A | U12: N/A | V12: Not Yet | Y12: 1. Enrolled & Orientated
A13: TU-2022-0011 | B13: Kezia Moraa | C13: Undergraduate | D13: BSc | E13: School of Science | F13: 2022-09-06 | G13: Sem 4 | H13: Complete | I13: Complete | J13: In Progress | K13: Pending | L13: 3.05 | M13: Good Standing | N13: 2024-01-15 | O13: Paid | P13: Paid | Q13: 0 | R13: N/A | S13: Sem Year 2 | T13: N/A | U13: N/A | V13: Not Yet | Y13: 2. Progressing — Year 2
A14: TU-2019-0012 | B14: Liam Okonkwo | C14: Undergraduate | D14: BSc | E14: School of Engineering | F14: 2019-09-02 | G14: Completed | H14: Complete | I14: Complete | J14: Complete | K14: Complete | L14: 2.6 | M14: Cleared | N14: 2024-01-15 | O14: Paid | P14: Cleared | Q14: 0 | R14: N/A | S14: Sem Year 4 | T14: N/A | U14: N/A | V14: Approved | W14: 2024-01-15 | X14: 2023-11-10 | Y14: 6. Graduated ✓
A15: TU-2021-0013 | B15: Mary Adhiambo | C15: Undergraduate | D15: BA | E15: School of Social Sciences | F15: 2021-09-05 | G15: Sem 6 | H15: Complete | I15: Complete | J15: Complete | K15: In Progress | L15: 3.5 | M15: Good Standing | N15: 2024-01-15 | O15: Paid | P15: Paid | Q15: 0 | R15: N/A | S15: Sem Year 3 | T15: N/A | U15: N/A | V15: Not Yet | Y15: 3. Progressing — Year 3
A16: TU-2020-0014 | B16: Noel Kiprotich | C16: Undergraduate | D16: BPharm | E16: School of Health Sciences | F16: 2020-09-07 | G16: Sem 8 | H16: Complete | I16: Complete | J16: Complete | K16: Complete | L16: 1.9 | M16: Suspended | N16: 2023-12-01 | O16: Overdue | P16: Overdue | Q16: 75000 | R16: N/A | S16: Sem Year 4 | T16: N/A | U16: N/A | V16: Blocked | Y16: ⚠ Academic Hold — Suspended
A17: TU-2023-0015 | B17: Olivia Achieng | C17: Undergraduate | D17: BA | E17: School of Arts | F17: 2023-09-04 | G17: Sem 2 | H17: In Progress | I17: In Progress | J17: Pending | K17: Pending | L17: 3.82 | M17: Good Standing | N17: 2024-01-15 | O17: Paid | P17: Paid | Q17: 0 | R17: N/A | S17: Sem Year 1 | T17: N/A | U17: N/A | V17: Not Yet | Y17: 1. Enrolled & Orientated
A18: TU-2022-0016 | B18: Patrick Owino | C18: Undergraduate | D18: BSc | E18: School of Science | F18: 2022-09-06 | G18: Sem 4 | H18: Complete | I18: Complete | J18: In Progress | K18: Pending | L18: 2.95 | M18: Good Standing | N18: 2024-01-15 | O18: Paid | P18: Paid | Q18: 0 | R18: N/A | S18: Sem Year 2 | T18: N/A | U18: N/A | V18: Not Yet | Y18: 2. Progressing — Year 2
A19: TU-2021-0017 | B19: Queenie Mugo | C19: Undergraduate | D19: BSc | E19: School of Computing | F19: 2021-09-05 | G19: Sem 6 | H19: Complete | I19: Complete | J19: Complete | K19: In Progress | L19: 3.95 | M19: Good Standing | N19: 2024-01-15 | O19: Paid | P19: Paid | Q19: 0 | R19: N/A | S19: Sem Year 3 | T19: N/A | U19: N/A | V19: Not Yet | Y19: 3. Progressing — Year 3
A20: TU-2020-0018 | B20: Robert Dlamini | C20: Undergraduate | D20: BEd | E20: School of Education | F20: 2020-09-07 | G20: Sem 8 | H20: Complete | I20: Complete | J20: Complete | K20: Complete | L20: 3.3 | M20: Good Standing | N20: 2024-01-15 | O20: Paid | P20: Paid | Q20: 0 | R20: N/A | S20: Sem Year 4 | T20: N/A | U20: N/A | V20: In Progress | Y20: 4. Final Year — Pre-Clearance
A21: TU-2023-0019 | B21: Sandra Chebet | C21: Undergraduate | D21: BSc | E21: School of Health Sciences | F21: 2023-09-04 | G21: Sem 2 | H21: In Progress | I21: In Progress | J21: Pending | K21: Pending | L21: 3.15 | M21: Good Standing | N21: 2024-01-15 | O21: Paid | P21: Paid | Q21: 0 | R21: N/A | S21: Sem Year 1 | T21: N/A | U21: N/A | V21: Not Yet | Y21: 1. Enrolled & Orientated
A22: TU-2022-0020 | B22: Tunde Adeyemi | C22: Undergraduate | D22: LLB | E22: School of Law | F22: 2022-09-06 | G22: Sem 4 | H22: Complete | I22: Complete | J22: In Progress | K22: Pending | L22: 3.6 | M22: Good Standing | N22: 2024-01-15 | O22: Paid | P22: Paid | Q22: 0 | R22: N/A | S22: Sem Year 2 | T22: N/A | U22: N/A | V22: Not Yet | Y22: 2. Progressing — Year 2
A23: TU-2021-0021 | B23: Uchenna Eze | C23: Undergraduate | D23: BA | E23: School of Social Sciences | F23: 2021-09-05 | G23: Sem 6 | H23: Complete | I23: Complete | J23: Complete | K23: In Progress | L23: 2.75 | M23: Good Standing | N23: 2024-01-15 | O23: Deferred | P23: Deferred | Q23: 0 | R23: N/A | S23: Sem Year 3 | T23: N/A | U23: N/A | V23: Not Yet | Y23: ⏸ Deferred — On Leave
A24: TU-2019-0022 | B24: Vivian Kamau | C24: Undergraduate | D24: BSc | E24: School of Science | F24: 2019-09-02 | G24: Completed | H24: Complete | I24: Complete | J24: Complete | K24: Complete | L24: 3.88 | M24: Cleared | N24: 2024-01-15 | O24: Paid | P24: Cleared | Q24: 0 | R24: N/A | S24: Sem Year 4 | T24: N/A | U24: N/A | V24: Approved | W24: 2024-01-15 | X24: 2023-11-10 | Y24: 6. Graduated ✓
A25: TU-2023-0023 | B25: William Barasa | C25: Undergraduate | D25: BComm | E25: School of Business | F25: 2023-09-04 | G25: Sem 2 | H25: In Progress | I25: In Progress | J25: Pending | K25: Pending | L25: 2.2 | M25: Probation | N25: 2023-12-01 | O25: Partial | P25: Partial | Q25: 35000 | R25: N/A | S25: Sem Year 1 | T25: N/A | U25: N/A | V25: Blocked | Y25: ⚠ Academic Review — Probation
A26: TU-2022-0024 | B26: Xena Mutua | C26: Undergraduate | D26: BSc | E26: School of Computing | F26: 2022-09-06 | G26: Sem 4 | H26: Complete | I26: Complete | J26: In Progress | K26: Pending | L26: 3.42 | M26: Good Standing | N26: 2024-01-15 | O26: Paid | P26: Paid | Q26: 0 | R26: N/A | S26: Sem Year 2 | T26: N/A | U26: N/A | V26: Not Yet | Y26: 2. Progressing — Year 2
A27: TU-2023-0025 | B27: Stephen Gaita Gaikia | C27: Undergraduate | D27: BSc | E27: School of Computing | F27: 2023-09-04 | G27: Sem 2 | H27: In Progress | I27: In Progress | J27: Pending | K27: Pending | L27: 3.65 | M27: Good Standing | N27: 2024-01-15 | O27: Paid | P27: Paid | Q27: 0 | R27: N/A | S27: Sem Year 1 | T27: N/A | U27: N/A | V27: Not Yet | Y27: 1. Enrolled & Orientated
A28: TU-PG-2022-0026 | B28: Amara Diallo | C28: Postgraduate | D28: MSc (Coursework) | E28: School of Computing | F28: 2022-09-05 | G28: Sem 4 | H28: Complete | I28: Complete | J28: In Progress | K28: Pending | L28: 3.72 | M28: Good Standing | N28: 2024-01-15 | O28: Paid | P28: Paid | Q28: 0 | R28: N/A | S28: Sem 4 | T28: N/A | U28: N/A | V28: In Progress | Y28: 3. PG Final Semester — Pre-Graduation
A29: TU-PG-2023-0027 | B29: Benjamin Kamto | C29: Postgraduate | D29: MBA (Coursework) | E29: School of Business | F29: 2023-09-04 | G29: Sem 2 | H29: In Progress | I29: In Progress | J29: Pending | K29: Pending | L29: 3.41 | M29: Good Standing | N29: 2024-01-15 | O29: Paid | P29: Paid | Q29: 0 | R29: N/A | S29: Sem 2 | T29: N/A | U29: N/A | V29: Not Yet | Y29: 1. PG Enrolled — Coursework Phase
A30: TU-PG-2022-0028 | B30: Celestine Awino | C30: Postgraduate | D30: MA (Coursework) | E30: School of Business | F30: 2022-09-05 | G30: Completed | H30: Complete | I30: Complete | J30: Complete | K30: Complete | L30: 3.55 | M30: Cleared | N30: 2023-11-01 | O30: Paid | P30: Cleared | Q30: 0 | R30: N/A | S30: Completed | T30: N/A | U30: N/A | V30: Approved | W30: 2023-11-01 | X30: 2023-11-10 | Y30: 4. Graduated ✓
A31: TU-PG-2023-0029 | B31: Derrick Ssempa | C31: Postgraduate | D31: MSc (Coursework) | E31: School of Science | F31: 2023-09-04 | G31: Sem 2 | H31: In Progress | I31: In Progress | J31: Pending | K31: Pending | L31: 2.81 | M31: Probation | N31: 2023-12-01 | O31: Partial | P31: Partial | Q31: 35000 | R31: N/A | S31: Sem 2 | T31: N/A | U31: N/A | V31: Blocked | Y31: ⚠ Academic Review — Probation
A32: TU-PG-2022-0030 | B32: Faith Onyango | C32: Postgraduate | D32: MA (Coursework) | E32: School of Arts | F32: 2022-09-05 | G32: Sem 4 | H32: Complete | I32: Complete | J32: In Progress | K32: Pending | L32: 3.65 | M32: Good Standing | N32: 2024-01-15 | O32: Paid | P32: Paid | Q32: 0 | R32: N/A | S32: Sem 4 | T32: N/A | U32: N/A | V32: In Progress | Y32: 3. PG Final Semester — Pre-Graduation
A33: TU-PG-2023-0031 | B33: George Nkosi | C33: Postgraduate | D33: MBA (Coursework) | E33: School of Business | F33: 2023-09-04 | G33: Sem 2 | H33: In Progress | I33: In Progress | J33: Pending | K33: Pending | L33: 3.22 | M33: Good Standing | N33: 2024-01-15 | O33: Paid | P33: Paid | Q33: 0 | R33: N/A | S33: Sem 2 | T33: N/A | U33: N/A | V33: Not Yet | Y33: 1. PG Enrolled — Coursework Phase
A34: TU-PG-2021-0032 | B34: Helen Mutuku | C34: Postgraduate | D34: MSc by Research | E34: School of Science | F34: 2021-09-06 | G34: Research Year 3 | H34: Complete | I34: Complete | J34: Complete | K34: Complete | L34: 3.82 | M34: Good Standing | N34: 2024-01-15 | O34: Paid | P34: Paid | Q34: 0 | R34: Writing | S34: Writing | T34: In Progress | U34: Not Yet | V34: Not Yet | Y34: 4. Thesis Writing Phase
A35: TU-PG-2022-0033 | B35: Ibrahim Hassan | C35: Postgraduate | D35: MSc by Research | E35: School of Computing | F35: 2022-09-05 | G35: Research Year 2 | H35: Complete | I35: Complete | J35: Complete | K35: In Progress | L35: 3.61 | M35: Good Standing | N35: 2024-01-15 | O35: Paid | P35: Paid | Q35: 0 | R35: Data Collection | S35: Data Collection | T35: Not Yet | U35: Not Yet | V35: Not Yet | Y35: 3. Data Collection & Analysis Phase
A36: TU-PG-2021-0034 | B36: Janet Akinyi | C36: Postgraduate | D36: MA by Research | E36: School of Education | F36: 2021-09-06 | G36: Research Year 3 | H36: Complete | I36: Complete | J36: Complete | K36: Complete | L36: 3.48 | M36: Good Standing | N36: 2024-01-15 | O36: Paid | P36: Paid | Q36: 0 | R36: Writing | S36: Writing | T36: In Progress | U36: Not Yet | V36: Not Yet | Y36: 4. Thesis Writing Phase
A37: TU-PG-2022-0035 | B37: Kenneth Osei | C37: Postgraduate | D37: MSc by Research | E37: School of Engineering | F37: 2022-09-05 | G37: Research Year 2 | H37: Complete | I37: Complete | J37: Complete | K37: In Progress | L37: 3.31 | M37: Good Standing | N37: 2024-01-15 | O37: Deferred | P37: Deferred | Q37: 0 | R37: Proposal Approved | S37: Proposal Approved | T37: Not Yet | U37: Not Yet | V37: Not Yet | Y37: ⏸ Deferred — On Leave (Research)
A38: TU-PG-2020-0036 | B38: Lydia Cheptoo | C38: Postgraduate | D38: MSc by Research | E38: School of Health Sciences | F38: 2020-09-07 | G38: Completed | H38: Complete | I38: Complete | J38: Complete | K38: Complete | L38: 3.91 | M38: Cleared | N38: 2023-11-01 | O38: Paid | P38: Cleared | Q38: 0 | R38: Defended & Approved | S38: Defended & Approved | T38: Submitted | U38: Passed | V38: Approved | W38: 2023-11-01 | X38: 2023-11-10 | Y38: 6. Graduated ✓ (Research)
A39: TU-PG-2023-0037 | B39: Moses Waweru | C39: Postgraduate | D39: MSc by Research | E39: School of Computing | F39: 2023-09-04 | G39: Research Year 1 | H39: Complete | I39: In Progress | J39: Pending | K39: Pending | L39: 3.52 | M39: Good Standing | N39: 2024-01-15 | O39: Paid | P39: Paid | Q39: 0 | R39: Proposal Submitted | S39: Proposal Submitted | T39: Submitted | U39: Not Yet | V39: Not Yet | Y39: 2. Research Proposal Phase

Sheet Rankings Dashboard
A1: TemplumIS University — Global Ranking Indicators Dashboard
A2: Academic Year 2023/24 · Semester 1 | Data sourced from LMS/SIS institutional records
A4: INSTITUTIONAL SUMMARY
A5: Total Students | B5: 37 | C5: Avg GPA | D5: 3.32 / 4.0 | E5: International Students | F5: 35.1% | G5: Female Ratio | H5: 48.6%
A6: UG Students | B6: 25 | C6: Active Students | D6: 25 | E6: Research Students | F6: 6 | G6: Nationalities | H6: 10
A7: PG Students | B7: 12 | C7: Graduates | D7: 5 | E7: Student:Faculty Ratio | F7: 2.5 : 1 | G7: Schools / Faculties | H7: 9
A8: Faculty (Instructors) | B8: 15 | C8: Active Courses | D8: 19 | E8: Avg Attendance | F8: 83% | G8: Avg Grade | H8: 77.6%
A10: WEBOMETRICS Ranking of World Universities
A11: Focus: Web presence, openness & academic output
A12: Indicator | B12: Weight | C12: Score Estimate | D12: Notes / TemplumIS Evidence | E12: Status
A13: Visibility / Impact (Web links) | B13: 50% | C13: ~20% | D13: Institutional website not indexed in dataset; no inlink data available | E13: ⚠
A14: Openness / Transparency (OA repos) | B14: 10% | C14: ~25% | D14: 6 research dissertations in progress; no open access repository evidenced | E14: ⚠
A15: Excellence (Google Scholar output) | B15: 10% | C15: ~15% | D15: Research topics active (malaria, AI, NLP) but publications not yet confirmed | E15: ✗
A16: Presence (indexed web pages) | B16: 5% | C16: ~30% | D16: Domain @templumis.ac confirmed; web footprint/page count unknown | E16: ⚠
A17: OVERALL DATA READINESS | B17: — | C17: ~22% | D17: Weighted estimate based on available institutional data
A19: THE World University Rankings
A20: Focus: Teaching, research, citations & international outlook
A21: Indicator | B21: Weight | C21: Score Estimate | D21: Notes / TemplumIS Evidence | E21: Status
A22: Teaching — Learning Environment | B22: 29.5% | C22: ~62% | D22: SFR 2.5:1 (excellent); avg GPA 3.32; 9 schools; 20 active courses; reputation survey data N/A | E22: ✓
A23: Research — Environment & Productivity | B23: 29% | C23: ~18% | D23: 6 research students; dissertations in health, CS, engineering; research income data unavailable | E23: ✗
A24: Citations — Research Influence (Scopus) | B24: 30% | C24: ~5% | D24: No citation records in institutional data; requires Scopus indexing | E24: ✗
A25: International Outlook | B25: 7.5% | C25: ~58% | D25: 35.1% international students; 10 nationalities; strong Pan-African diversity | E25: ✓
A26: Industry Income per Academic | B26: 4% | C26: ~5% | D26: No industry partnership or income data recorded in dataset | E26: ✗
A27: OVERALL DATA READINESS | B27: — | C27: ~26% | D27: Weighted estimate based on available institutional data
A29: THE Sub-Saharan Africa Rankings (SSA)
A30: Focus: Regionally adapted THE criteria for African universities
A31: Indicator | B31: Weight | C31: Score Estimate | D31: Notes / TemplumIS Evidence | E31: Status
A32: Teaching & Learning | B32: 25% | C32: ~70% | D32: SFR 2.5:1; 20 courses; 5 graduates; avg grade 77.6%; strong student support systems | E32: ✓
A33: Research | B33: 30% | C33: ~35% | D33: 6 active research students (16.2%); applied African topics; no citation data | E33: ⚠
A34: Knowledge Transfer to Society | B34: 20% | C34: ~40% | D34: Dissertations on maternal health, Swahili NLP, solar desalination — locally relevant | E34: ⚠
A35: International Outlook | B35: 15% | C35: ~65% | D35: 10 nationalities; 35.1% international; Pan-African student mix across 10 countries | E35: ✓
A36: Access & Inclusion | B36: 10% | C36: ~68% | D36: 48.6% female; academic support processes (probation, standing review) evidenced | E36: ✓
A37: OVERALL DATA READINESS | B37: — | C37: ~50% | D37: Weighted estimate based on available institutional data
A39: Shanghai ARWU (Academic Ranking of World Universities)
A40: Focus: Research output, Nobel laureates & high-impact publications
A41: Indicator | B41: Weight | C41: Score Estimate | D41: Notes / TemplumIS Evidence | E41: Status
A42: Alumni — Nobel / Fields Medal winners | B42: 10% | C42: ~0% | D42: 5 graduates confirmed; no Nobel/Fields alumni data applicable at this stage | E42: ✗
A43: Staff — Nobel / Fields Medal winners | B43: 20% | C43: ~0% | D43: No data on faculty international awards of this calibre | E43: ✗
A44: Highly Cited Researchers (Clarivate HiCi) | B44: 20% | C44: ~0% | D44: No citation records; Clarivate HiCi designation not evidenced | E44: ✗
A45: Papers in Nature & Science | B45: 20% | C45: ~0% | D45: Research in dissertation phase; no Nature/Science publications confirmed | E45: ✗
A46: Papers in SCI / SSCI (Web of Science) | B46: 20% | C46: ~5% | D46: 6 research dissertations underway; journal publishing pipeline not recorded | E46: ⚠
A47: Per capita academic performance (PCP) | B47: 10% | C47: ~8% | D47: 15 faculty; small institution could score relatively if output begins | E47: ⚠
A48: OVERALL DATA READINESS | B48: — | C48: ~5% | D48: Weighted estimate based on available institutional data
A50: QS World University Rankings
A51: Focus: Reputation, faculty ratio, citations & international diversity
A52: Indicator | B52: Weight | C52: Score Estimate | D52: Notes / TemplumIS Evidence | E52: Status
A53: Academic Reputation (survey) | B53: 30% | C53: ~10% | D53: No global survey presence; institution not yet globally known | E53: ✗
A54: Employer Reputation (survey) | B54: 15% | C54: ~10% | D54: 5 graduates; no employment tracking or employer survey data available | E54: ✗
A55: Faculty/Student Ratio | B55: 10% | C55: ~88% | D55: 2.5:1 ratio — exceptional; well within global top-tier benchmarks (<10:1) | E55: ✓
A56: Citations per Faculty (Scopus) | B56: 20% | C56: ~5% | D56: No Scopus citation records in dataset; requires active publication base | E56: ✗
A57: International Faculty Ratio | B57: 5% | C57: ~25% | D57: All 15 instructors appear local; international faculty not distinguishable from data | E57: ⚠
A58: International Student Ratio | B58: 5% | C58: ~72% | D58: 35.1% international students — strong; 13 students from 9 non-Kenyan countries | E58: ✓
A59: Sustainability (ESG metrics) | B59: 5% | C59: ~20% | D59: Community-focused research topics noted; formal sustainability reporting not evidenced | E59: ⚠
A60: Employment Outcomes | B60: 10% | C60: ~20% | D60: 5 confirmed graduates; no employment rate or alumni outcomes tracking data | E60: ⚠
A61: OVERALL DATA READINESS | B61: — | C61: ~32% | D61: Weighted estimate based on available institutional data
A63: CWTS Leiden Ranking
A64: Focus: Bibliometric research performance (Web of Science)
A65: Indicator | B65: Weight | C65: Score Estimate | D65: Notes / TemplumIS Evidence | E65: Status
A66: P — Scientific output (WoS papers) | B66: Core | C66: ~8% | D66: 6 research theses in progress; malaria, AI/UAV, NLP topics; none confirmed indexed | E66: ⚠
A67: PP(top 10%) — Citation impact | B67: Core | C67: ~3% | D67: No Web of Science citation records available; requires published indexed output | E67: ✗
A68: MCS — Mean citation score (normalised) | B68: Core | C68: ~3% | D68: Citation tracking requires published and indexed output in WoS | E68: ✗
A69: PP(collab) — International co-authorship | B69: Core | C69: ~10% | D69: Multi-national student body; potential for collaboration; no co-authorship data recorded | E69: ⚠
A70: PP(gender) — Female authorship | B70: Supplementary | C70: ~45% | D70: 48.6% female students; 3 of 6 research students are female — strong potential | E70: ⚠
A71: PP(OA) — Open Access publications | B71: Supplementary | C71: ~10% | D71: No open access repository or infrastructure evidenced in institutional data | E71: ✗
A72: OVERALL DATA READINESS | B72: — | C72: ~8% | D72: Weighted estimate based on available institutional data
A74: METHODOLOGY NOTE
A75: Score estimates are proxies derived from institutional LMS/SIS data available in the TemplumIS dataset. Indicators requiring external data (Scopus, Web of Science, employer surveys, academic reputation surveys, Clarivate HiCi lists) cannot be fully evaluated from internal records alone. Status symbols: ✓ = Performing well, ⚠ = Limited/partial data, ✗ = No data or not applicable. Scores represent current data readiness relative to each ranking's criteria, not projected global ranking positions.

Sheet PG Research Tracker
A1: Student ID | B1: Full Name | C1: Programme Level | D1: Supervisor | E1: Research Area | F1: Dissertation Title | G1: Proposal Status | H1: Ethics Approval | I1: Data Collection | J1: Thesis Draft | K1: Submission Target | L1: Publications | M1: Conferences | N1: Grant Funding | O1: Current Challenge | P1: Next Milestone | Q1: Risk Flag
A2: TU-PG-2022-0026 | B2: Amara Diallo | C2: MSc (Coursework) | D2: Dr. Fatima Okello | E2: Public Health Policy | F2: Community Health Interventions in Rural Kenya | G2: Approved | H2: Cleared | I2: Complete | J2: Final draft | K2: 2026-04-15 | L2: 1 | M2: 2 | N2: Internal research grant — KES 120,000 | O2: Thesis formatting review | P2: Submit final dissertation | Q2: Low
A3: TU-PG-2023-0027 | B3: Benjamin Kamto | C3: MBA (Coursework) | D3: Prof. James Wanjala | E3: Strategic Management | F3: Digital Transformation in SMEs | G3: Submitted — under review | H3: Pending | I3: In progress | J3: Chapter 3 draft | K3: 2026-08-30 | L3: 0 | M3: 1 | N3: None | O3: Supervisor feedback turnaround | P3: Complete coursework modules | Q3: Medium
A4: TU-PG-2022-0028 | B4: Celestine Awino | C4: MA (Coursework) | D4: Dr. Grace Muthoni | E4: Education Policy | F4: Inclusive Education Practices in Secondary Schools | G4: Approved | H4: Cleared | I4: Complete | J4: Under revision | K4: 2026-05-20 | L4: 0 | M4: 1 | N4: Faculty seed grant — KES 80,000 | O4: Literature gap refinement | P4: Revise thesis chapters 2–3 | Q4: Low
A5: TU-PG-2023-0029 | B5: David Ochieng | C5: MSc (Research) | D5: Dr. Peter Kimani | E5: Data Science | F5: Machine Learning for Agricultural Yield Prediction | G5: Approved | H5: Cleared | I5: Active | J5: Chapter 4 in progress | K5: 2026-12-01 | L5: 1 | M5: 0 | N5: Research council grant — KES 250,000 | O5: Dataset licensing (FAIR compliance) | P5: Complete data analysis chapter | Q5: Medium
A6: TU-PG-2021-0030 | B6: Elena Vasquez | C6: PhD | D6: Prof. Samuel Njoroge | E6: Climate Science | F6: Climate Resilience Modelling for East African Coasts | G6: Approved | H6: Cleared | I6: Active | J6: Draft v3 | K6: 2027-06-30 | L6: 3 | M6: 4 | N6: International fellowship — USD 15,000 | O6: Publication pipeline coordination | P6: Prepare for progression review | Q6: Low

Sheet PG Academic Support
A1: Student ID | B1: Service | C1: Provider | D1: Contact Email | E1: Status | F1: Last Session | G1: Next Session | H1: Notes | I1: Priority
A2: TU-PG-2022-0026 | B2: Writing Centre | C2: PG Writing Lab | D2: writing@templumis.ac | E2: Active | F2: 2026-02-10 | G2: 2026-03-05 | H2: Thesis structure coaching | I2: Normal
A3: TU-PG-2022-0026 | B3: Research Methods | C3: Graduate School | D3: gradschool@templumis.ac | E3: Completed | F3: 2026-01-20 | H3: Qualitative methods workshop | I3: Normal
A4: TU-PG-2023-0027 | B4: Academic Coaching | C4: PG Support Office | D4: pgsupport@templumis.ac | E4: Scheduled | F4: 2026-02-28 | G4: 2026-03-12 | H4: Time management for coursework | I4: High
A5: TU-PG-2022-0028 | B5: Library Research | C5: Research Librarian | D5: library@templumis.ac | E5: Active | F5: 2026-02-15 | G5: 2026-03-08 | H5: Systematic review search strategy | I5: Normal
A6: TU-PG-2023-0029 | B6: Data Management | C6: Research Data Team | D6: data@templumis.ac | E6: Active | F6: 2026-02-18 | G6: 2026-03-15 | H6: FAIR data plan review | I6: High
A7: TU-PG-2021-0030 | B7: Supervisor Meeting | C7: Graduate School | D7: gradschool@templumis.ac | E7: Active | F7: 2026-02-22 | G7: 2026-03-20 | H7: Annual progression review prep | I7: Normal
A8: TU-PG-2021-0030 | B8: Ethics Advisory | C8: Research Ethics Board | D8: ethics@templumis.ac | E8: Completed | F8: 2025-11-10 | H8: Ethics clearance renewed | I8: Normal

Sheet Library Resources
A1: Resource ID | B1: Title | C1: Type | D1: Subject Area | E1: Programme Level | F1: FAIR — Findable (DOI/Metadata) | G1: FAIR — Accessible | H1: FAIR — Interoperable | I1: FAIR — Reusable (License) | J1: URL | K1: Description | L1: Access Notes
A2: LIB-001 | B2: TemplumIS Research Repository | C2: Repository | D2: Multidisciplinary | E2: All | F2: Indexed with DOI; rich metadata (Dublin Core) | G2: Campus SSO + ORCID login | H2: OAI-PMH API; JSON metadata export | I2: CC BY 4.0 for published theses | J2: https://repository.templumis.ac | K2: Institutional open-access repository for PG theses and datasets. | L2: Upload via Graduate School portal
A3: LIB-002 | B3: Scopus | C3: Database | D3: Multidisciplinary | E3: Postgraduate | F3: Persistent IDs for indexed publications | G3: Campus IP + remote VPN | H3: RIS/BibTeX export; API for bibliometrics | I3: Publisher terms apply | J3: https://www.scopus.com | K3: Citation and abstract database for literature reviews. | L3: Use library proxy off-campus
A4: LIB-003 | B4: Web of Science | C4: Database | D4: Sciences | E4: Postgraduate | F4: DOI-linked records | G4: Campus authentication | H4: EndNote integration | I4: Publisher license | J4: https://www.webofscience.com | K4: Peer-reviewed journal index and citation tracking. | L4: Book a librarian session for advanced search
A5: LIB-004 | B5: Kenya National Research Data Archive | C5: Dataset | D5: Social Sciences | E5: Postgraduate | F5: Registered dataset DOIs; README metadata | G5: Open download + API key for restricted sets | H5: CSV, JSON, STATA interoperable formats | I5: CC BY 4.0 / custom data agreements | J5: https://data.kenya-research.ac | K5: National FAIR-compliant datasets for policy and health research. | L5: Register before downloading restricted data
A6: LIB-005 | B6: IEEE Xplore | C6: Database | D6: Engineering & CS | E6: Postgraduate | F6: IEEE DOI metadata | G6: Institutional subscription | H6: BibTeX, XML exports | I6: IEEE terms of use | J6: https://ieeexplore.ieee.org | K6: Engineering and computing literature for MSc/PhD research. | L6: Link ORCID for author profiles
A7: LIB-006 | B7: JSTOR | C7: Database | D7: Humanities & Social Sciences | E7: All | F7: Stable URLs and citation metadata | G7: Campus login | H7: PDF + citation export | I7: JSTOR license | J7: https://www.jstor.org | K7: Archive of journals and books for humanities PG research. | L7: Use advanced search filters
A8: LIB-007 | B8: Zotero Research Guide | C8: Tool | D8: Research Skills | E8: Postgraduate | F8: Guide metadata on library catalogue | G8: Open access guide | H8: RIS/BibTeX compatible | I8: Creative Commons guide | J8: https://libguides.templumis.ac/zotero | K8: Reference management and FAIR citation workflows. | L8: Install desktop + browser connector
A9: LIB-008 | B9: Open Data Kenya — Agriculture | C9: Dataset | D9: Agriculture | E9: Postgraduate | F9: Dataset catalogue with DOIs | G9: Open API + bulk download | H9: CSV, GeoJSON | I9: Open Government Licence | J9: https://opendata.templumis.ac/agriculture | K9: FAIR agricultural datasets for MSc research projects. | L9: Cite dataset DOI in thesis
