Workbook

Sheet Students
A1: student_id | B1: full_name | C1: gender | D1: date_of_birth | E1: email | F1: phone | G1: program | H1: major | I1: department | J1: year_of_study | K1: gpa | L1: credit_hours_earned | M1: status | N1: nationality | O1: enrollment_date | P1: expected_graduation | Q1: Student Type | R1: Programme Level | S1: Journey Stage | T1: Current Semester | U1: Fees Status | V1: Fees Balance (KES) | W1: Academic Standing | X1: Last Standing Review | Y1: Dissertation Title | Z1: Dissertation Status | AA1: Graduation Clearance | AB1: Actual Graduation Date | AC1: Programme Advisor / Supervisor | AD1: Co-Supervisor | AE1: Specialisation / Research Area | AF1: Expected Defense / Completion | AG1: Milestones Achieved | AH1: Next Milestone | AI1: Research / Capstone Output | AJ1: Institution | AK1: NSFAS Beneficiary | AL1: Has Disability | AM1: Disability Type | AN1: Disability Accommodation Needed
A2: TU-2021-0001 | B2: Amelia Odhiambo | C2: Female | D2: 2001-03-12 | E2: a.odhiambo@templumis.ac | F2: +254712345001 | G2: BSc | H2: Computer Science | I2: School of Computing | J2: Year 3 | K2: 3.78 | L2: 96 | M2: Active | N2: Kenyan | O2: 2021-09-05 | P2: 2025-06-30 | Q2: Undergraduate | R2: BSc | S2: 3. Progressing — Year 3 | T2: Sem 6 | U2: Paid | V2: 0 | W2: Good Standing | X2: 2024-01-15 | Y2: N/A | Z2: N/A | AA2: Not Yet | AJ2: Templumis University | AK2: No | AL2: No | AM2: None | AN2: None
A3: TU-2022-0002 | B3: Brian Mwangi | C3: Male | D3: 2002-07-22 | E3: b.mwangi@templumis.ac | F3: +254712345002 | G3: BA | H3: Economics | I3: School of Business | J3: Year 2 | K3: 3.12 | L3: 64 | M3: Active | N3: Kenyan | O3: 2022-09-05 | P3: 2026-06-30 | Q3: Undergraduate | R3: BA | S3: 2. Progressing — Year 2 | T3: Sem 4 | U3: Paid | V3: 0 | W3: Good Standing | X3: 2024-01-15 | Y3: N/A | Z3: N/A | AA3: Not Yet | AJ3: Templumis University | AK3: No | AL3: No | AM3: None | AN3: None
A4: TU-2020-0003 | B4: Claire Nakato | C4: Female | D4: 2000-11-05 | E4: c.nakato@templumis.ac | F4: +256712345003 | G4: BSc | H4: Civil Engineering | I4: School of Engineering | J4: Year 4 | K4: 3.55 | L4: 128 | M4: Active | N4: Ugandan | O4: 2020-09-07 | P4: 2024-06-30 | Q4: Undergraduate | R4: BSc | S4: 4. Final Year — Pre-Clearance | T4: Sem 8 | U4: Paid | V4: 0 | W4: Good Standing | X4: 2024-01-15 | Y4: N/A | Z4: N/A | AA4: In Progress | AJ4: Templumis University | AK4: No | AL4: Yes | AM4: Physical / Mobility Impairment | AN4: Ground-floor lecture venues; extended assignment deadlines
A5: TU-2019-0004 | B5: David Mensah | C5: Male | D5: 1999-04-18 | E5: d.mensah@templumis.ac | F5: +233712345004 | G5: BSc | H5: Nursing | I5: School of Health Sciences | J5: Year 4 | K5: 3.9 | L5: 132 | M5: Graduated | N5: Ghanaian | O5: 2019-09-02 | Q5: Undergraduate | R5: BSc | S5: 6. Graduated ✓ | T5: Completed | U5: Cleared | V5: 0 | W5: Cleared | X5: 2024-01-15 | Y5: N/A | Z5: N/A | AA5: Approved | AB5: 2023-11-10 | AJ5: Templumis University | AK5: No | AL5: No | AM5: None | AN5: None
A6: TU-2023-0005 | B6: Esther Wanjiku | C6: Female | D6: 2003-09-30 | E6: e.wanjiku@templumis.ac | F6: +254712345005 | G6: BSc | H6: Mathematics | I6: School of Science | J6: Year 1 | K6: 2.45 | L6: 32 | M6: Probation | N6: Kenyan | O6: 2023-09-04 | P6: 2027-06-30 | Q6: Undergraduate | R6: BSc | S6: ⚠ Academic Review — Probation | T6: Sem 2 | U6: Partial | V6: 35000 | W6: Probation | X6: 2023-12-01 | Y6: N/A | Z6: N/A | AA6: Blocked | AJ6: Templumis University | AK6: No | AL6: No | AM6: None | AN6: None
A7: TU-2021-0006 | B7: Felix Otieno | C7: Male | D7: 2001-01-14 | E7: f.otieno@templumis.ac | F7: +254712345006 | G7: BEd | H7: Education | I7: School of Education | J7: Year 3 | K7: 3.22 | L7: 98 | M7: Active | N7: Kenyan | O7: 2021-09-05 | P7: 2025-06-30 | Q7: Undergraduate | R7: BEd | S7: 3. Progressing — Year 3 | T7: Sem 6 | U7: Paid | V7: 0 | W7: Good Standing | X7: 2024-01-15 | Y7: N/A | Z7: N/A | AA7: Not Yet | AJ7: Templumis University | AK7: No | AL7: No | AM7: None | AN7: None
A8: TU-2022-0007 | B8: Grace Auma | C8: Female | D8: 2002-06-08 | E8: g.auma@templumis.ac | F8: +254712345007 | G8: BSc | H8: Biochemistry | I8: School of Science | J8: Year 2 | K8: 3.68 | L8: 66 | M8: Active | N8: Kenyan | O8: 2022-09-06 | P8: 2026-06-30 | Q8: Undergraduate | R8: BSc | S8: 2. Progressing — Year 2 | T8: Sem 4 | U8: Paid | V8: 0 | W8: Good Standing | X8: 2024-01-15 | Y8: N/A | Z8: N/A | AA8: Not Yet | AJ8: Templumis University | AK8: No | AL8: No | AM8: None | AN8: None
A9: TU-2020-0008 | B9: Hassan Abdi | C9: Male | D9: 2000-12-20 | E9: h.abdi@templumis.ac | F9: +252712345008 | G9: LLB | H9: Law | I9: School of Law | J9: Year 4 | K9: 3.1 | L9: 120 | M9: Active | N9: Somali | O9: 2020-09-07 | P9: 2024-06-30 | Q9: Undergraduate | R9: LLB | S9: 4. Final Year — Pre-Clearance | T9: Sem 8 | U9: Paid | V9: 0 | W9: Good Standing | X9: 2024-01-15 | Y9: N/A | Z9: N/A | AA9: In Progress | AJ9: Templumis University | AK9: No | AL9: No | AM9: None | AN9: None
A10: TU-2021-0009 | B10: Ivy Njeri | C10: Female | D10: 2001-08-03 | E10: i.njeri@templumis.ac | F10: +254712345009 | G10: BComm | H10: Accounting | I10: School of Business | J10: Year 3 | K10: 2.8 | L10: 90 | M10: On Leave | N10: Kenyan | O10: 2021-09-05 | P10: 2025-06-30 | Q10: Undergraduate | R10: BComm | S10: ⏸ Deferred — On Leave | T10: Sem 6 | U10: Deferred | V10: 0 | W10: Good Standing | X10: 2024-01-15 | Y10: N/A | Z10: N/A | AA10: Not Yet | AJ10: Templumis University | AK10: No | AL10: No | AM10: None | AN10: None
A11: TU-2023-0010 | B11: James Kibaki | C11: Male | D11: 2003-02-25 | E11: j.kibaki@templumis.ac | F11: +254712345010 | G11: BSc | H11: Information Technology | I11: School of Computing | J11: Year 1 | K11: 3.4 | L11: 30 | M11: Active | N11: Kenyan | O11: 2023-09-04 | P11: 2027-06-30 | Q11: Undergraduate | R11: BSc | S11: 1. Enrolled & Orientated | T11: Sem 2 | U11: Paid | V11: 0 | W11: Good Standing | X11: 2024-01-15 | Y11: N/A | Z11: N/A | AA11: Not Yet | AJ11: Templumis University | AK11: No | AL11: No | AM11: None | AN11: None
A12: TU-2022-0011 | B12: Kezia Moraa | C12: Female | D12: 2002-10-11 | E12: k.moraa@templumis.ac | F12: +254712345011 | G12: BSc | H12: Environmental Science | I12: School of Science | J12: Year 2 | K12: 3.05 | L12: 60 | M12: Active | N12: Kenyan | O12: 2022-09-06 | P12: 2026-06-30 | Q12: Undergraduate | R12: BSc | S12: 2. Progressing — Year 2 | T12: Sem 4 | U12: Paid | V12: 0 | W12: Good Standing | X12: 2024-01-15 | Y12: N/A | Z12: N/A | AA12: Not Yet | AJ12: Templumis University | AK12: No | AL12: No | AM12: None | AN12: None
A13: TU-2019-0012 | B13: Liam Okonkwo | C13: Male | D13: 1999-05-17 | E13: l.okonkwo@templumis.ac | F13: +234712345012 | G13: BSc | H13: Electrical Engineering | I13: School of Engineering | J13: Year 4 | K13: 2.6 | L13: 124 | M13: Graduated | N13: Nigerian | O13: 2019-09-02 | Q13: Undergraduate | R13: BSc | S13: 6. Graduated ✓ | T13: Completed | U13: Cleared | V13: 0 | W13: Cleared | X13: 2024-01-15 | Y13: N/A | Z13: N/A | AA13: Approved | AB13: 2023-11-10 | AJ13: Templumis University | AK13: No | AL13: No | AM13: None | AN13: None
A14: TU-2021-0013 | B14: Mary Adhiambo | C14: Female | D14: 2001-07-29 | E14: m.adhiambo@templumis.ac | F14: +254712345013 | G14: BA | H14: Sociology | I14: School of Social Sciences | J14: Year 3 | K14: 3.5 | L14: 94 | M14: Active | N14: Kenyan | O14: 2021-09-05 | P14: 2025-06-30 | Q14: Undergraduate | R14: BA | S14: 3. Progressing — Year 3 | T14: Sem 6 | U14: Paid | V14: 0 | W14: Good Standing | X14: 2024-01-15 | Y14: N/A | Z14: N/A | AA14: Not Yet | AJ14: Templumis University | AK14: No | AL14: No | AM14: None | AN14: None
A15: TU-2020-0014 | B15: Noel Kiprotich | C15: Male | D15: 2000-03-06 | E15: n.kiprotich@templumis.ac | F15: +254712345014 | G15: BPharm | H15: Pharmacy | I15: School of Health Sciences | J15: Year 4 | K15: 1.9 | L15: 112 | M15: Suspended | N15: Kenyan | O15: 2020-09-07 | P15: 2024-06-30 | Q15: Undergraduate | R15: BPharm | S15: ⚠ Academic Hold — Suspended | T15: Sem 8 | U15: Overdue | V15: 75000 | W15: Suspended | X15: 2023-12-01 | Y15: N/A | Z15: N/A | AA15: Blocked | AJ15: Templumis University | AK15: No | AL15: No | AM15: None | AN15: None
A16: TU-2023-0015 | B16: Olivia Achieng | C16: Female | D16: 2003-11-15 | E16: o.achieng@templumis.ac | F16: +254712345015 | G16: BA | H16: Communication | I16: School of Arts | J16: Year 1 | K16: 3.82 | L16: 34 | M16: Active | N16: Kenyan | O16: 2023-09-04 | P16: 2027-06-30 | Q16: Undergraduate | R16: BA | S16: 1. Enrolled & Orientated | T16: Sem 2 | U16: Paid | V16: 0 | W16: Good Standing | X16: 2024-01-15 | Y16: N/A | Z16: N/A | AA16: Not Yet | AJ16: Templumis University | AK16: No | AL16: No | AM16: None | AN16: None
A17: TU-2022-0016 | B17: Patrick Owino | C17: Male | D17: 2002-04-02 | E17: p.owino@templumis.ac | F17: +254712345016 | G17: BSc | H17: Statistics | I17: School of Science | J17: Year 2 | K17: 2.95 | L17: 58 | M17: Active | N17: Kenyan | O17: 2022-09-06 | P17: 2026-06-30 | Q17: Undergraduate | R17: BSc | S17: 2. Progressing — Year 2 | T17: Sem 4 | U17: Paid | V17: 0 | W17: Good Standing | X17: 2024-01-15 | Y17: N/A | Z17: N/A | AA17: Not Yet | AJ17: Templumis University | AK17: No | AL17: Yes | AM17: Visual Impairment | AN17: Screen-reader software; extended exam time
A18: TU-2021-0017 | B18: Queenie Mugo | C18: Female | D18: 2001-09-19 | E18: q.mugo@templumis.ac | F18: +254712345017 | G18: BSc | H18: Computer Science | I18: School of Computing | J18: Year 3 | K18: 3.95 | L18: 100 | M18: Active | N18: Kenyan | O18: 2021-09-05 | P18: 2025-06-30 | Q18: Undergraduate | R18: BSc | S18: 3. Progressing — Year 3 | T18: Sem 6 | U18: Paid | V18: 0 | W18: Good Standing | X18: 2024-01-15 | Y18: N/A | Z18: N/A | AA18: Not Yet | AJ18: Templumis University | AK18: No | AL18: No | AM18: None | AN18: None
A19: TU-2020-0018 | B19: Robert Dlamini | C19: Male | D19: 2000-06-23 | E19: r.dlamini@templumis.ac | F19: +268712345018 | G19: BEd | H19: Science Education | I19: School of Education | J19: Year 4 | K19: 3.3 | L19: 118 | M19: Active | N19: Swazi | O19: 2020-09-07 | P19: 2024-06-30 | Q19: Undergraduate | R19: BEd | S19: 4. Final Year — Pre-Clearance | T19: Sem 8 | U19: Paid | V19: 0 | W19: Good Standing | X19: 2024-01-15 | Y19: N/A | Z19: N/A | AA19: In Progress | AJ19: Templumis University | AK19: No | AL19: No | AM19: None | AN19: None
A20: TU-2023-0019 | B20: Sandra Chebet | C20: Female | D20: 2003-01-08 | E20: s.chebet@templumis.ac | F20: +254712345019 | G20: BSc | H20: Nutrition | I20: School of Health Sciences | J20: Year 1 | K20: 3.15 | L20: 28 | M20: Active | N20: Kenyan | O20: 2023-09-04 | P20: 2027-06-30 | Q20: Undergraduate | R20: BSc | S20: 1. Enrolled & Orientated | T20: Sem 2 | U20: Paid | V20: 0 | W20: Good Standing | X20: 2024-01-15 | Y20: N/A | Z20: N/A | AA20: Not Yet | AJ20: Templumis University | AK20: No | AL20: No | AM20: None | AN20: None
A21: TU-2022-0020 | B21: Tunde Adeyemi | C21: Male | D21: 2002-08-14 | E21: t.adeyemi@templumis.ac | F21: +234712345020 | G21: LLB | H21: Law | I21: School of Law | J21: Year 2 | K21: 3.6 | L21: 62 | M21: Active | N21: Nigerian | O21: 2022-09-06 | P21: 2026-06-30 | Q21: Undergraduate | R21: LLB | S21: 2. Progressing — Year 2 | T21: Sem 4 | U21: Paid | V21: 0 | W21: Good Standing | X21: 2024-01-15 | Y21: N/A | Z21: N/A | AA21: Not Yet | AJ21: Templumis University | AK21: No | AL21: No | AM21: None | AN21: None
A22: TU-2021-0021 | B22: Uchenna Eze | C22: Male | D22: 2001-12-01 | E22: u.eze@templumis.ac | F22: +234712345021 | G22: BA | H22: Political Science | I22: School of Social Sciences | J22: Year 3 | K22: 2.75 | L22: 88 | M22: On Leave | N22: Nigerian | O22: 2021-09-05 | P22: 2025-06-30 | Q22: Undergraduate | R22: BA | S22: ⏸ Deferred — On Leave | T22: Sem 6 | U22: Deferred | V22: 0 | W22: Good Standing | X22: 2024-01-15 | Y22: N/A | Z22: N/A | AA22: Not Yet | AJ22: Templumis University | AK22: No | AL22: No | AM22: None | AN22: None
A23: TU-2019-0022 | B23: Vivian Kamau | C23: Female | D23: 1999-07-27 | E23: v.kamau@templumis.ac | F23: +254712345022 | G23: BSc | H23: Biochemistry | I23: School of Science | J23: Year 4 | K23: 3.88 | L23: 134 | M23: Graduated | N23: Kenyan | O23: 2019-09-02 | Q23: Undergraduate | R23: BSc | S23: 6. Graduated ✓ | T23: Completed | U23: Cleared | V23: 0 | W23: Cleared | X23: 2024-01-15 | Y23: N/A | Z23: N/A | AA23: Approved | AB23: 2023-11-10 | AJ23: Templumis University | AK23: No | AL23: No | AM23: None | AN23: None
A24: TU-2023-0023 | B24: William Barasa | C24: Male | D24: 2003-05-10 | E24: w.barasa@templumis.ac | F24: +254712345023 | G24: BComm | H24: Finance | I24: School of Business | J24: Year 1 | K24: 2.2 | L24: 26 | M24: Probation | N24: Kenyan | O24: 2023-09-04 | P24: 2027-06-30 | Q24: Undergraduate | R24: BComm | S24: ⚠ Academic Review — Probation | T24: Sem 2 | U24: Partial | V24: 35000 | W24: Probation | X24: 2023-12-01 | Y24: N/A | Z24: N/A | AA24: Blocked | AJ24: Templumis University | AK24: No | AL24: No | AM24: None | AN24: None
A25: TU-2022-0024 | B25: Xena Mutua | C25: Female | D25: 2002-02-18 | E25: x.mutua@templumis.ac | F25: +254712345024 | G25: BSc | H25: Information Technology | I25: School of Computing | J25: Year 2 | K25: 3.42 | L25: 68 | M25: Active | N25: Kenyan | O25: 2022-09-06 | P25: 2026-06-30 | Q25: Undergraduate | R25: BSc | S25: 2. Progressing — Year 2 | T25: Sem 4 | U25: Paid | V25: 0 | W25: Good Standing | X25: 2024-01-15 | Y25: N/A | Z25: N/A | AA25: Not Yet | AJ25: Templumis University | AK25: No | AL25: No | AM25: None | AN25: None
A26: TU-2023-0025 | B26: Stephen Gaita Gaikia | C26: Male | D26: 2003-06-17 | E26: s.gaikia@templumis.ac | F26: +254712345025 | G26: BSc | H26: Computer Science | I26: School of Computing | J26: Year 1 | K26: 3.65 | L26: 32 | M26: Active | N26: Kenyan | O26: 2023-09-04 | P26: 2027-06-30 | Q26: Undergraduate | R26: BSc | S26: 1. Enrolled & Orientated | T26: Sem 2 | U26: In Arrears | V26: 75000 | W26: Good Standing | X26: 2024-01-15 | Y26: N/A | Z26: N/A | AA26: Not Yet | AJ26: Templumis University | AK26: No | AL26: No | AM26: None | AN26: None
A27: TU-PG-2022-0026 | B27: Amara Diallo | C27: Female | D27: 1996-03-15 | E27: a.diallo@templumis.ac | F27: +221712345026 | G27: MSc | H27: Data Science | I27: School of Computing | J27: Year 2 | K27: 3.72 | L27: 48 | M27: Active | N27: Senegalese | O27: 2022-09-05 | P27: 2024-06-30 | Q27: Postgraduate | R27: MSc (Coursework) | S27: 3. PG Final Semester — Pre-Graduation | T27: Sem 4 | U27: Paid | V27: 0 | W27: Good Standing | X27: 2024-01-15 | Y27: N/A | Z27: N/A | AA27: In Progress | AC27: Ms. Cynthia Aluoch | AD27: Dr. Kevin Otiato (JKUAT, External) | AE27: Data Science — Urban Mobility & Smart City Analytics | AF27: 45473 | AG27: Coursework Yr1 ✓ | Yr2 ✓ | Capstone Proposal Approved ✓ | Data Analysis In Progress | AH27: Final Capstone Report Submission | AI27: N/A (Coursework Track) | AJ27: Templumis University | AK27: No | AL27: No | AM27: None | AN27: None
A28: TU-PG-2023-0027 | B28: Benjamin Kamto | C28: Male | D28: 1994-07-22 | E28: b.kamto@templumis.ac | F28: +237712345027 | G28: MBA | H28: Business Administration | I28: School of Business | J28: Year 1 | K28: 3.41 | L28: 24 | M28: Active | N28: Cameroonian | O28: 2023-09-04 | P28: 2025-06-30 | Q28: Postgraduate | R28: MBA (Coursework) | S28: 1. PG Enrolled — Coursework Phase | T28: Sem 2 | U28: Paid | V28: 0 | W28: Good Standing | X28: 2024-01-15 | Y28: N/A | Z28: N/A | AA28: Not Yet | AC28: Prof. Wambua Simiyu | AD28: N/A | AE28: MBA — Marketing Analytics & Consumer Behaviour | AF28: 45838 | AG28: Orientation ✓ | Semester 1 Coursework ✓ | AH28: Semester 2 Coursework Completion | AI28: N/A (Coursework Phase) | AJ28: Templumis University | AK28: No | AL28: No | AM28: None | AN28: None
A29: TU-PG-2022-0028 | B29: Celestine Awino | C29: Female | D29: 1995-11-05 | E29: c.awino@templumis.ac | F29: +254712345028 | G29: MA | H29: Economics | I29: School of Business | J29: Year 2 | K29: 3.55 | L29: 52 | M29: Graduated | N29: Kenyan | O29: 2022-09-05 | Q29: Postgraduate | R29: MA (Coursework) | S29: 4. Graduated ✓ | T29: Completed | U29: Cleared | V29: 0 | W29: Cleared | X29: 2023-11-01 | Y29: N/A | Z29: N/A | AA29: Approved | AB29: 2023-11-10 | AC29: Prof. Wambua Simiyu | AD29: N/A | AE29: MA Economics — International Trade & Regional Integration | AF29: 45971 | AG29: All Milestones Complete ✓ | Capstone Defended ✓ | Graduated | AH29: N/A — Graduated | AI29: Capstone: Kenya's Export Diversification & EAC Trade Agreements (2024) | AJ29: Templumis University | AK29: No | AL29: No | AM29: None | AN29: None
A30: TU-PG-2023-0029 | B30: Derrick Ssempa | C30: Male | D30: 1997-04-18 | E30: d.ssempa@templumis.ac | F30: +256712345029 | G30: MSc | H30: Environmental Science | I30: School of Science | J30: Year 1 | K30: 2.81 | L30: 20 | M30: Probation | N30: Ugandan | O30: 2023-09-04 | P30: 2025-06-30 | Q30: Postgraduate | R30: MSc (Coursework) | S30: ⚠ Academic Review — Probation | T30: Sem 2 | U30: Partial | V30: 35000 | W30: Probation | X30: 2023-12-01 | Y30: N/A | Z30: N/A | AA30: Blocked | AC30: Dr. Sasha Mutinda | AD30: N/A | AE30: MSc Environmental Science — Climate Change & Sustainability | AF30: 46022 | AG30: Orientation ✓ | Semester 1 Completed (Probation) | AH30: Semester 2 — Achieve GPA ≥ 3.00 to Continue Programme | AI30: N/A — Academic Review Phase | AJ30: Templumis University | AK30: No | AL30: No | AM30: None | AN30: None
A31: TU-PG-2022-0030 | B31: Faith Onyango | C31: Female | D31: 1996-09-30 | E31: f.onyango@templumis.ac | F31: +254712345030 | G31: MA | H31: Communication | I31: School of Arts | J31: Year 2 | K31: 3.65 | L31: 46 | M31: Active | N31: Kenyan | O31: 2022-09-05 | P31: 2024-06-30 | Q31: Postgraduate | R31: MA (Coursework) | S31: 3. PG Final Semester — Pre-Graduation | T31: Sem 4 | U31: Paid | V31: 0 | W31: Good Standing | X31: 2024-01-15 | Y31: N/A | Z31: N/A | AA31: In Progress | AC31: Ms. Abigael Ndungu | AD31: Dr. Zawadi Amani (School of Social Sciences) | AE31: MA Communication — Digital Media & Political Engagement in Africa | AF31: 45473 | AG31: Coursework Yr1 ✓ | Yr2 ✓ | Capstone Proposal Approved ✓ | AH31: Final Capstone Report Submission | AI31: N/A (Coursework Track) | AJ31: Templumis University | AK31: No | AL31: No | AM31: None | AN31: None
A32: TU-PG-2023-0031 | B32: George Nkosi | C32: Male | D32: 1993-02-14 | E32: g.nkosi@templumis.ac | F32: +27712345031 | G32: MBA | H32: Strategic Management | I32: School of Business | J32: Year 1 | K32: 3.22 | L32: 24 | M32: Active | N32: South African | O32: 2023-09-04 | P32: 2025-06-30 | Q32: Postgraduate | R32: MBA (Coursework) | S32: 1. PG Enrolled — Coursework Phase | T32: Sem 2 | U32: Paid | V32: 0 | W32: Good Standing | X32: 2024-01-15 | Y32: N/A | Z32: N/A | AA32: Not Yet | AC32: Prof. Wambua Simiyu | AD32: N/A | AE32: MBA — Strategic Management & Organisational Leadership | AF32: 45838 | AG32: Orientation ✓ | Semester 1 Coursework ✓ | AH32: Semester 2 Coursework + Capstone Topic Selection | AI32: N/A (Coursework Phase) | AJ32: Templumis University | AK32: No | AL32: No | AM32: None | AN32: None
A33: TU-PG-2021-0032 | B33: Helen Mutuku | C33: Female | D33: 1995-07-03 | E33: h.mutuku@templumis.ac | F33: +254712345032 | G33: MSc by Research | H33: Biochemistry | I33: School of Science | J33: Year 3 | K33: 3.82 | L33: 36 | M33: Active | N33: Kenyan | O33: 2021-09-06 | P33: 2024-06-30 | Q33: Postgraduate | R33: MSc by Research | S33: 4. Thesis Writing Phase | T33: Research Year 3 | U33: Paid | V33: 0 | W33: Good Standing | X33: 2024-01-15 | Y33: Novel Enzyme Inhibitors in Malaria Parasite Metabolism | Z33: Writing | AA33: Not Yet | AC33: Prof. Margaret Wangari | AD33: Dr. Daniel Njomo (KEMRI, External) | AE33: MSc Biochemistry — Antimalarial Drug Discovery & Enzyme Inhibition | AF33: 45463 | AG33: Registered ✓ | Lit Review ✓ | Lab Work ✓ | Analysis ✓ | ⚠ CHALLENGE: Ch.3 Major Revision Required — Kinetic Model Error | Chs 1–2 Supervisor-Approved | AH33: ⚠ CASE-PG-001 ACTIVE: (1) Re-run Ch.3 kinetics using Hill Equation (not Michaelis-Menten) | (2) Secure interim co-supervisor (Dr. Ouma) | (3) Rebook LC-MS/MS (March 2024) | Revised viva: Oct 2024 | AI33: Conference Paper: E. Africa Biochem Symposium 2024 | ⚠ Viva postponed June → October 2024 due to Ch.3 major revision requirement | AJ33: Templumis University | AK33: No | AL33: No | AM33: None | AN33: None
A34: TU-PG-2022-0033 | B34: Ibrahim Hassan | C34: Male | D34: 1996-12-20 | E34: i.hassan@templumis.ac | F34: +251712345033 | G34: MSc by Research | H34: Computer Science | I34: School of Computing | J34: Year 2 | K34: 3.61 | L34: 24 | M34: Active | N34: Ethiopian | O34: 2022-09-05 | P34: 2025-06-30 | Q34: Postgraduate | R34: MSc by Research | S34: 3. Data Collection & Analysis Phase | T34: Research Year 2 | U34: Paid | V34: 0 | W34: Good Standing | X34: 2024-01-15 | Y34: AI-Based Crop Disease Detection Using UAV Imagery | Z34: Data Collection | AA34: Not Yet | AC34: Dr. Kamande Njoroge | AD34: Prof. James Mwema (School of Engineering) | AE34: MSc CS — Computer Vision & Precision Agriculture (UAV-Based Systems) | AF34: 45792 | AG34: Registered ✓ | Lit Review ✓ | ⚠ CHALLENGE: UAV Dataset 31% Unusable (345/500 images valid) | CNN Model Training PAUSED — Dataset rebuild + ethics amendment required | AH34: ⚠ CASE-PG-002 ACTIVE: (1) Ethics amendment: expand to Kakamega & Meru counties | (2) Recollect ≥700 images per revised UAV protocol | (3) Add YOLOv8/EfficientDet/ViT baselines + ablation study for paper revision | AI34: ⚠ AAAI Africa 2025 paper: Major Revisions Required — resubmitting to IEEE Access / CVPR Africa after dataset rebuild | Revised completion: November 2025 | AJ34: Templumis University | AK34: No | AL34: No | AM34: None | AN34: None
A35: TU-PG-2021-0034 | B35: Janet Akinyi | C35: Female | D35: 1994-08-11 | E35: j.akinyi@templumis.ac | F35: +254712345034 | G35: MA by Research | H35: Education | I35: School of Education | J35: Year 3 | K35: 3.48 | L35: 36 | M35: Active | N35: Kenyan | O35: 2021-09-06 | P35: 2024-06-30 | Q35: Postgraduate | R35: MA by Research | S35: 4. Thesis Writing Phase | T35: Research Year 3 | U35: Paid | V35: 0 | W35: Good Standing | X35: 2024-01-15 | Y35: Digital Pedagogy & Learning Outcomes in Kenyan Secondary Schools | Z35: Writing | AA35: Not Yet | AC35: Mr. Barasa Wekesa | AD35: Prof. Agnes Njeru (Ministry of Education, External) | AE35: MA Education — EdTech & Learning Outcomes in Kenyan Secondary Schools | AF35: 45534 | AG35: Registered ✓ | Literature Review ✓ | Fieldwork (12 schools) ✓ | Data Analysis ✓ | Chapters 1–4 Complete ✓ | AH35: Chapter 5 (Conclusions) + Final Submission (Target: August 2024) | AI35: Policy Brief submitted to Kenya Ministry of Education (February 2024) | AJ35: Templumis University | AK35: No | AL35: No | AM35: None | AN35: None
A36: TU-PG-2022-0035 | B36: Kenneth Osei | C36: Male | D36: 1995-05-17 | E36: k.osei@templumis.ac | F36: +233712345035 | G36: MSc by Research | H36: Mechanical Engineering | I36: School of Engineering | J36: Year 2 | K36: 3.31 | L36: 18 | M36: On Leave | N36: Ghanaian | O36: 2022-09-05 | P36: 2026-06-30 | Q36: Postgraduate | R36: MSc by Research | S36: ⏸ Deferred — On Leave (Research) | T36: Research Year 2 | U36: Deferred | V36: 0 | W36: Good Standing | X36: 2024-01-15 | Y36: Low-Cost Solar Desalination for Rural East Africa | Z36: Proposal Approved | AA36: Not Yet | AC36: Dr. Oloo Otiende | AD36: Dr. Marcus Kipande (University of Nairobi, External) | AE36: MSc Mechanical Engineering — Renewable Energy Systems & Rural Water Security | AF36: 46203 | AG36: Registered ✓ | Literature Review ✓ | Research Proposal Approved ✓ | AH36: Return from Leave (Est. Sep 2024) & Begin Prototype Development | AI36: N/A — On Leave; No Research Output Yet | AJ36: Templumis University | AK36: No | AL36: No | AM36: None | AN36: None
A37: TU-PG-2020-0036 | B37: Lydia Cheptoo | C37: Female | D37: 1993-06-23 | E37: l.cheptoo@templumis.ac | F37: +254712345036 | G37: MSc by Research | H37: Public Health | I37: School of Health Sciences | J37: Year 4 | K37: 3.91 | L37: 48 | M37: Graduated | N37: Kenyan | O37: 2020-09-07 | Q37: Postgraduate | R37: MSc by Research | S37: 6. Graduated ✓ (Research) | T37: Completed | U37: Cleared | V37: 0 | W37: Cleared | X37: 2023-11-01 | Y37: Community-Based Interventions for Maternal Health in Western Kenya | Z37: Defended & Approved | AA37: Approved | AB37: 2023-11-10 | AC37: Dr. Atieno Ouma | AD37: Prof. Grace Adhola (WHO Kenya, External) | AE37: MSc Public Health — Maternal & Child Health Interventions in SSA | AF37: 45915 | AG37: All Milestones Complete ✓ | Thesis Defended & Approved ✓ | Graduated | AH37: N/A — Graduated | AI37: Published: East African Medical Journal, 2025 (Vol. 102, Issue 3) | AJ37: Templumis University | AK37: No | AL37: No | AM37: None | AN37: None
A38: TU-PG-2023-0037 | B38: Moses Waweru | C38: Male | D38: 1997-01-08 | E38: m.waweru@templumis.ac | F38: +254712345037 | G38: MSc by Research | H38: Computer Science | I38: School of Computing | J38: Year 1 | K38: 3.52 | L38: 12 | M38: Active | N38: Kenyan | O38: 2023-09-04 | P38: 2026-06-30 | Q38: Postgraduate | R38: MSc by Research | S38: 2. Research Proposal Phase | T38: Research Year 1 | U38: Paid | V38: 0 | W38: Good Standing | X38: 2024-01-15 | Y38: Machine Learning for Swahili NLP Applications | Z38: Proposal Submitted | AA38: Not Yet | AC38: Dr. Kamande Njoroge | AD38: Ms. Cynthia Aluoch | AE38: MSc CS — Natural Language Processing for African Languages (Swahili) | AF38: 46203 | AG38: Registered ✓ | Topic Selection ✓ | Proposal Submitted (Pending Departmental Review) | AH38: Proposal Defense & Ethics Clearance (Target: April 2024) | AI38: N/A — Early Stage Research (Year 1) | AJ38: Templumis University | AK38: No | AL38: No | AM38: None | AN38: None
A39: TU-PHD-2021-0038 | B39: Amina Osei | C39: Female | D39: 33465 | E39: a.osei@templumis.ac | F39: +233712345038 | G39: PhD | H39: Computer Science | I39: School of Computing | J39: Year 3 | K39: 3.88 | L39: 36 | M39: Active | N39: Ghanaian | O39: 45175 | P39: 46203 | Q39: Postgraduate | R39: PhD by Research | S39: 5. Candidacy Confirmed — Data Collection Phase | T39: Research Year 3 | U39: Paid | V39: 0 | W39: Good Standing | X39: 45306 | Y39: Federated Learning for Privacy-Preserving Health Data Analytics in Sub-Saharan Africa | Z39: Data Collection | AA39: Not Yet | AC39: Dr. Kamande Njoroge | AD39: Prof. Ruth Mutua (Strathmore University, External) | AE39: Computer Science — Federated Learning, Privacy & mHealth in Africa | AF39: 46142 | AG39: Enrolled ✓ | Foundation CW ✓ | Proposal Defended ✓ | Candidacy Confirmed ✓ | FL Architecture Designed ✓ | Data Collection Ongoing (4 hospital sites) | AH39: Complete Hospital Data Collection & Begin Federated Model Training | AI39: Poster: African AI Summit 2024 | Working Paper: IEEE Trans. Medical Informatics (under review) | AJ39: Templumis University | AK39: No | AL39: No | AM39: None | AN39: None
A40: TU-PHD-2020-0039 | B40: Samuel Odhiambo | C40: Male | D40: 32954 | E40: s.odhiambo@templumis.ac | F40: +254712345039 | G40: PhD | H40: Public Health | I40: School of Health Sciences | J40: Year 4 | K40: 3.71 | L40: 48 | M40: Active | N40: Kenyan | O40: 45176 | P40: 46203 | Q40: Postgraduate | R40: PhD by Research | S40: 6. Thesis Writing Phase (Final) | T40: Research Year 4 | U40: Paid | V40: 0 | W40: Good Standing | X40: 45306 | Y40: Impact of Community Health Worker Integration on Under-5 Mortality Rates in Rural Kenya | Z40: Writing | AA40: Pending | AC40: Dr. Atieno Ouma | AD40: Dr. Rebecca Adero (WHO Kenya, External) | AE40: Public Health — Community Health Systems, Child Survival & Rural Health Delivery | AF40: 45930 | AG40: Enrolled ✓ | Foundation CW ✓ | Proposal Defended ✓ | Candidacy Confirmed ✓ | Fieldwork (14 counties, n=2,400) ✓ | Data Analysis ✓ | Chapters 1–4 Approved ✓ | AH40: Complete Chapter 5 (Conclusions & Policy Recommendations) + Submit Full Thesis Draft | AI40: Published: African J. Primary Health Care (2024) | Under Review: PLOS Global Health | AJ40: Templumis University | AK40: No | AL40: No | AM40: None | AN40: None
A41: TU-PHD-2023-0040 | B41: Fatima Al-Rashid | C41: Female | D41: 34303 | E41: f.al-rashid@templumis.ac | F41: +249712345040 | G41: PhD | H41: Economics | I41: School of Business | J41: Year 1 | K41: 3.65 | L41: 12 | M41: Active | N41: Sudanese | O41: 45173 | P41: 46203 | Q41: Postgraduate | R41: PhD by Research | S41: 2. Research Proposal Writing | T41: Research Year 1 | U41: Paid | V41: 0 | W41: Good Standing | X41: 45306 | Y41: FDI, Structural Transformation & Inclusive Growth in East Africa: A Panel Data Analysis | Z41: Proposal Writing | AA41: Not Yet | AC41: Prof. Wambua Simiyu | AD41: Dr. Emmanuel Kiprotich (IMF Africa Division, External) | AE41: Economics — International Economics, Structural Change & Panel Econometrics | AF41: 46203 | AG41: Enrolled ✓ | Foundation CW (PHD701 ✓) | Systematic Lit Review 60% ✓ | Research Proposal Draft 40% In Progress | AH41: Submit Full Research Proposal to Departmental Committee (Target: April 2024) | AI41: N/A — Year 1, Foundation Phase | AJ41: Templumis University | AK41: No | AL41: No | AM41: None | AN41: None
A42: TU-PHD-2022-0041 | B42: Peter Kamau Njeru | C42: Male | D42: 32646 | E42: p.njeru@templumis.ac | F42: +254712345041 | G42: PhD | H42: Environmental Science | I42: School of Science | J42: Year 2 | K42: 3.42 | L42: 24 | M42: Active | N42: Kenyan | O42: 45540 | P42: 46203 | Q42: Postgraduate | R42: PhD by Research | S42: 3. Proposal Defense — Pre-Candidacy Phase | T42: Research Year 2 | U42: Paid | V42: 0 | W42: Good Standing | X42: 45306 | Y42: Carbon Sequestration Potential of Afromontane Forests: Evidence from Central Kenya | Z42: Proposal Submitted — Awaiting Defense | AA42: Not Yet | AC42: Dr. Sasha Mutinda | AD42: Dr. Osei Kwame (UNEP Kenya, External) | AE42: Environmental Science — Carbon Science, Forest Ecology & Climate Change Mitigation | AF42: 46387 | AG42: Enrolled ✓ | Foundation CW ✓ | Systematic Lit Review ✓ | Proposal Submitted (Dept Review) | Pilot Site Identified (Aberdares Forest Reserve, 500ha) | AH42: Proposal Defense (Target: March 2024) + Ethics Clearance Application | AI42: N/A — Year 2, Pre-Candidacy Phase | AJ42: Templumis University | AK42: No | AL42: No | AM42: None | AN42: None
A43: KT-2021-0001 | B43: Yusuf Al-Farsi | C43: Male | D43: 2001-02-11 | E43: y.al-farsi@kitaptech.com | F43: +966712345001 | G43: BSc | H43: Computer Science | I43: School of Computer Science | J43: Year 3 | K43: 3.71 | L43: 92 | M43: Active | N43: Saudi Arabian | O43: 2021-09-02 | P43: 2025-06-30 | Q43: Undergraduate | R43: BSc | S43: 3. Progressing — Year 3 | T43: Sem 6 | U43: Paid | V43: 0 | W43: Good Standing | X43: 2024-01-15 | Y43: N/A | Z43: N/A | AA43: Not Yet | AJ43: Kitaptech University | AK43: No | AL43: No | AM43: None | AN43: None
A44: KT-2022-0002 | B44: Fatima Al-Sayed | C44: Female | D44: 2002-06-24 | E44: f.al-sayed@kitaptech.com | F44: +971712345002 | G44: BSc | H44: Software Engineering | I44: School of Software Engineering | J44: Year 2 | K44: 3.18 | L44: 67 | M44: Active | N44: Emirati | O44: 2022-09-04 | P44: 2026-06-30 | Q44: Undergraduate | R44: BSc | S44: 2. Progressing — Year 2 | T44: Sem 4 | U44: Paid | V44: 0 | W44: Good Standing | X44: 2024-01-15 | Y44: N/A | Z44: N/A | AA44: Not Yet | AJ44: Kitaptech University | AK44: No | AL44: No | AM44: None | AN44: None
A45: KT-2020-0003 | B45: Omar Haddad | C45: Male | D45: 2000-10-03 | E45: o.haddad@kitaptech.com | F45: +962712345003 | G45: BSc | H45: Information Technology | I45: School of Information Technology & Cybersecurity | J45: Year 4 | K45: 3.49 | L45: 129 | M45: Active | N45: Jordanian | O45: 2020-09-05 | P45: 2024-06-30 | Q45: Undergraduate | R45: BSc | S45: 4. Final Year — Pre-Clearance | T45: Sem 8 | U45: Paid | V45: 0 | W45: Good Standing | X45: 2024-01-15 | Y45: N/A | Z45: N/A | AA45: In Progress | AJ45: Kitaptech University | AK45: No | AL45: Yes | AM45: Hearing Impairment | AN45: Sign-language interpreter; note-taking support
A46: KT-2020-0004 | B46: Layla Mansour | C46: Female | D46: 1999-04-19 | E46: l.mansour@kitaptech.com | F46: +961712345004 | G46: BSc | H46: Data Science | I46: School of Data Science & Artificial Intelligence | J46: Year 4 | K46: 3.92 | L46: 127 | M46: Graduated | N46: Lebanese | O46: 2020-09-06 | Q46: Undergraduate | R46: BSc | S46: 6. Graduated ✓ | T46: Completed | U46: Cleared | V46: 0 | W46: Cleared | X46: 2024-01-15 | Y46: N/A | Z46: N/A | AA46: Approved | AB46: 2023-11-10 | AJ46: Kitaptech University | AK46: No | AL46: No | AM46: None | AN46: None
A47: KT-2023-0005 | B47: Khalid Nasser | C47: Male | D47: 2003-08-30 | E47: k.nasser@kitaptech.com | F47: +974712345005 | G47: BSc | H47: Cybersecurity | I47: School of Information Technology & Cybersecurity | J47: Year 1 | K47: 2.38 | L47: 23 | M47: Probation | N47: Qatari | O47: 2023-09-07 | P47: 2027-06-30 | Q47: Undergraduate | R47: BSc | S47: ⚠ Academic Review — Probation | T47: Sem 2 | U47: Partial | V47: 35000 | W47: Probation | X47: 2023-12-01 | Y47: N/A | Z47: N/A | AA47: Blocked | AJ47: Kitaptech University | AK47: No | AL47: No | AM47: None | AN47: None
A48: KT-2021-0006 | B48: Rania Saleh | C48: Female | D48: 2001-01-17 | E48: r.saleh@kitaptech.com | F48: +20712345006 | G48: BSc | H48: Computer Science | I48: School of Computer Science | J48: Year 3 | K48: 3.27 | L48: 100 | M48: Active | N48: Egyptian | O48: 2021-09-02 | P48: 2025-06-30 | Q48: Undergraduate | R48: BSc | S48: 3. Progressing — Year 3 | T48: Sem 6 | U48: Paid | V48: 0 | W48: Good Standing | X48: 2024-01-15 | Y48: N/A | Z48: N/A | AA48: Not Yet | AJ48: Kitaptech University | AK48: No | AL48: No | AM48: None | AN48: None
A49: KT-2022-0007 | B49: Hamza Zidane | C49: Male | D49: 2002-09-12 | E49: h.zidane@kitaptech.com | F49: +213712345007 | G49: BSc | H49: Financial Technology | I49: School of Digital Business & Financial Technology | J49: Year 2 | K49: 3.61 | L49: 66 | M49: Active | N49: Algerian | O49: 2022-09-04 | P49: 2026-06-30 | Q49: Undergraduate | R49: BSc | S49: 2. Progressing — Year 2 | T49: Sem 4 | U49: Paid | V49: 0 | W49: Good Standing | X49: 2024-01-15 | Y49: N/A | Z49: N/A | AA49: Not Yet | AJ49: Kitaptech University | AK49: No | AL49: No | AM49: None | AN49: None
A50: KT-2020-0008 | B50: Noor Al-Amin | C50: Female | D50: 2000-05-02 | E50: n.al-amin@kitaptech.com | F50: +965712345008 | G50: BSc | H50: Software Engineering | I50: School of Software Engineering | J50: Year 4 | K50: 3.15 | L50: 128 | M50: Active | N50: Kuwaiti | O50: 2020-09-05 | P50: 2024-06-30 | Q50: Undergraduate | R50: BSc | S50: 4. Final Year — Pre-Clearance | T50: Sem 8 | U50: Paid | V50: 0 | W50: Good Standing | X50: 2024-01-15 | Y50: N/A | Z50: N/A | AA50: In Progress | AJ50: Kitaptech University | AK50: No | AL50: No | AM50: None | AN50: None
A51: KT-2021-0009 | B51: Bilal Qureshi | C51: Male | D51: 2001-11-27 | E51: b.qureshi@kitaptech.com | F51: +970712345009 | G51: BSc | H51: Data Science | I51: School of Data Science & Artificial Intelligence | J51: Year 3 | K51: 2.73 | L51: 90 | M51: On Leave | N51: Palestinian | O51: 2021-09-06 | P51: 2025-06-30 | Q51: Undergraduate | R51: BSc | S51: ⏸ Deferred — On Leave | T51: Sem 6 | U51: Deferred | V51: 0 | W51: Good Standing | X51: 2024-01-15 | Y51: N/A | Z51: N/A | AA51: Not Yet | AJ51: Kitaptech University | AK51: No | AL51: No | AM51: None | AN51: None
A52: KT-2023-0010 | B52: Sami Hijazi | C52: Male | D52: 2003-03-08 | E52: s.hijazi@kitaptech.com | F52: +963712345010 | G52: BSc | H52: Information Technology | I52: School of Information Technology & Cybersecurity | J52: Year 1 | K52: 3.38 | L52: 28 | M52: Active | N52: Syrian | O52: 2023-09-07 | P52: 2027-06-30 | Q52: Undergraduate | R52: BSc | S52: 1. Enrolled & Orientated | T52: Sem 2 | U52: Paid | V52: 0 | W52: Good Standing | X52: 2024-01-15 | Y52: N/A | Z52: N/A | AA52: Not Yet | AJ52: Kitaptech University | AK52: No | AL52: No | AM52: None | AN52: None
A53: KT-2022-0011 | B53: Dalia Abdullah | C53: Female | D53: 2002-07-21 | E53: d.abdullah@kitaptech.com | F53: +968712345011 | G53: BSc | H53: Computer Science | I53: School of Computer Science | J53: Year 2 | K53: 3.02 | L53: 67 | M53: Active | N53: Omani | O53: 2022-09-02 | P53: 2026-06-30 | Q53: Undergraduate | R53: BSc | S53: 2. Progressing — Year 2 | T53: Sem 4 | U53: Paid | V53: 0 | W53: Good Standing | X53: 2024-01-15 | Y53: N/A | Z53: N/A | AA53: Not Yet | AJ53: Kitaptech University | AK53: No | AL53: No | AM53: None | AN53: None
A54: KT-2020-0012 | B54: Tariq Al-Otaibi | C54: Male | D54: 1999-12-14 | E54: t.al-otaibi@kitaptech.com | F54: +966712345012 | G54: BSc | H54: Software Engineering | I54: School of Software Engineering | J54: Year 4 | K54: 2.58 | L54: 129 | M54: Graduated | N54: Saudi Arabian | O54: 2020-09-04 | Q54: Undergraduate | R54: BSc | S54: 6. Graduated ✓ | T54: Completed | U54: Cleared | V54: 0 | W54: Cleared | X54: 2024-01-15 | Y54: N/A | Z54: N/A | AA54: Approved | AB54: 2023-11-10 | AJ54: Kitaptech University | AK54: No | AL54: No | AM54: None | AN54: None
A55: KT-2021-0013 | B55: Maryam Karam | C55: Female | D55: 2001-06-09 | E55: m.karam@kitaptech.com | F55: +964712345013 | G55: BSc | H55: Cybersecurity | I55: School of Information Technology & Cybersecurity | J55: Year 3 | K55: 3.55 | L55: 95 | M55: Active | N55: Iraqi | O55: 2021-09-05 | P55: 2025-06-30 | Q55: Undergraduate | R55: BSc | S55: 3. Progressing — Year 3 | T55: Sem 6 | U55: Paid | V55: 0 | W55: Good Standing | X55: 2024-01-15 | Y55: N/A | Z55: N/A | AA55: Not Yet | AJ55: Kitaptech University | AK55: No | AL55: No | AM55: None | AN55: None
A56: KT-2020-0014 | B56: Faisal Al-Mutairi | C56: Male | D56: 2000-02-28 | E56: f.al-mutairi@kitaptech.com | F56: +965712345014 | G56: BSc | H56: Financial Technology | I56: School of Digital Business & Financial Technology | J56: Year 4 | K56: 1.92 | L56: 119 | M56: Suspended | N56: Kuwaiti | O56: 2020-09-06 | P56: 2024-06-30 | Q56: Undergraduate | R56: BSc | S56: ⚠ Academic Hold — Suspended | T56: Sem 8 | U56: Overdue | V56: 75000 | W56: Suspended | X56: 2023-12-01 | Y56: N/A | Z56: N/A | AA56: Blocked | AJ56: Kitaptech University | AK56: No | AL56: No | AM56: None | AN56: None
A57: KT-2023-0015 | B57: Huda Shammari | C57: Female | D57: 2003-10-05 | E57: h.shammari@kitaptech.com | F57: +966712345015 | G57: BSc | H57: Data Science | I57: School of Data Science & Artificial Intelligence | J57: Year 1 | K57: 3.79 | L57: 36 | M57: Active | N57: Saudi Arabian | O57: 2023-09-07 | P57: 2027-06-30 | Q57: Undergraduate | R57: BSc | S57: 1. Enrolled & Orientated | T57: Sem 2 | U57: Paid | V57: 0 | W57: Good Standing | X57: 2024-01-15 | Y57: N/A | Z57: N/A | AA57: Not Yet | AJ57: Kitaptech University | AK57: No | AL57: No | AM57: None | AN57: None
A58: KT-2021-0016 | B58: Ahmed Al-Masri | C58: Male | D58: 2001-08-16 | E58: a.al-masri@kitaptech.com | F58: +20712345016 | G58: BSc | H58: Computer Science | I58: School of Computer Science | J58: Year 3 | K58: 3.11 | L58: 98 | M58: Active | N58: Egyptian | O58: 2021-09-02 | P58: 2025-06-30 | Q58: Undergraduate | R58: BSc | S58: 3. Progressing — Year 3 | T58: Sem 6 | U58: Paid | V58: 0 | W58: Good Standing | X58: 2024-01-15 | Y58: N/A | Z58: N/A | AA58: Not Yet | AJ58: Kitaptech University | AK58: No | AL58: No | AM58: None | AN58: None
A59: KT-2022-0017 | B59: Yasmin Qasim | C59: Female | D59: 2002-03-22 | E59: y.qasim@kitaptech.com | F59: +962712345017 | G59: BSc | H59: Information Technology | I59: School of Information Technology & Cybersecurity | J59: Year 2 | K59: 3.64 | L59: 64 | M59: Active | N59: Jordanian | O59: 2022-09-04 | P59: 2026-06-30 | Q59: Undergraduate | R59: BSc | S59: 2. Progressing — Year 2 | T59: Sem 4 | U59: Paid | V59: 0 | W59: Good Standing | X59: 2024-01-15 | Y59: N/A | Z59: N/A | AA59: Not Yet | AJ59: Kitaptech University | AK59: No | AL59: No | AM59: None | AN59: None
A60: KT-2020-0018 | B60: Karim Hamdan | C60: Male | D60: 2000-09-09 | E60: k.hamdan@kitaptech.com | F60: +961712345018 | G60: BSc | H60: Software Engineering | I60: School of Software Engineering | J60: Year 4 | K60: 3.05 | L60: 126 | M60: Active | N60: Lebanese | O60: 2020-09-05 | P60: 2024-06-30 | Q60: Undergraduate | R60: BSc | S60: 4. Final Year — Pre-Clearance | T60: Sem 8 | U60: Paid | V60: 0 | W60: Good Standing | X60: 2024-01-15 | Y60: N/A | Z60: N/A | AA60: In Progress | AJ60: Kitaptech University | AK60: No | AL60: Yes | AM60: Chronic Illness (Epilepsy) | AN60: Modified exam schedule for medical appointments; rest breaks
A61: KT-2021-0019 | B61: Zainab Al-Rashid | C61: Female | D61: 2001-05-13 | E61: z.al-rashid@kitaptech.com | F61: +973712345019 | G61: BSc | H61: Financial Technology | I61: School of Digital Business & Financial Technology | J61: Year 3 | K61: 3.44 | L61: 92 | M61: Active | N61: Bahraini | O61: 2021-09-06 | P61: 2025-06-30 | Q61: Undergraduate | R61: BSc | S61: 3. Progressing — Year 3 | T61: Sem 6 | U61: Paid | V61: 0 | W61: Good Standing | X61: 2024-01-15 | Y61: N/A | Z61: N/A | AA61: Not Yet | AJ61: Kitaptech University | AK61: No | AL61: No | AM61: None | AN61: None
A62: KT-2023-0020 | B62: Hassan Mansour | C62: Male | D62: 2003-01-30 | E62: h.mansour@kitaptech.com | F62: +967712345020 | G62: BSc | H62: Computer Science | I62: School of Computer Science | J62: Year 1 | K62: 2.21 | L62: 29 | M62: Probation | N62: Yemeni | O62: 2023-09-07 | P62: 2027-06-30 | Q62: Undergraduate | R62: BSc | S62: ⚠ Academic Review — Probation | T62: Sem 2 | U62: Partial | V62: 35000 | W62: Probation | X62: 2023-12-01 | Y62: N/A | Z62: N/A | AA62: Blocked | AJ62: Kitaptech University | AK62: No | AL62: No | AM62: None | AN62: None
A63: KT-2022-0021 | B63: Salma Nasser | C63: Female | D63: 2002-11-02 | E63: s.nasser@kitaptech.com | F63: +216712345021 | G63: BSc | H63: Cybersecurity | I63: School of Information Technology & Cybersecurity | J63: Year 2 | K63: 3.59 | L63: 65 | M63: Active | N63: Tunisian | O63: 2022-09-02 | P63: 2026-06-30 | Q63: Undergraduate | R63: BSc | S63: 2. Progressing — Year 2 | T63: Sem 4 | U63: Paid | V63: 0 | W63: Good Standing | X63: 2024-01-15 | Y63: N/A | Z63: N/A | AA63: Not Yet | AJ63: Kitaptech University | AK63: No | AL63: No | AM63: None | AN63: None
A64: KT-2020-0022 | B64: Ali Abdullah | C64: Male | D64: 1999-07-18 | E64: a.abdullah@kitaptech.com | F64: +212712345022 | G64: BSc | H64: Data Science | I64: School of Data Science & Artificial Intelligence | J64: Year 4 | K64: 3.67 | L64: 127 | M64: Active | N64: Moroccan | O64: 2020-09-04 | P64: 2024-06-30 | Q64: Undergraduate | R64: BSc | S64: 4. Final Year — Pre-Clearance | T64: Sem 8 | U64: Paid | V64: 0 | W64: Good Standing | X64: 2024-01-15 | Y64: N/A | Z64: N/A | AA64: In Progress | AJ64: Kitaptech University | AK64: No | AL64: No | AM64: None | AN64: None
A65: KT-2021-0023 | B65: Reem Al-Farsi | C65: Female | D65: 2001-04-06 | E65: r.al-farsi@kitaptech.com | F65: +971712345023 | G65: BSc | H65: Software Engineering | I65: School of Software Engineering | J65: Year 3 | K65: 2.84 | L65: 89 | M65: On Leave | N65: Emirati | O65: 2021-09-05 | P65: 2025-06-30 | Q65: Undergraduate | R65: BSc | S65: ⏸ Deferred — On Leave | T65: Sem 6 | U65: Deferred | V65: 0 | W65: Good Standing | X65: 2024-01-15 | Y65: N/A | Z65: N/A | AA65: Not Yet | AJ65: Kitaptech University | AK65: No | AL65: No | AM65: None | AN65: None
A66: KT-2022-0024 | B66: Mohammed Khalil | C66: Male | D66: 2002-12-23 | E66: m.khalil@kitaptech.com | F66: +974712345024 | G66: BSc | H66: Information Technology | I66: School of Information Technology & Cybersecurity | J66: Year 2 | K66: 3.36 | L66: 68 | M66: Active | N66: Qatari | O66: 2022-09-06 | P66: 2026-06-30 | Q66: Undergraduate | R66: BSc | S66: 2. Progressing — Year 2 | T66: Sem 4 | U66: Paid | V66: 0 | W66: Good Standing | X66: 2024-01-15 | Y66: N/A | Z66: N/A | AA66: Not Yet | AJ66: Kitaptech University | AK66: No | AL66: No | AM66: None | AN66: None
A67: KT-2023-0025 | B67: Lina Haddad | C67: Female | D67: 2003-02-14 | E67: l.haddad@kitaptech.com | F67: +962712345025 | G67: BSc | H67: Computer Science | I67: School of Computer Science | J67: Year 1 | K67: 3.58 | L67: 34 | M67: Active | N67: Jordanian | O67: 2023-09-07 | P67: 2027-06-30 | Q67: Undergraduate | R67: BSc | S67: 1. Enrolled & Orientated | T67: Sem 2 | U67: Paid | V67: 0 | W67: Good Standing | X67: 2024-01-15 | Y67: N/A | Z67: N/A | AA67: Not Yet | AJ67: Kitaptech University | AK67: No | AL67: No | AM67: None | AN67: None
A68: KT-PG-2022-0026 | B68: Nadia Saleh | C68: Female | D68: 1996-03-11 | E68: n.saleh@kitaptech.com | F68: +20712345026 | G68: MSc | H68: Artificial Intelligence | I68: School of Data Science & Artificial Intelligence | J68: Year 2 | K68: 3.69 | L68: 48 | M68: Active | N68: Egyptian | O68: 2022-09-02 | P68: 2024-06-30 | Q68: Postgraduate | R68: MSc (Coursework) | S68: 3. PG Final Semester — Pre-Graduation | T68: Sem 4 | U68: Paid | V68: 0 | W68: Good Standing | X68: 2024-01-15 | Y68: N/A | Z68: N/A | AA68: In Progress | AC68: Dr. Samir Al-Balawi | AD68: N/A | AE68: AI — Applied Machine Learning for Arabic NLP | AF68: 2024-06-30 | AG68: Coursework Yr1 ✓ | Yr2 ✓ | Capstone Proposal Approved ✓ | AH68: Final Capstone Report Submission | AI68: N/A (Coursework Track) | AJ68: Kitaptech University | AK68: No | AL68: No | AM68: None | AN68: None
A69: KT-PG-2023-0027 | B69: Rashid Al-Amin | C69: Male | D69: 1994-07-19 | E69: r.al-amin@kitaptech.com | F69: +966712345027 | G69: MBA | H69: Technology Management | I69: School of Digital Business & Financial Technology | J69: Year 1 | K69: 3.35 | L69: 24 | M69: Active | N69: Saudi Arabian | O69: 2023-09-04 | P69: 2025-06-30 | Q69: Postgraduate | R69: MBA (Coursework) | S69: 1. PG Enrolled — Coursework Phase | T69: Sem 2 | U69: Paid | V69: 0 | W69: Good Standing | X69: 2024-01-15 | Y69: N/A | Z69: N/A | AA69: Not Yet | AC69: Dr. Huda Ibrahim | AD69: N/A | AE69: Tech Management — Digital Transformation & FinTech Strategy | AF69: 2025-06-30 | AG69: Orientation ✓ | Semester 1 Coursework ✓ | AH69: Semester 2 Coursework Completion | AI69: N/A (Coursework Phase) | AJ69: Kitaptech University | AK69: No | AL69: No | AM69: None | AN69: None
A70: KT-PG-2022-0028 | B70: Dina Khalil | C70: Female | D70: 1995-11-02 | E70: d.khalil@kitaptech.com | F70: +961712345028 | G70: MSc | H70: Cybersecurity | I70: School of Information Technology & Cybersecurity | J70: Year 2 | K70: 3.58 | L70: 52 | M70: Graduated | N70: Lebanese | O70: 2022-09-05 | Q70: Postgraduate | R70: MSc (Coursework) | S70: 4. Graduated ✓ | T70: Completed | U70: Cleared | V70: 0 | W70: Cleared | X70: 2023-11-01 | Y70: N/A | Z70: N/A | AA70: Approved | AB70: 2023-11-10 | AC70: Dr. Adel Karam | AD70: N/A | AE70: Cybersecurity — Critical Infrastructure Protection | AF70: 2024-06-30 | AG70: Coursework Yr1 ✓ | Yr2 ✓ | Capstone Proposal Approved ✓ | AH70: N/A — Graduated | AI70: Capstone: Critical Infrastructure Protection (Completed) | AJ70: Kitaptech University | AK70: No | AL70: No | AM70: None | AN70: None
A71: KT-PG-2023-0029 | B71: Waleed Hamdan | C71: Male | D71: 1997-04-27 | E71: w.hamdan@kitaptech.com | F71: +962712345029 | G71: MSc | H71: Software Engineering | I71: School of Software Engineering | J71: Year 1 | K71: 2.77 | L71: 20 | M71: Probation | N71: Jordanian | O71: 2023-09-06 | P71: 2025-06-30 | Q71: Postgraduate | R71: MSc (Coursework) | S71: ⚠ Academic Review — Probation | T71: Sem 2 | U71: Partial | V71: 35000 | W71: Probation | X71: 2023-12-01 | Y71: N/A | Z71: N/A | AA71: Blocked | AC71: Dr. Samar Odeh | AD71: N/A | AE71: Software Engineering — DevSecOps & Cloud-Native Architectures | AF71: 2025-06-30 | AG71: Orientation ✓ | Semester 1 Completed (Probation) | AH71: Semester 2 — Achieve GPA ≥ 3.00 to Continue (MSc Software Engineering) | AI71: N/A — Academic Review Phase | AJ71: Kitaptech University | AK71: No | AL71: No | AM71: None | AN71: None
A72: KT-PG-2022-0030 | B72: Amal Qasim | C72: Female | D72: 1996-09-08 | E72: a.qasim@kitaptech.com | F72: +216712345030 | G72: MSc | H72: Data Science | I72: School of Data Science & Artificial Intelligence | J72: Year 2 | K72: 3.62 | L72: 48 | M72: Active | N72: Tunisian | O72: 2022-09-07 | P72: 2024-06-30 | Q72: Postgraduate | R72: MSc (Coursework) | S72: 3. PG Final Semester — Pre-Graduation | T72: Sem 4 | U72: Paid | V72: 0 | W72: Good Standing | X72: 2024-01-15 | Y72: N/A | Z72: N/A | AA72: In Progress | AC72: Dr. Samir Al-Balawi | AD72: Prof. Nour Kassem (School of Digital Business & FinTech) | AE72: Data Science — Predictive Analytics for Fintech Risk Scoring | AF72: 2024-06-30 | AG72: Coursework Yr1 ✓ | Yr2 ✓ | Capstone Proposal Approved ✓ | AH72: Final Capstone Report Submission | AI72: N/A (Coursework Track) | AJ72: Kitaptech University | AK72: No | AL72: No | AM72: None | AN72: None
A73: KT-PG-2023-0031 | B73: Jamal Al-Otaibi | C73: Male | D73: 1993-01-15 | E73: j.al-otaibi@kitaptech.com | F73: +965712345031 | G73: MBA | H73: Technology Management | I73: School of Digital Business & Financial Technology | J73: Year 1 | K73: 3.24 | L73: 24 | M73: Active | N73: Kuwaiti | O73: 2023-09-02 | P73: 2025-06-30 | Q73: Postgraduate | R73: MBA (Coursework) | S73: 1. PG Enrolled — Coursework Phase | T73: Sem 2 | U73: Paid | V73: 0 | W73: Good Standing | X73: 2024-01-15 | Y73: N/A | Z73: N/A | AA73: Not Yet | AC73: Dr. Huda Ibrahim | AD73: N/A | AE73: Tech Management — AI Adoption in Gulf Banking Sector | AF73: 2025-06-30 | AG73: Orientation ✓ | Semester 1 Coursework ✓ | AH73: Semester 2 Coursework Completion | AI73: N/A (Coursework Phase) | AJ73: Kitaptech University | AK73: No | AL73: No | AM73: None | AN73: None
A74: KT-PG-2021-0032 | B74: Samira Haddad | C74: Female | D74: 1995-06-03 | E74: s.haddad@kitaptech.com | F74: +963712345032 | G74: MSc | H74: Data Science | I74: School of Data Science & Artificial Intelligence | J74: Year 3 | K74: 3.84 | L74: 36 | M74: Active | N74: Syrian | O74: 2021-09-02 | P74: 2024-06-30 | Q74: Postgraduate | R74: MSc by Research | S74: 4. Thesis Writing Phase | T74: Research Year 3 | U74: Paid | V74: 0 | W74: Good Standing | X74: 2024-01-15 | Y74: Arabic Dialect Identification Using Transformer-Based Deep Learning | Z74: Writing | AA74: Not Yet | AC74: Prof. Nour Kassem | AD74: Dr. Leila Sabbagh (KAUST, External) | AE74: Data Science — Arabic NLP & Dialectal Speech Processing | AF74: 2024-06-30 | AG74: Registered ✓ | Lit Review ✓ | Proposal Approved ✓ | Fieldwork Underway | AH74: Complete Analysis & Begin Thesis Writing | AI74: Working paper in preparation — Arabic NLP & Dialectal Speech Processing | AJ74: Kitaptech University | AK74: No | AL74: No | AM74: None | AN74: None
A75: KT-PG-2022-0033 | B75: Anwar Mutairi | C75: Male | D75: 1996-12-21 | E75: a.mutairi@kitaptech.com | F75: +974712345033 | G75: MSc | H75: Computer Science | I75: School of Computer Science | J75: Year 2 | K75: 3.47 | L75: 24 | M75: Active | N75: Qatari | O75: 2022-09-04 | P75: 2025-06-30 | Q75: Postgraduate | R75: MSc by Research | S75: 3. Data Collection & Analysis Phase | T75: Research Year 2 | U75: Paid | V75: 0 | W75: Good Standing | X75: 2024-01-15 | Y75: Edge-Computing Architectures for Real-Time Fraud Detection in Mobile Payments | Z75: Data Collection | AA75: Not Yet | AC75: Dr. Karim Badawi | AD75: Dr. Rafiq Qadri (MBZUAI, External) | AE75: Computer Science — Edge AI & FinTech Security | AF75: 2025-06-30 | AG75: Registered ✓ | Literature Review ✓ | Research Proposal Approved ✓ | AH75: Complete Data Collection & Begin Analysis | AI75: Working paper in preparation — Edge AI & FinTech Security | AJ75: Kitaptech University | AK75: No | AL75: No | AM75: None | AN75: None
A76: KT-PG-2021-0034 | B76: Samar Odeh | C76: Female | D76: 1994-08-09 | E76: s.odeh@kitaptech.com | F76: +970712345034 | G76: MA | H76: Information Systems | I76: School of Information Technology & Cybersecurity | J76: Year 3 | K76: 3.51 | L76: 36 | M76: Active | N76: Palestinian | O76: 2021-09-05 | P76: 2024-06-30 | Q76: Postgraduate | R76: MA by Research | S76: 4. Thesis Writing Phase | T76: Research Year 3 | U76: Paid | V76: 0 | W76: Good Standing | X76: 2024-01-15 | Y76: Digital Inclusion & E-Government Adoption Among Arab Youth | Z76: Writing | AA76: Not Yet | AC76: Dr. Adel Karam | AD76: Prof. Yasir Mansoor (Qatar University, External) | AE76: Information Systems — Digital Government & Youth Digital Inclusion | AF76: 2024-06-30 | AG76: Registered ✓ | Lit Review ✓ | Proposal Approved ✓ | Fieldwork Underway | AH76: Complete Analysis & Begin Thesis Writing | AI76: Working paper in preparation — Digital Government & Youth Digital Inclusion | AJ76: Kitaptech University | AK76: No | AL76: No | AM76: None | AN76: None
A77: KT-PG-2022-0035 | B77: Bassam Najjar | C77: Male | D77: 1995-05-17 | E77: b.najjar@kitaptech.com | F77: +212712345035 | G77: MSc | H77: Cybersecurity | I77: School of Information Technology & Cybersecurity | J77: Year 2 | K77: 3.29 | L77: 18 | M77: On Leave | N77: Moroccan | O77: 2022-09-06 | P77: 2025-06-30 | Q77: Postgraduate | R77: MSc by Research | S77: ⏸ Deferred — On Leave (Research) | T77: Research Year 2 | U77: Deferred | V77: 0 | W77: Good Standing | X77: 2024-01-15 | Y77: Threat Intelligence Sharing Frameworks for GCC Financial Institutions | Z77: Data Collection | AA77: Not Yet | AC77: Dr. Adel Karam | AD77: N/A | AE77: Cybersecurity — Threat Intelligence & Financial Sector Resilience | AF77: 2025-06-30 | AG77: Registered ✓ | Literature Review ✓ | Research Proposal Approved ✓ | AH77: Return from Leave & Resume Fieldwork | AI77: N/A — On Leave; No Research Output Yet | AJ77: Kitaptech University | AK77: No | AL77: No | AM77: None | AN77: None
A78: KT-PG-2020-0036 | B78: Hanan Zahran | C78: Female | D78: 1993-06-23 | E78: h.zahran@kitaptech.com | F78: +967712345036 | G78: MSc | H78: Data Science | I78: School of Data Science & Artificial Intelligence | J78: Year 4 | K78: 3.88 | L78: 48 | M78: Graduated | N78: Yemeni | O78: 2020-09-07 | Q78: Postgraduate | R78: MSc by Research | S78: 6. Graduated ✓ (Research) | T78: Completed | U78: Cleared | V78: 0 | W78: Cleared | X78: 2023-11-01 | Y78: Satellite Imagery & Deep Learning for Water Scarcity Monitoring in Arid Regions | Z78: Defended & Approved | AA78: Approved | AB78: 2023-11-10 | AC78: Dr. Samir Al-Balawi | AD78: Prof. Leila Sabbagh (KAUST, External) | AE78: Data Science — Remote Sensing & Climate Resilience | AF78: 2023-06-30 | AG78: All Milestones Complete ✓ | Thesis Defended & Approved ✓ | Graduated | AH78: N/A — Graduated | AI78: Thesis published / archived — Remote Sensing & Climate Resilience | AJ78: Kitaptech University | AK78: No | AL78: No | AM78: None | AN78: None
A79: KT-PG-2023-0037 | B79: Marwan Saad | C79: Male | D79: 1997-01-08 | E79: m.saad@kitaptech.com | F79: +973712345037 | G79: MSc | H79: Computer Science | I79: School of Computer Science | J79: Year 1 | K79: 3.49 | L79: 12 | M79: Active | N79: Bahraini | O79: 2023-09-02 | P79: 2026-06-30 | Q79: Postgraduate | R79: MSc by Research | S79: 2. Research Proposal Phase | T79: Research Year 1 | U79: Paid | V79: 0 | W79: Good Standing | X79: 2024-01-15 | Y79: Federated Learning for Cross-Border Mobile Money Fraud Detection | Z79: Proposal Submitted | AA79: Not Yet | AC79: Dr. Karim Badawi | AD79: N/A | AE79: Computer Science — Federated Learning & Cross-Border FinTech | AF79: 2026-06-30 | AG79: Registered ✓ | Topic Selection ✓ | Proposal Submitted (Pending Departmental Review) | AH79: Proposal Defense & Ethics Clearance | AI79: N/A — Early-Stage Research | AJ79: Kitaptech University | AK79: No | AL79: No | AM79: None | AN79: None
A80: KT-PHD-2021-0038 | B80: Nabil Farouk | C80: Male | D80: 1990-02-19 | E80: n.farouk@kitaptech.com | F80: +20712345038 | G80: PhD | H80: Computer Science | I80: School of Computer Science | J80: Year 3 | K80: 3.81 | L80: 36 | M80: Active | N80: Egyptian | O80: 2021-09-02 | P80: 2025-06-30 | Q80: Postgraduate | R80: PhD by Research | S80: 5. Candidacy Confirmed — Data Collection Phase | T80: Research Year 3 | U80: Paid | V80: 0 | W80: Good Standing | X80: 2024-01-15 | Y80: Explainable AI for Credit Risk Assessment in Underbanked GCC Populations | Z80: Data Collection | AA80: Not Yet | AC80: Dr. Karim Badawi | AD80: Prof. Aisha Rahman (MBZUAI, External) | AE80: Computer Science — Explainable AI & Financial Inclusion | AF80: 2025-06-30 | AG80: Enrolled ✓ | Foundation CW ✓ | Proposal Defended ✓ | Candidacy Confirmed ✓ | Data Collection Ongoing | AH80: Complete Data Collection & Begin Thesis Writing | AI80: Working paper in preparation — Explainable AI & Financial Inclusion | AJ80: Kitaptech University | AK80: No | AL80: No | AM80: None | AN80: None
A81: KT-PHD-2020-0039 | B81: Soraya Bint Nasser | C81: Female | D81: 1989-09-04 | E81: s.nasser@kitaptech.com | F81: +966712345039 | G81: PhD | H81: Data Science & AI | I81: School of Data Science & Artificial Intelligence | J81: Year 4 | K81: 3.73 | L81: 48 | M81: Active | N81: Saudi Arabian | O81: 2020-09-04 | P81: 2024-06-30 | Q81: Postgraduate | R81: PhD by Research | S81: 6. Thesis Writing Phase (Final) | T81: Research Year 4 | U81: Paid | V81: 0 | W81: Good Standing | X81: 2024-01-15 | Y81: Deep Learning for Early-Stage Drought Prediction Across the Arabian Peninsula | Z81: Writing | AA81: Not Yet | AC81: Dr. Samir Al-Balawi | AD81: Dr. Leila Sabbagh (KAUST, External) | AE81: Data Science — Climate Modelling & Deep Learning | AF81: 2024-06-30 | AG81: Enrolled ✓ | Foundation CW ✓ | Proposal Defended ✓ | Candidacy Confirmed ✓ | Fieldwork ✓ | Data Analysis ✓ | AH81: Submit Full Thesis Draft & Schedule Viva | AI81: Working paper in preparation — Climate Modelling & Deep Learning | AJ81: Kitaptech University | AK81: No | AL81: No | AM81: None | AN81: None
A82: KT-PHD-2023-0040 | B82: Karam Abu Zaid | C82: Male | D82: 1992-11-27 | E82: k.zaid@kitaptech.com | F82: +962712345040 | G82: PhD | H82: Information Systems | I82: School of Information Technology & Cybersecurity | J82: Year 1 | K82: 3.55 | L82: 12 | M82: Active | N82: Jordanian | O82: 2023-09-05 | P82: 2027-06-30 | Q82: Postgraduate | R82: PhD by Research | S82: 2. Research Proposal Writing | T82: Research Year 1 | U82: Paid | V82: 0 | W82: Good Standing | X82: 2024-01-15 | Y82: Cybersecurity Governance Maturity Models for Gulf State E-Government Platforms | Z82: Proposal Writing | AA82: Not Yet | AC82: Dr. Adel Karam | AD82: Prof. Yasir Mansoor (Qatar University, External) | AE82: Information Systems — Cybersecurity Governance & Public Sector Digitalisation | AF82: 2027-06-30 | AG82: Enrolled ✓ | Foundation Coursework (PHD701 ✓) | Systematic Lit Review In Progress | AH82: Submit Full Research Proposal to Departmental Committee | AI82: N/A — Year 1, Foundation Phase | AJ82: Kitaptech University | AK82: No | AL82: No | AM82: None | AN82: None
A83: KT-PHD-2022-0041 | B83: Widad El-Amrani | C83: Female | D83: 1991-04-13 | E83: w.el-amrani@kitaptech.com | F83: +212712345041 | G83: PhD | H83: Software Engineering | I83: School of Software Engineering | J83: Year 2 | K83: 3.38 | L83: 24 | M83: Active | N83: Moroccan | O83: 2022-09-06 | P83: 2026-06-30 | Q83: Postgraduate | R83: PhD by Research | S83: 3. Proposal Defense — Pre-Candidacy Phase | T83: Research Year 2 | U83: Paid | V83: 0 | W83: Good Standing | X83: 2024-01-15 | Y83: Low-Resource Software Testing Automation for Arabic-Script Mobile Applications | Z83: Proposal Submitted — Awaiting Defense | AA83: Not Yet | AC83: Dr. Samar Odeh | AD83: Dr. Rafiq Qadri (MBZUAI, External) | AE83: Software Engineering — Automated Testing & Localisation | AF83: 2026-06-30 | AG83: Enrolled ✓ | Foundation CW ✓ | Systematic Lit Review ✓ | Proposal Submitted (Dept Review) | AH83: Proposal Defense & Ethics Clearance | AI83: Working paper in preparation — Automated Testing & Localisation | AJ83: Kitaptech University | AK83: No | AL83: No | AM83: None | AN83: None
A84: RU-2021-0001 | B84: Dennis Otieno | C84: Male | D84: 2001-03-02 | E84: d.otieno@rongovarsity.ac.ke | F84: +254712345001 | G84: BEd | H84: Education | I84: School of Education | J84: Year 3 | K84: 3.41 | L84: 92 | M84: Active | N84: Kenyan | O84: 2021-09-02 | P84: 2025-06-30 | Q84: Undergraduate | R84: BEd | S84: 3. Progressing — Year 3 | T84: Sem 6 | U84: Paid | V84: 0 | W84: Good Standing | X84: 2024-01-15 | Y84: N/A | Z84: N/A | AA84: Not Yet | AJ84: Rongo University | AK84: No | AL84: No | AM84: None | AN84: None
A85: RU-2022-0002 | B85: Sharon Achieng | C85: Female | D85: 2002-07-14 | E85: s.achieng@rongovarsity.ac.ke | F85: +254712345002 | G85: BCom | H85: Human Resource Management | I85: School of Business and Human Resource Management | J85: Year 2 | K85: 3.09 | L85: 67 | M85: Active | N85: Kenyan | O85: 2022-09-04 | P85: 2026-06-30 | Q85: Undergraduate | R85: BCom | S85: 2. Progressing — Year 2 | T85: Sem 4 | U85: Paid | V85: 0 | W85: Good Standing | X85: 2024-01-15 | Y85: N/A | Z85: N/A | AA85: Not Yet | AJ85: Rongo University | AK85: No | AL85: No | AM85: None | AN85: None
A86: RU-2020-0003 | B86: Collins Onyango | C86: Male | D86: 2000-11-21 | E86: c.onyango@rongovarsity.ac.ke | F86: +254712345003 | G86: BA | H86: Journalism & Mass Communication | I86: School of Information, Communication and Media Studies | J86: Year 4 | K86: 3.52 | L86: 129 | M86: Active | N86: Kenyan | O86: 2020-09-05 | P86: 2024-06-30 | Q86: Undergraduate | R86: BA | S86: 4. Final Year — Pre-Clearance | T86: Sem 8 | U86: Paid | V86: 0 | W86: Good Standing | X86: 2024-01-15 | Y86: N/A | Z86: N/A | AA86: In Progress | AJ86: Rongo University | AK86: No | AL86: Yes | AM86: Specific Learning Disability (Dyslexia) | AN86: Extended exam time; reader/scribe support
A87: RU-2020-0004 | B87: Brenda Adhiambo | C87: Female | D87: 1999-05-09 | E87: b.adhiambo@rongovarsity.ac.ke | F87: +254712345004 | G87: BSc | H87: Computer Science | I87: School of Science, Technology and Engineering | J87: Year 4 | K87: 3.87 | L87: 127 | M87: Graduated | N87: Kenyan | O87: 2020-09-06 | Q87: Undergraduate | R87: BSc | S87: 6. Graduated ✓ | T87: Completed | U87: Cleared | V87: 0 | W87: Cleared | X87: 2024-01-15 | Y87: N/A | Z87: N/A | AA87: Approved | AB87: 2023-11-10 | AJ87: Rongo University | AK87: No | AL87: No | AM87: None | AN87: None
A88: RU-2023-0005 | B88: Kevin Owino | C88: Male | D88: 2003-09-28 | E88: k.owino@rongovarsity.ac.ke | F88: +254712345005 | G88: BA | H88: Sociology | I88: School of Arts and Social Sciences | J88: Year 1 | K88: 2.31 | L88: 23 | M88: Probation | N88: Kenyan | O88: 2023-09-07 | P88: 2027-06-30 | Q88: Undergraduate | R88: BA | S88: ⚠ Academic Review — Probation | T88: Sem 2 | U88: Partial | V88: 35000 | W88: Probation | X88: 2023-12-01 | Y88: N/A | Z88: N/A | AA88: Blocked | AJ88: Rongo University | AK88: No | AL88: No | AM88: None | AN88: None
A89: RU-2021-0006 | B89: Mercy Akinyi | C89: Female | D89: 2001-01-16 | E89: m.akinyi@rongovarsity.ac.ke | F89: +254712345006 | G89: BSc | H89: Agricultural Science | I89: School of Agriculture, Natural Resources and Environmental Studies | J89: Year 3 | K89: 3.22 | L89: 100 | M89: Active | N89: Kenyan | O89: 2021-09-02 | P89: 2025-06-30 | Q89: Undergraduate | R89: BSc | S89: 3. Progressing — Year 3 | T89: Sem 6 | U89: Paid | V89: 0 | W89: Good Standing | X89: 2024-01-15 | Y89: N/A | Z89: N/A | AA89: Not Yet | AJ89: Rongo University | AK89: No | AL89: No | AM89: None | AN89: None
A90: RU-2022-0007 | B90: Elvis Opiyo | C90: Male | D90: 2002-10-04 | E90: e.opiyo@rongovarsity.ac.ke | F90: +254712345007 | G90: BCom | H90: Accounting | I90: School of Business and Human Resource Management | J90: Year 2 | K90: 3.64 | L90: 66 | M90: Active | N90: Kenyan | O90: 2022-09-04 | P90: 2026-06-30 | Q90: Undergraduate | R90: BCom | S90: 2. Progressing — Year 2 | T90: Sem 4 | U90: Paid | V90: 0 | W90: Good Standing | X90: 2024-01-15 | Y90: N/A | Z90: N/A | AA90: Not Yet | AJ90: Rongo University | AK90: No | AL90: No | AM90: None | AN90: None
A91: RU-2020-0008 | B91: Joy Anyango | C91: Female | D91: 2000-04-12 | E91: j.anyango@rongovarsity.ac.ke | F91: +254712345008 | G91: BEd | H91: Curriculum Studies | I91: School of Education | J91: Year 4 | K91: 3.17 | L91: 128 | M91: Active | N91: Kenyan | O91: 2020-09-05 | P91: 2024-06-30 | Q91: Undergraduate | R91: BEd | S91: 4. Final Year — Pre-Clearance | T91: Sem 8 | U91: Paid | V91: 0 | W91: Good Standing | X91: 2024-01-15 | Y91: N/A | Z91: N/A | AA91: In Progress | AJ91: Rongo University | AK91: No | AL91: No | AM91: None | AN91: None
A92: RU-2021-0009 | B92: Moses Ochieng | C92: Male | D92: 2001-12-19 | E92: m.ochieng@rongovarsity.ac.ke | F92: +254712345009 | G92: BSc | H92: Environmental Science | I92: School of Agriculture, Natural Resources and Environmental Studies | J92: Year 3 | K92: 2.78 | L92: 90 | M92: On Leave | N92: Kenyan | O92: 2021-09-06 | P92: 2025-06-30 | Q92: Undergraduate | R92: BSc | S92: ⏸ Deferred — On Leave | T92: Sem 6 | U92: Deferred | V92: 0 | W92: Good Standing | X92: 2024-01-15 | Y92: N/A | Z92: N/A | AA92: Not Yet | AJ92: Rongo University | AK92: No | AL92: No | AM92: None | AN92: None
A93: RU-2023-0010 | B93: Lilian Auma | C93: Female | D93: 2003-02-25 | E93: l.auma@rongovarsity.ac.ke | F93: +254712345010 | G93: BA | H93: Communication & Media Studies | I93: School of Information, Communication and Media Studies | J93: Year 1 | K93: 3.45 | L93: 28 | M93: Active | N93: Kenyan | O93: 2023-09-07 | P93: 2027-06-30 | Q93: Undergraduate | R93: BA | S93: 1. Enrolled & Orientated | T93: Sem 2 | U93: Paid | V93: 0 | W93: Good Standing | X93: 2024-01-15 | Y93: N/A | Z93: N/A | AA93: Not Yet | AJ93: Rongo University | AK93: No | AL93: No | AM93: None | AN93: None
A94: RU-2022-0011 | B94: Paul Oduya | C94: Male | D94: 2002-08-07 | E94: p.oduya@rongovarsity.ac.ke | F94: +254712345011 | G94: BSc | H94: Computer Science | I94: School of Science, Technology and Engineering | J94: Year 2 | K94: 3.06 | L94: 67 | M94: Active | N94: Kenyan | O94: 2022-09-02 | P94: 2026-06-30 | Q94: Undergraduate | R94: BSc | S94: 2. Progressing — Year 2 | T94: Sem 4 | U94: Paid | V94: 0 | W94: Good Standing | X94: 2024-01-15 | Y94: N/A | Z94: N/A | AA94: Not Yet | AJ94: Rongo University | AK94: No | AL94: No | AM94: None | AN94: None
A95: RU-2020-0012 | B95: Janet Nyambura | C95: Female | D95: 1999-06-30 | E95: j.nyambura@rongovarsity.ac.ke | F95: +254712345012 | G95: BEd | H95: Special Needs Education | I95: School of Education | J95: Year 4 | K95: 2.61 | L95: 129 | M95: Graduated | N95: Kenyan | O95: 2020-09-04 | Q95: Undergraduate | R95: BEd | S95: 6. Graduated ✓ | T95: Completed | U95: Cleared | V95: 0 | W95: Cleared | X95: 2024-01-15 | Y95: N/A | Z95: N/A | AA95: Approved | AB95: 2023-11-10 | AJ95: Rongo University | AK95: No | AL95: No | AM95: None | AN95: None
A96: RU-2021-0013 | B96: Brian Omondi | C96: Male | D96: 2001-07-23 | E96: b.omondi@rongovarsity.ac.ke | F96: +254712345013 | G96: BA | H96: Political Science | I96: School of Arts and Social Sciences | J96: Year 3 | K96: 3.48 | L96: 95 | M96: Active | N96: Kenyan | O96: 2021-09-05 | P96: 2025-06-30 | Q96: Undergraduate | R96: BA | S96: 3. Progressing — Year 3 | T96: Sem 6 | U96: Paid | V96: 0 | W96: Good Standing | X96: 2024-01-15 | Y96: N/A | Z96: N/A | AA96: Not Yet | AJ96: Rongo University | AK96: No | AL96: No | AM96: None | AN96: None
A97: RU-2020-0014 | B97: Beatrice Atieno | C97: Female | D97: 2000-03-11 | E97: b.atieno@rongovarsity.ac.ke | F97: +254712345014 | G97: BSc | H97: Agribusiness Management | I97: School of Agriculture, Natural Resources and Environmental Studies | J97: Year 4 | K97: 1.96 | L97: 119 | M97: Suspended | N97: Kenyan | O97: 2020-09-06 | P97: 2024-06-30 | Q97: Undergraduate | R97: BSc | S97: ⚠ Academic Hold — Suspended | T97: Sem 8 | U97: Overdue | V97: 75000 | W97: Suspended | X97: 2023-12-01 | Y97: N/A | Z97: N/A | AA97: Blocked | AJ97: Rongo University | AK97: No | AL97: No | AM97: None | AN97: None
A98: RU-2023-0015 | B98: Michael Wafula | C98: Male | D98: 2003-11-08 | E98: m.wafula@rongovarsity.ac.ke | F98: +256712345015 | G98: BSc | H98: Mathematics | I98: School of Science, Technology and Engineering | J98: Year 1 | K98: 3.71 | L98: 36 | M98: Active | N98: Ugandan | O98: 2023-09-07 | P98: 2027-06-30 | Q98: Undergraduate | R98: BSc | S98: 1. Enrolled & Orientated | T98: Sem 2 | U98: Paid | V98: 0 | W98: Good Standing | X98: 2024-01-15 | Y98: N/A | Z98: N/A | AA98: Not Yet | AJ98: Rongo University | AK98: No | AL98: No | AM98: None | AN98: None
A99: RU-2021-0016 | B99: Christine Achola | C99: Female | D99: 2001-09-17 | E99: c.achola@rongovarsity.ac.ke | F99: +254712345016 | G99: BCom | H99: Marketing | I99: School of Business and Human Resource Management | J99: Year 3 | K99: 3.13 | L99: 98 | M99: Active | N99: Kenyan | O99: 2021-09-02 | P99: 2025-06-30 | Q99: Undergraduate | R99: BCom | S99: 3. Progressing — Year 3 | T99: Sem 6 | U99: Paid | V99: 0 | W99: Good Standing | X99: 2024-01-15 | Y99: N/A | Z99: N/A | AA99: Not Yet | AJ99: Rongo University | AK99: No | AL99: No | AM99: None | AN99: None
A100: RU-2022-0017 | B100: Steve Okoth | C100: Male | D100: 2002-05-26 | E100: s.okoth@rongovarsity.ac.ke | F100: +254712345017 | G100: BSc | H100: Electrical & Electronics Engineering | I100: School of Science, Technology and Engineering | J100: Year 2 | K100: 3.59 | L100: 64 | M100: Active | N100: Kenyan | O100: 2022-09-04 | P100: 2026-06-30 | Q100: Undergraduate | R100: BSc | S100: 2. Progressing — Year 2 | T100: Sem 4 | U100: Paid | V100: 0 | W100: Good Standing | X100: 2024-01-15 | Y100: N/A | Z100: N/A | AA100: Not Yet | AJ100: Rongo University | AK100: No | AL100: Yes | AM100: Psychosocial Disability (Anxiety Disorder) | AN100: Counselling support; flexible coursework deadlines
...

Sheet Courses
A1: course_code | B1: title | C1: department | D1: instructor | E1: credits | F1: enrolled_count | G1: type | H1: schedule | I1: room | J1: status | K1: Institution
A2: CS301 | B2: Data Structures & Algorithms | C2: School of Computing | D2: Dr. Kamande Njoroge | E2: 4 | F2: 18 | G2: Core | H2: Mon/Wed 8–10am | I2: LH-201 | J2: Active | K2: Templumis University
A3: CS201 | B3: Object-Oriented Programming | C3: School of Computing | D3: Dr. Kamande Njoroge | E3: 3 | F3: 22 | G3: Core | H3: Tue/Thu 10–12pm | I3: LH-202 | J3: Active | K3: Templumis University
A4: ECO201 | B4: Microeconomics | C4: School of Business | D4: Prof. Wambua Simiyu | E4: 3 | F4: 35 | G4: Core | H4: Mon/Wed 2–4pm | I4: BH-101 | J4: Active | K4: Templumis University
A5: ACC301 | B5: Intermediate Accounting | C5: School of Business | D5: Ms. Ruth Kariuki | E5: 4 | F5: 28 | G5: Core | H5: Tue/Thu 8–10am | I5: BH-102 | J5: Active | K5: Templumis University
A6: CE401 | B6: Structural Engineering | C6: School of Engineering | D6: Dr. Oloo Otiende | E6: 4 | F6: 15 | G6: Core | H6: Mon 8–12pm | I6: EH-301 | J6: Active | K6: Templumis University
A7: EE401 | B7: Power Systems | C7: School of Engineering | D7: Prof. James Mwema | E7: 4 | F7: 12 | G7: Core | H7: Wed 8–12pm | I7: EH-302 | J7: Active | K7: Templumis University
A8: LAW301 | B8: Contract Law | C8: School of Law | D8: Prof. Adhiambo Orengo | E8: 4 | F8: 20 | G8: Core | H8: Tue/Thu 2–4pm | I8: LW-101 | J8: Active | K8: Templumis University
A9: BCH201 | B9: Biochemistry I | C9: School of Science | D9: Dr. Mwangi Kiarie | E9: 3 | F9: 24 | G9: Core | H9: Mon/Wed 10–12pm | I9: SC-201 | J9: Active | K9: Templumis University
A10: NUR301 | B10: Clinical Nursing Practice | C10: School of Health Sciences | D10: Dr. Atieno Ouma | E10: 5 | F10: 18 | G10: Core | H10: Fri 8am–2pm | I10: HS-401 | J10: Active | K10: Templumis University
A11: EDU201 | B11: Curriculum Development | C11: School of Education | D11: Mr. Barasa Wekesa | E11: 3 | F11: 20 | G11: Core | H11: Tue/Thu 12–2pm | I11: ED-101 | J11: Active | K11: Templumis University
A12: SOC201 | B12: Sociological Theory | C12: School of Social Sciences | D12: Dr. Zawadi Amani | E12: 3 | F12: 26 | G12: Core | H12: Mon/Wed 12–2pm | I12: SS-101 | J12: Active | K12: Templumis University
A13: COM101 | B13: Introduction to Mass Media | C13: School of Arts | D13: Ms. Abigael Ndungu | E13: 3 | F13: 30 | G13: Core | H13: Mon/Wed 4–6pm | I13: AR-101 | J13: Active | K13: Templumis University
... A78: RU-PHD702 | B78: Doctoral Seminar Series | C78: Directorate of Graduate Studies | D78: Prof. Richard Onyango | E78: 1 | F78: 4 | G78: PhD Core | H78: Fri 3–4pm | I78: GS-Seminar | J78: Active | K78: Rongo University

Sheet Enrolments
A1: enrolment_id | B1: student_id | C1: student_name | D1: course_code | E1: course_title | F1: enrol_date | G1: status | H1: midterm_score | I1: current_grade | J1: Institution
A2: ENR-0001 | B2: TU-2021-0001 | C2: Amelia Odhiambo | D2: CS301 | E2: Data Structures & Algorithms | F2: 2023-09-05 | G2: Enrolled | H2: 82 | I2: 85 | J2: Templumis University
A3: ENR-0002 | B3: TU-2021-0001 | C3: Amelia Odhiambo | D3: CS201 | E3: Object-Oriented Programming | F3: 2023-09-05 | G3: Enrolled | H3: 88 | I3: 87 | J3: Templumis University
A4: ENR-0003 | B4: TU-2021-0001 | C4: Amelia Odhiambo | D4: MATH201 | E4: Calculus II | F4: 2023-09-05 | G4: Enrolled | H4: 75 | I4: 78 | J4: Templumis University
A5: ENR-0004 | B5: TU-2021-0001 | C5: Amelia Odhiambo | D5: GEN101 | E5: Communication Skills | F5: 2023-09-05 | G5: Enrolled | H5: 90 | I5: 91 | J5: Templumis University
A6: ENR-0005 | B6: TU-2022-0002 | C6: Brian Mwangi | D6: ECO201 | E6: Microeconomics | F6: 2023-09-05 | G6: Enrolled | H6: 72 | I6: 74 | J6: Templumis University
A7: ENR-0006 | B7: TU-2022-0002 | C7: Brian Mwangi | D7: FIN201 | E7: Principles of Finance | F7: 2023-09-05 | G7: Enrolled | H7: 68 | I7: 70 | J7: Templumis University
A8: ENR-0007 | B8: TU-2022-0002 | C8: Brian Mwangi | D8: MATH201 | E8: Calculus II | F8: 2023-09-05 | G8: Enrolled | H8: 65 | I8: 67 | J8: Templumis University
A9: ENR-0008 | B9: TU-2022-0002 | C9: Brian Mwangi | D9: GEN101 | E9: Communication Skills | F9: 2023-09-05 | G9: Enrolled | H9: 78 | I9: 77 | J9: Templumis University
A10: ENR-0009 | B10: TU-2020-0003 | C10: Claire Nakato | D10: CE401 | E10: Structural Engineering | F10: 2023-09-07 | G10: Enrolled | H10: 80 | I10: 82 | J10: Templumis University
A11: ENR-0010 | B11: TU-2020-0003 | C11: Claire Nakato | D11: MATH201 | E11: Calculus II | F11: 2023-09-07 | G11: Enrolled | H11: 76 | I11: 78 | J11: Templumis University
A12: ENR-0011 | B12: TU-2020-0003 | C12: Claire Nakato | D12: ENV201 | E12: Environmental Ecology | F12: 2023-09-07 | G12: Enrolled | H12: 83 | I12: 84 | J12: Templumis University
A13: ENR-0012 | B13: TU-2020-0003 | C13: Claire Nakato | D13: GEN101 | E13: Communication Skills | F13: 2023-09-07 | G13: Enrolled | H13: 88 | I13: 89 | J13: Templumis University
... A82: ENR-0081 | B82: TU-2023-0025 | C82: Stephen Gaita Gaikia | D82: GEN101 | E82: Communication Skills | F82: 2023-09-04 | G82: Enrolled | H82: 87 | I82: 88 | J82: Templumis University
A83: ENR-0082 | B83: TU-PG-2022-0026 | C83: Amara Diallo | D83: MSC601 | E83: Advanced Data Science & Machine Learning | F83: 45327 | G83: Enrolled | H83: 81 | I83: 83 | J83: Templumis University
A84: ENR-0083 | B84: TU-PG-2022-0026 | C84: Amara Diallo | D84: PGR602 | E84: Thesis Writing & Scholarly Communication | F84: 45327 | G84: Enrolled | H84: 78 | I84: 80 | J84: Templumis University
A85: ENR-0084 | B85: TU-PG-2022-0026 | C85: Amara Diallo | D85: PGR603 | E85: Graduate Research Colloquium & Seminar | F85: 45327 | G85: Enrolled | H85: 85 | I85: 86 | J85: Templumis University
A86: ENR-0085 | B86: TU-PG-2023-0027 | C86: Benjamin Kamto | D86: MBA601 | E86: Strategic Leadership & Corporate Governance | F86: 45306 | G86: Enrolled | H86: 74 | I86: 76 | J86: Templumis University
A87: ENR-0086 | B87: TU-PG-2023-0027 | C87: Benjamin Kamto | D87: MBA602 | E87: Advanced Financial Management | F87: 45306 | G87: Enrolled | H87: 70 | I87: 72 | J87: Templumis University
A88: ENR-0087 | B88: TU-PG-2023-0027 | C88: Benjamin Kamto | D88: MBA603 | E88: Innovation, Entrepreneurship & Strategy | F88: 45306 | G88: Enrolled | H88: 77 | I88: 79 | J88: Templumis University
A89: ENR-0088 | B89: TU-PG-2023-0027 | C89: Benjamin Kamto | D89: PGR603 | E89: Graduate Research Colloquium & Seminar | F89: 45306 | G89: Enrolled | H89: 72 | I89: 74 | J89: Templumis University
A90: ENR-0089 | B90: TU-PG-2023-0029 | C90: Derrick Ssempa | D90: MSC602 | E90: Advanced Environmental Research Methods | F90: 45306 | G90: Enrolled | H90: 55 | I90: 58 | J90: Templumis University
A91: ENR-0090 | B91: TU-PG-2023-0029 | C91: Derrick Ssempa | D91: PGR601 | E91: Research Methods & Academic Writing | F91: 45306 | G91: Enrolled | H91: 60 | I91: 62 | J91: Templumis University
A92: ENR-0091 | B92: TU-PG-2022-0030 | C92: Faith Onyango | D92: PGR602 | E92: Thesis Writing & Scholarly Communication | F92: 45327 | G92: Enrolled | H92: 80 | I92: 82 | J92: Templumis University
A93: ENR-0092 | B93: TU-PG-2022-0030 | C93: Faith Onyango | D93: PGR603 | E93: Graduate Research Colloquium & Seminar | F93: 45327 | G93: Enrolled | H93: 84 | I93: 85 | J93: Templumis University
A94: ENR-0093 | B94: TU-PG-2023-0031 | C94: George Nkosi | D94: MBA601 | E94: Strategic Leadership & Corporate Governance | F94: 45306 | G94: Enrolled | H94: 71 | I94: 73 | J94: Templumis University
... A115: ENR-0114 | B115: TU-PHD-2020-0039 | C115: Samuel Odhiambo | D115: PGR602 | E115: Thesis Writing & Scholarly Communication | F115: 45301 | G115: Enrolled | H115: 91 | I115: 93 | J115: Templumis University
A116: ENR-0115 | B116: KT-2021-0001 | C116: Yusuf Al-Farsi | D116: KT-CS101 | E116: Introduction to Programming | F116: 2023-09-05 | G116: Enrolled | H116: 92 | I116: 95 | J116: Kitaptech University
A117: ENR-0116 | B117: KT-2021-0001 | C117: Yusuf Al-Farsi | D117: KT-CS201 | E117: Data Structures & Algorithms | F117: 2023-09-05 | G117: Enrolled | H117: 90 | I117: 93 | J117: Kitaptech University
A118: ENR-0117 | B118: KT-2021-0001 | C118: Yusuf Al-Farsi | D118: KT-MATH201 | E118: Discrete Mathematics | F118: 2023-09-05 | G118: Enrolled | H118: 88 | I118: 91 | J118: Kitaptech University
A119: ENR-0118 | B119: KT-2022-0002 | C119: Fatima Al-Sayed | D119: KT-SE201 | E119: Object-Oriented Software Design | F119: 2023-09-05 | G119: Enrolled | H119: 87 | I119: 85 | J119: Kitaptech University
A120: ENR-0119 | B120: KT-2022-0002 | C120: Fatima Al-Sayed | D120: KT-SE301 | E120: DevOps & Cloud-Native Engineering | F120: 2023-09-05 | G120: Enrolled | H120: 85 | I120: 83 | J120: Kitaptech University
A121: ENR-0120 | B121: KT-2022-0002 | C121: Fatima Al-Sayed | D121: KT-MATH201 | E121: Discrete Mathematics | F121: 2023-09-05 | G121: Enrolled | H121: 83 | I121: 81 | J121: Kitaptech University
A122: ENR-0121 | B122: KT-2020-0003 | C122: Omar Haddad | D122: KT-IT201 | E122: Networks & Systems Administration | F122: 2023-09-05 | G122: Enrolled | H122: 90 | I122: 93 | J122: Kitaptech University
A123: ENR-0122 | B123: KT-2020-0003 | C123: Omar Haddad | D123: KT-IT301 | E123: Cybersecurity Fundamentals | F123: 2023-09-05 | G123: Enrolled | H123: 88 | I123: 91 | J123: Kitaptech University
A124: ENR-0123 | B124: KT-2020-0003 | C124: Omar Haddad | D124: KT-IT302 | E124: Digital Forensics & Incident Response | F124: 2023-09-05 | G124: Enrolled | H124: 86 | I124: 89 | J124: Kitaptech University
A125: ENR-0124 | B125: KT-2020-0004 | C125: Layla Mansour | D125: KT-DS201 | E125: Statistics & Probability for Data Science | F125: 2023-09-05 | G125: Completed | H125: 94 | I125: 97 | J125: Kitaptech University
A126: ENR-0125 | B126: KT-2020-0004 | C126: Layla Mansour | D126: KT-DS301 | E126: Machine Learning Foundations | F126: 2023-09-05 | G126: Completed | H126: 92 | I126: 95 | J126: Kitaptech University
A127: ENR-0126 | B127: KT-2020-0004 | C127: Layla Mansour | D127: KT-DS401 | E127: Deep Learning & Neural Networks | F127: 2023-09-05 | G127: Completed | H127: 90 | I127: 93 | J127: Kitaptech University
... A391: ENR-0390 | B391: TU-PG-2025-0081 | C391: Given Mthembu | D391: MBA602 | E391: Advanced Financial Management | F391: 2025-09-05 | G391: Enrolled | H391: 60 | I391: 60 | J391: Templumis University

Sheet Grades
A1: grade_id | B1: student_id | C1: student_name | D1: course_code | E1: assignment_1 | F1: assignment_2 | G1: midterm | H1: final | I1: total | J1: letter_grade | K1: Institution
A2: GRD-0001 | B2: TU-2021-0001 | C2: Amelia Odhiambo | D2: CS301 | E2: 85 | F2: 88 | G2: 82 | J2: B | K2: Templumis University
A3: GRD-0002 | B3: TU-2021-0001 | C3: Amelia Odhiambo | D3: CS201 | E3: 90 | F3: 87 | G3: 88 | J3: B | K3: Templumis University
A4: GRD-0003 | B4: TU-2021-0001 | C4: Amelia Odhiambo | D4: MATH201 | E4: 78 | F4: 80 | G4: 75 | J4: B | K4: Templumis University
A5: GRD-0004 | B5: TU-2021-0001 | C5: Amelia Odhiambo | D5: GEN101 | E5: 92 | F5: 91 | G5: 90 | J5: A | K5: Templumis University
A6: GRD-0005 | B6: TU-2019-0004 | C6: David Mensah | D6: NUR301 | E6: 94 | F6: 93 | G6: 91 | H6: 95 | I6: 93 | J6: A | K6: Templumis University
A7: GRD-0006 | B7: TU-2019-0004 | C7: David Mensah | D7: BCH201 | E7: 91 | F7: 90 | G7: 88 | H7: 91 | I7: 90 | J7: A | K7: Templumis University
A8: GRD-0007 | B8: TU-2023-0005 | C8: Esther Wanjiku | D8: MATH201 | E8: 52 | F8: 55 | G8: 48 | J8: D | K8: Templumis University
A9: GRD-0008 | B9: TU-2021-0017 | C9: Queenie Mugo | D9: CS301 | E9: 97 | F9: 96 | G9: 95 | J9: A | K9: Templumis University
A10: GRD-0009 | B10: TU-2020-0014 | C10: Noel Kiprotich | D10: BCH201 | E10: 48 | F10: 46 | G10: 45 | J10: F | K10: Templumis University
A11: GRD-0010 | B11: TU-2022-0020 | C11: Tunde Adeyemi | D11: LAW301 | E11: 86 | F11: 85 | G11: 84 | J11: B | K11: Templumis University
A12: GRD-0011 | B12: TU-2023-0015 | C12: Olivia Achieng | D12: COM101 | E12: 91 | F12: 90 | G12: 89 | J12: A | K12: Templumis University
A13: GRD-0012 | B13: TU-2019-0022 | C13: Vivian Kamau | D13: BCH201 | E13: 93 | F13: 92 | G13: 90 | H13: 94 | I13: 93 | J13: A | K13: Templumis University
A14: GRD-0013 | B14: TU-2023-0025 | C14: Stephen Gaita Gaikia | D14: CS101 | E14: 88 | F14: 85 | G14: 84 | J14: B | K14: Templumis University
A15: GRD-0014 | B15: TU-2023-0025 | C15: Stephen Gaita Gaikia | D15: IT201 | E15: 80 | F15: 79 | G15: 78 | J15: B | K15: Templumis University
A16: GRD-0015 | B16: TU-2023-0025 | C16: Stephen Gaita Gaikia | D16: MATH201 | E16: 83 | F16: 82 | G16: 81 | J16: B | K16: Templumis University
A17: GRD-0016 | B17: TU-2023-0025 | C17: Stephen Gaita Gaikia | D17: GEN101 | E17: 89 | F17: 88 | G17: 87 | J17: B | K17: Templumis University
A18: GRD-0017 | B18: TU-PG-2022-0026 | C18: Amara Diallo | D18: MSC601 | E18: 83 | F18: 85 | G18: 81 | J18: B | K18: Templumis University
A19: GRD-0018 | B19: TU-PG-2022-0026 | C19: Amara Diallo | D19: PGR602 | E19: 80 | F19: 82 | G19: 78 | J19: B | K19: Templumis University
A20: GRD-0019 | B20: TU-PG-2022-0026 | C20: Amara Diallo | D20: PGR603 | E20: 88 | F20: 87 | G20: 85 | J20: B | K20: Templumis University
A21: GRD-0020 | B21: TU-PG-2023-0027 | C21: Benjamin Kamto | D21: MBA601 | E21: 76 | F21: 78 | G21: 74 | J21: B | K21: Templumis University
A22: GRD-0021 | B22: TU-PG-2023-0027 | C22: Benjamin Kamto | D22: MBA602 | E22: 72 | F22: 75 | G22: 70 | J22: C | K22: Templumis University
A23: GRD-0022 | B23: TU-PG-2023-0027 | C23: Benjamin Kamto | D23: MBA603 | E23: 79 | F23: 80 | G23: 77 | J23: B | K23: Templumis University
A24: GRD-0023 | B24: TU-PG-2023-0029 | C24: Derrick Ssempa | D24: MSC602 | E24: 58 | F24: 60 | G24: 55 | J24: D | K24: Templumis University
A25: GRD-0024 | B25: TU-PG-2023-0029 | C25: Derrick Ssempa | D25: PGR601 | E25: 62 | F25: 63 | G25: 60 | J25: D | K25: Templumis University
... A51: GRD-0050 | B51: KT-2020-0003 | C51: Omar Haddad | D51: KT-IT201 | E51: 93 | F51: 88 | G51: 90 | J51: A | K51: Kitaptech University
A52: GRD-0051 | B52: KT-2020-0004 | C52: Layla Mansour | D52: KT-DS201 | E52: 97 | F52: 92 | G52: 94 | H52: 97 | I52: 95 | J52: A | K52: Kitaptech University
A53: GRD-0052 | B53: KT-2023-0005 | C53: Khalid Nasser | D53: KT-IT201 | E53: 82 | F53: 77 | G53: 79 | J53: C | K53: Kitaptech University
A54: GRD-0053 | B54: KT-2021-0006 | C54: Rania Saleh | D54: KT-CS101 | E54: 91 | F54: 86 | G54: 88 | J54: B | K54: Kitaptech University
A55: GRD-0054 | B55: KT-2022-0007 | C55: Hamza Zidane | D55: KT-FT201 | E55: 94 | F55: 89 | G55: 91 | J55: A | K55: Kitaptech University
A56: GRD-0055 | B56: KT-2020-0008 | C56: Noor Al-Amin | D56: KT-SE201 | E56: 89 | F56: 84 | G56: 86 | J56: B | K56: Kitaptech University
A57: GRD-0056 | B57: KT-2021-0009 | C57: Bilal Qureshi | D57: KT-DS201 | E57: 85 | F57: 80 | G57: 82 | H57: 80 | I57: 82 | J57: B | K57: Kitaptech University
A58: GRD-0057 | B58: KT-2023-0010 | C58: Sami Hijazi | D58: KT-IT201 | E58: 92 | F58: 87 | G58: 89 | J58: A | K58: Kitaptech University
A59: GRD-0058 | B59: KT-2022-0011 | C59: Dalia Abdullah | D59: KT-CS101 | E59: 88 | F59: 83 | G59: 85 | J59: B | K59: Kitaptech University
A60: GRD-0059 | B60: KT-2020-0012 | C60: Tariq Al-Otaibi | D60: KT-SE201 | E60: 84 | F60: 79 | G60: 81 | H60: 79 | I60: 81 | J60: B | K60: Kitaptech University
A61: GRD-0060 | B61: KT-2021-0013 | C61: Maryam Karam | D61: KT-IT201 | E61: 93 | F61: 88 | G61: 90 | J61: A | K61: Kitaptech University
A62: GRD-0061 | B62: KT-2020-0014 | C62: Faisal Al-Mutairi | D62: KT-FT201 | E62: 77 | F62: 72 | G62: 74 | J62: C | K62: Kitaptech University
A63: GRD-0062 | B63: KT-2023-0015 | C63: Huda Shammari | D63: KT-DS201 | E63: 96 | F63: 91 | G63: 93 | J63: A | K63: Kitaptech University
A64: GRD-0063 | B64: KT-2021-0016 | C64: Ahmed Al-Masri | D64: KT-CS101 | E64: 89 | F64: 84 | G64: 86 | J64: B | K64: Kitaptech University
A65: GRD-0064 | B65: KT-2022-0017 | C65: Yasmin Qasim | D65: KT-IT201 | E65: 94 | F65: 89 | G65: 91 | J65: A | K65: Kitaptech University
A66: GRD-0065 | B66: KT-2020-0018 | C66: Karim Hamdan | D66: KT-SE201 | E66: 89 | F66: 84 | G66: 86 | J66: B | K66: Kitaptech University
A67: GRD-0066 | B67: KT-2021-0019 | C67: Zainab Al-Rashid | D67: KT-FT201 | E67: 92 | F67: 87 | G67: 89 | J67: A | K67: Kitaptech University
A68: GRD-0067 | B68: KT-2023-0020 | C68: Hassan Mansour | D68: KT-CS101 | E68: 80 | F68: 75 | G68: 77 | J68: C | K68: Kitaptech University
A69: GRD-0068 | B69: KT-2022-0021 | C69: Salma Nasser | D69: KT-IT201 | E69: 94 | F69: 89 | G69: 91 | J69: A | K69: Kitaptech University
A70: GRD-0069 | B70: KT-2020-0022 | C70: Ali Abdullah | D70: KT-DS201 | E70: 95 | F70: 90 | G70: 92 | J70: A | K70: Kitaptech University
A71: GRD-0070 | B71: KT-2021-0023 | C71: Reem Al-Farsi | D71: KT-SE201 | E71: 86 | F71: 81 | G71: 83 | H71: 81 | I71: 83 | J71: B | K71: Kitaptech University
A72: GRD-0071 | B72: KT-2022-0024 | C72: Mohammed Khalil | D72: KT-IT201 | E72: 92 | F72: 87 | G72: 89 | J72: A | K72: Kitaptech University
A73: GRD-0072 | B73: KT-2023-0025 | C73: Lina Haddad | D73: KT-CS101 | E73: 94 | F73: 89 | G73: 91 | J73: A | K73: Kitaptech University
A74: GRD-0073 | B74: KT-PG-2022-0026 | C74: Nadia Saleh | D74: KT-PGR601 | E74: 95 | F74: 90 | G74: 92 | J74: A | K74: Kitaptech University
A75: GRD-0074 | B75: KT-PG-2023-0027 | C75: Rashid Al-Amin | D75: KT-PGR601 | E75: 91 | F75: 86 | G75: 88 | J75: A | K75: Kitaptech University
A76: GRD-0075 | B76: KT-PG-2022-0028 | C76: Dina Khalil | D76: KT-PGR601 | E76: 94 | F76: 89 | G76: 91 | H76: 94 | I76: 92 | J76: A | K76: Kitaptech University
A77: GRD-0076 | B77: KT-PG-2023-0029 | C77: Waleed Hamdan | D77: KT-PGR601 | E77: 86 | F77: 81 | G77: 83 | J77: B | K77: Kitaptech University
A78: GRD-0077 | B78: KT-PG-2022-0030 | C78: Amal Qasim | D78: KT-PGR601 | E78: 94 | F78: 89 | G78: 91 | J78: A | K78: Kitaptech University
A79: GRD-0078 | B79: KT-PG-2023-0031 | C79: Jamal Al-Otaibi | D79: KT-PGR601 | E79: 90 | F79: 85 | G79: 87 | J79: B | K79: Kitaptech University
A80: GRD-0079 | B80: KT-PG-2021-0032 | C80: Samira Haddad | D80: KT-PGR603 | E80: 96 | F80: 91 | G80: 93 | J80: A | K80: Kitaptech University
A81: GRD-0080 | B81: KT-PG-2022-0033 | C81: Anwar Mutairi | D81: KT-PGR603 | E81: 93 | F81: 88 | G81: 90 | J81: A | K81: Kitaptech University
A82: GRD-0081 | B82: KT-PG-2021-0034 | C82: Samar Odeh | D82: KT-PGR603 | E82: 93 | F82: 88 | G82: 90 | J82: A | K82: Kitaptech University
A83: GRD-0082 | B83: KT-PG-2022-0035 | C83: Bassam Najjar | D83: KT-PGR603 | E83: 91 | F83: 86 | G83: 88 | H83: 86 | I83: 88 | J83: B | K83: Kitaptech University
A84: GRD-0083 | B84: KT-PG-2020-0036 | C84: Hanan Zahran | D84: KT-PGR603 | E84: 97 | F84: 92 | G84: 94 | H84: 97 | I84: 95 | J84: A | K84: Kitaptech University
A85: GRD-0084 | B85: KT-PG-2023-0037 | C85: Marwan Saad | D85: KT-PGR603 | E85: 93 | F85: 88 | G85: 90 | J85: A | K85: Kitaptech University
A86: GRD-0085 | B86: KT-PHD-2021-0038 | C86: Nabil Farouk | D86: KT-PHD701 | E86: 96 | F86: 91 | G86: 93 | J86: A | K86: Kitaptech University
A87: GRD-0086 | B87: KT-PHD-2020-0039 | C87: Soraya Bint Nasser | D87: KT-PHD701 | E87: 95 | F87: 90 | G87: 92 | J87: A | K87: Kitaptech University
A88: GRD-0087 | B88: KT-PHD-2023-0040 | C88: Karam Abu Zaid | D88: KT-PHD701 | E88: 93 | F88: 88 | G88: 90 | J88: A | K88: Kitaptech University
A89: GRD-0088 | B89: KT-PHD-2022-0041 | C89: Widad El-Amrani | D89: KT-PHD701 | E89: 92 | F89: 87 | G89: 89 | J89: A | K89: Kitaptech University
A90: GRD-0089 | B90: RU-2021-0001 | C90: Dennis Otieno | D90: RU-EDU101 | E90: 92 | F90: 87 | G90: 89 | J90: A | K90: Rongo University
A91: GRD-0090 | B91: RU-2022-0002 | C91: Sharon Achieng | D91: RU-BUS201 | E91: 89 | F91: 84 | G91: 86 | J91: B | K91: Rongo University
A92: GRD-0091 | B92: RU-2020-0003 | C92: Collins Onyango | D92: RU-ICM201 | E92: 93 | F92: 88 | G92: 90 | J92: A | K92: Rongo University
A93: GRD-0092 | B93: RU-2020-0004 | C93: Brenda Adhiambo | D93: RU-STE201 | E93: 97 | F93: 92 | G93: 94 | H93: 97 | I93: 95 | J93: A | K93: Rongo University
A94: GRD-0093 | B94: RU-2023-0005 | C94: Kevin Owino | D94: RU-ASS201 | E94: 81 | F94: 76 | G94: 78 | J94: C | K94: Rongo University
A95: GRD-0094 | B95: RU-2021-0006 | C95: Mercy Akinyi | D95: RU-ANR201 | E95: 90 | F95: 85 | G95: 87 | J95: B | K95: Rongo University
A96: GRD-0095 | B96: RU-2022-0007 | C96: Elvis Opiyo | D96: RU-BUS201 | E96: 94 | F96: 89 | G96: 91 | J96: A | K96: Rongo University
A97: GRD-0096 | B97: RU-2020-0008 | C97: Joy Anyango | D97: RU-EDU101 | E97: 90 | F97: 85 | G97: 87 | J97: B | K97: Rongo University
A98: GRD-0097 | B98: RU-2021-0009 | C98: Moses Ochieng | D98: RU-ANR201 | E98: 86 | F98: 81 | G98: 83 | H98: 81 | I98: 83 | J98: B | K98: Rongo University
A99: GRD-0098 | B99: RU-2023-0010 | C99: Lilian Auma | D99: RU-ICM201 | E99: 93 | F99: 88 | G99: 90 | J99: A | K99: Rongo University
A100: GRD-0099 | B100: RU-2022-0011 | C100: Paul Oduya | D100: RU-STE201 | E100: 89 | F100: 84 | G100: 86 | J100: B | K100: Rongo University
A101: GRD-0100 | B101: RU-2020-0012 | C101: Janet Nyambura | D101: RU-EDU101 | E101: 84 | F101: 79 | G101: 81 | H101: 79 | I101: 81 | J101: B | K101: Rongo University
A102: GRD-0101 | B102: RU-2021-0013 | C102: Brian Omondi | D102: RU-ASS201 | E102: 93 | F102: 88 | G102: 90 | J102: A | K102: Rongo University
A103: GRD-0102 | B103: RU-2020-0014 | C103: Beatrice Atieno | D103: RU-ANR201 | E103: 78 | F103: 73 | G103: 75 | J103: C | K103: Rongo University
A104: GRD-0103 | B104: RU-2023-0015 | C104: Michael Wafula | D104: RU-STE201 | E104: 95 | F104: 90 | G104: 92 | J104: A | K104: Rongo University
A105: GRD-0104 | B105: RU-2021-0016 | C105: Christine Achola | D105: RU-BUS201 | E105: 89 | F105: 84 | G105: 86 | J105: B | K105: Rongo University
A106: GRD-0105 | B106: RU-2022-0017 | C106: Steve Okoth | D106: RU-STE201 | E106: 94 | F106: 89 | G106: 91 | J106: A | K106: Rongo University
A107: GRD-0106 | B107: RU-2020-0018 | C107: Vivian Nyakundi | D107: RU-ASS201 | E107: 88 | F107: 83 | G107: 85 | J107: B | K107: Rongo University
A108: GRD-0107 | B108: RU-2021-0019 | C108: Erick Oyugi | D108: RU-EDU101 | E108: 91 | F108: 86 | G108: 88 | J108: A | K108: Rongo University
A109: GRD-0108 | B109: RU-2023-0020 | C109: Gladys Kerubo | D109: RU-ANR201 | E109: 80 | F109: 75 | G109: 77 | J109: C | K109: Rongo University
A110: GRD-0109 | B110: RU-2022-0021 | C110: Felix Omolo | D110: RU-ICM201 | E110: 92 | F110: 87 | G110: 89 | J110: A | K110: Rongo University
A111: GRD-0110 | B111: RU-2020-0022 | C111: Margaret Awuor | D111: RU-STE201 | E111: 94 | F111: 89 | G111: 91 | J111: A | K111: Rongo University
A112: GRD-0111 | B112: RU-2021-0023 | C112: Dancun Wanyama | D112: RU-BUS201 | E112: 87 | F112: 82 | G112: 84 | H112: 82 | I112: 84 | J112: B | K112: Rongo University
A113: GRD-0112 | B113: RU-2022-0024 | C113: Purity Moraa | D113: RU-ANR201 | E113: 92 | F113: 87 | G113: 89 | J113: A | K113: Rongo University
A114: GRD-0113 | B114: RU-2023-0025 | C114: Samuel Ogola | D114: RU-ICM201 | E114: 94 | F114: 89 | G114: 91 | J114: A | K114: Rongo University
A115: GRD-0114 | B115: RU-PG-2022-0026 | C115: Evelyn Nyabuto | D115: RU-PGR601 | E115: 95 | F115: 90 | G115: 92 | J115: A | K115: Rongo University
A116: GRD-0115 | B116: RU-PG-2023-0027 | C116: Antony Nyakwaka | D116: RU-PGR601 | E116: 91 | F116: 86 | G116: 88 | J116: B | K116: Rongo University
A117: GRD-0116 | B117: RU-PG-2022-0028 | C117: Caroline Adika | D117: RU-PGR601 | E117: 94 | F117: 89 | G117: 91 | H117: 94 | I117: 92 | J117: A | K117: Rongo University
A118: GRD-0117 | B118: RU-PG-2023-0029 | C118: Isaac Otiende | D118: RU-PGR601 | E118: 85 | F118: 80 | G118: 82 | J118: B | K118: Rongo University
A119: GRD-0118 | B119: RU-PG-2022-0030 | C119: Agnes Kwamboka | D119: RU-PGR601 | E119: 93 | F119: 88 | G119: 90 | J119: A | K119: Rongo University
A120: GRD-0119 | B120: RU-PG-2023-0031 | C120: Dickson Obare | D120: RU-PGR601 | E120: 90 | F120: 85 | G120: 87 | J120: B | K120: Rongo University
A121: GRD-0120 | B121: RU-PG-2021-0032 | C121: Mercyline Atandi | D121: RU-PGR603 | E121: 96 | F121: 91 | G121: 93 | J121: A | K121: Rongo University
A122: GRD-0121 | B122: RU-PG-2022-0033 | C122: Kennedy Abuga | D122: RU-PGR603 | E122: 92 | F122: 87 | G122: 89 | J122: A | K122: Rongo University
A123: GRD-0122 | B123: RU-PG-2021-0034 | C123: Naomi Sianga | D123: RU-PGR603 | E123: 93 | F123: 88 | G123: 90 | J123: A | K123: Rongo University
A124: GRD-0123 | B124: RU-PG-2022-0035 | C124: Robert Ratemo | D124: RU-PGR603 | E124: 90 | F124: 85 | G124: 87 | H124: 85 | I124: 87 | J124: B | K124: Rongo University
A125: GRD-0124 | B125: RU-PG-2020-0036 | C125: Josephine Moige | D125: RU-PGR603 | E125: 97 | F125: 92 | G125: 94 | H125: 97 | I125: 95 | J125: A | K125: Rongo University
...

Sheet Attendance
A1: attendance_id | B1: student_id | C1: student_name | D1: course_code | E1: course_title | F1: total_sessions | G1: present | H1: absent | I1: late | J1: attendance_pct | K1: risk_level | L1: Institution
A2: ATT-0001 | B2: TU-2021-0001 | C2: Amelia Odhiambo | D2: CS301 | E2: Data Structures & Algorithms | F2: 28 | G2: 26 | H2: 2 | I2: 1 | J2: =ROUND(G2/F2*100,0) -> 93 | K2: Good | L2: Templumis University
A3: ATT-0002 | B3: TU-2021-0001 | C3: Amelia Odhiambo | D3: CS201 | E3: Object-Oriented Programming | F3: 26 | G3: 25 | H3: 1 | I3: 2 | J3: =ROUND(G3/F3*100,0) -> 96 | K3: Good | L3: Templumis University
A4: ATT-0003 | B4: TU-2023-0005 | C4: Esther Wanjiku | D4: MATH201 | E4: Calculus II | F4: 30 | G4: 17 | H4: 13 | I4: 3 | J4: =ROUND(G4/F4*100,0) -> 57 | K4: At Risk | L4: Templumis University
A5: ATT-0004 | B5: TU-2020-0014 | C5: Noel Kiprotich | D5: BCH201 | E5: Biochemistry I | F5: 26 | G5: 14 | H5: 12 | I5: 2 | J5: =ROUND(G5/F5*100,0) -> 54 | K5: At Risk | L5: Templumis University
A6: ATT-0005 | B6: TU-2021-0017 | C6: Queenie Mugo | D6: CS301 | E6: Data Structures & Algorithms | F6: 28 | G6: 28 | H6: 0 | I6: 0 | J6: =ROUND(G6/F6*100,0) -> 100 | K6: Good | L6: Templumis University
A7: ATT-0006 | B7: TU-2022-0002 | C7: Brian Mwangi | D7: ECO201 | E7: Microeconomics | F7: 26 | G7: 21 | H7: 5 | I7: 2 | J7: =ROUND(G7/F7*100,0) -> 81 | K7: Good | L7: Templumis University
A8: ATT-0007 | B8: TU-2023-0023 | C8: William Barasa | D8: FIN201 | E8: Principles of Finance | F8: 26 | G8: 16 | H8: 10 | I8: 3 | J8: =ROUND(G8/F8*100,0) -> 62 | K8: Warning | L8: Templumis University
A9: ATT-0008 | B9: TU-2023-0015 | C9: Olivia Achieng | D9: COM101 | E9: Introduction to Mass Media | F9: 24 | G9: 24 | H9: 0 | I9: 1 | J9: =ROUND(G9/F9*100,0) -> 100 | K9: Good | L9: Templumis University
A10: ATT-0009 | B10: TU-2020-0008 | C10: Hassan Abdi | D10: LAW301 | E10: Contract Law | F10: 26 | G10: 22 | H10: 4 | I10: 1 | J10: =ROUND(G10/F10*100,0) -> 85 | K10: Good | L10: Templumis University
A11: ATT-0010 | B11: TU-2021-0009 | C11: Ivy Njeri | D11: ACC301 | E11: Intermediate Accounting | F11: 26 | G11: 16 | H11: 10 | I11: 2 | J11: =ROUND(G11/F11*100,0) -> 62 | K11: Warning | L11: Templumis University
A12: ATT-0011 | B12: TU-2021-0021 | C12: Uchenna Eze | D12: SOC201 | E12: Sociological Theory | F12: 24 | G12: 15 | H12: 9 | I12: 2 | J12: =ROUND(G12/F12*100,0) -> 63 | K12: Warning | L12: Templumis University
A13: ATT-0012 | B13: TU-2022-0024 | C13: Xena Mutua | D13: IT201 | E13: Database Management Systems | F13: 24 | G13: 22 | H13: 2 | I13: 1 | J13: =ROUND(G13/F13*100,0) -> 92 | K13: Good | L13: Templumis University
... A17: ATT-0016 | B17: TU-2023-0025 | C17: Stephen Gaita Gaikia | D17: GEN101 | E17: Communication Skills | F17: 24 | G17: 23 | H17: 1 | I17: 0 | J17: =ROUND(G17/F17*100,0) -> 96 | K17: Good | L17: Templumis University
A18: ATT-0017 | B18: TU-PG-2022-0026 | C18: Amara Diallo | D18: MSC601 | E18: Advanced Data Science & Machine Learning | F18: 24 | G18: 22 | H18: 2 | I18: 1 | J18: 92 | K18: Good | L18: Templumis University
A19: ATT-0018 | B19: TU-PG-2022-0026 | C19: Amara Diallo | D19: PGR602 | E19: Thesis Writing & Scholarly Communication | F19: 20 | G19: 19 | H19: 1 | I19: 1 | J19: 95 | K19: Good | L19: Templumis University
A20: ATT-0019 | B20: TU-PG-2022-0026 | C20: Amara Diallo | D20: PGR603 | E20: Graduate Research Colloquium & Seminar | F20: 16 | G20: 15 | H20: 1 | I20: 0 | J20: 94 | K20: Good | L20: Templumis University
A21: ATT-0020 | B21: TU-PG-2023-0027 | C21: Benjamin Kamto | D21: MBA601 | E21: Strategic Leadership & Corporate Governance | F21: 22 | G21: 19 | H21: 3 | I21: 1 | J21: 86 | K21: Good | L21: Templumis University
A22: ATT-0021 | B22: TU-PG-2023-0027 | C22: Benjamin Kamto | D22: MBA602 | E22: Advanced Financial Management | F22: 22 | G22: 18 | H22: 4 | I22: 1 | J22: 82 | K22: Good | L22: Templumis University
A23: ATT-0022 | B23: TU-PG-2023-0027 | C23: Benjamin Kamto | D23: MBA603 | E23: Innovation, Entrepreneurship & Strategy | F23: 20 | G23: 18 | H23: 2 | I23: 1 | J23: 90 | K23: Good | L23: Templumis University
A24: ATT-0023 | B24: TU-PG-2023-0029 | C24: Derrick Ssempa | D24: MSC602 | E24: Advanced Environmental Research Methods | F24: 22 | G24: 13 | H24: 9 | I24: 2 | J24: 59 | K24: At Risk | L24: Templumis University
A25: ATT-0024 | B25: TU-PG-2023-0029 | C25: Derrick Ssempa | D25: PGR601 | E25: Research Methods & Academic Writing | F25: 18 | G25: 11 | H25: 7 | I25: 2 | J25: 61 | K25: Warning | L25: Templumis University
A26: ATT-0025 | B26: TU-PG-2022-0030 | C26: Faith Onyango | D26: PGR602 | E26: Thesis Writing & Scholarly Communication | F26: 20 | G26: 19 | H26: 1 | I26: 0 | J26: 95 | K26: Good | L26: Templumis University
A27: ATT-0026 | B27: TU-PG-2022-0030 | C27: Faith Onyango | D27: PGR603 | E27: Graduate Research Colloquium & Seminar | F27: 16 | G27: 15 | H27: 1 | I27: 1 | J27: 94 | K27: Good | L27: Templumis University
A28: ATT-0027 | B28: TU-PG-2023-0031 | C28: George Nkosi | D28: MBA601 | E28: Strategic Leadership & Corporate Governance | F28: 22 | G28: 20 | H28: 2 | I28: 0 | J28: 91 | K28: Good | L28: Templumis University
A29: ATT-0028 | B29: TU-PG-2023-0031 | C29: George Nkosi | D29: MBA602 | E29: Advanced Financial Management | F29: 22 | G29: 19 | H29: 3 | I29: 1 | J29: 86 | K29: Good | L29: Templumis University
... A48: ATT-0047 | B48: TU-PHD-2020-0039 | C48: Samuel Odhiambo | D48: PGR602 | E48: Thesis Writing & Scholarly Communication | F48: 20 | G48: 20 | H48: 0 | I48: 0 | J48: 100 | K48: Good | L48: Templumis University
A49: ATT-0048 | B49: KT-2021-0001 | C49: Yusuf Al-Farsi | D49: KT-CS101 | E49: Introduction to Programming | F49: 26 | G49: 25 | H49: 0 | I49: 1 | J49: =ROUND(G49/F49*100,0) -> 96 | K49: Good | L49: Kitaptech University
A50: ATT-0049 | B50: KT-2022-0002 | C50: Fatima Al-Sayed | D50: KT-SE201 | E50: Object-Oriented Software Design | F50: 28 | G50: 27 | H50: 0 | I50: 1 | J50: =ROUND(G50/F50*100,0) -> 96 | K50: Good | L50: Kitaptech University
A51: ATT-0050 | B51: KT-2020-0003 | C51: Omar Haddad | D51: KT-IT201 | E51: Networks & Systems Administration | F51: 30 | G51: 29 | H51: 0 | I51: 1 | J51: =ROUND(G51/F51*100,0) -> 97 | K51: Good | L51: Kitaptech University
A52: ATT-0051 | B52: KT-2020-0004 | C52: Layla Mansour | D52: KT-DS201 | E52: Statistics & Probability for Data Science | F52: 26 | G52: 25 | H52: 0 | I52: 1 | J52: =ROUND(G52/F52*100,0) -> 96 | K52: Good | L52: Kitaptech University
A53: ATT-0052 | B53: KT-2023-0005 | C53: Khalid Nasser | D53: KT-IT201 | E53: Networks & Systems Administration | F53: 27 | G53: 26 | H53: 0 | I53: 1 | J53: =ROUND(G53/F53*100,0) -> 96 | K53: Good | L53: Kitaptech University
A54: ATT-0053 | B54: KT-2021-0006 | C54: Rania Saleh | D54: KT-CS101 | E54: Introduction to Programming | F54: 30 | G54: 29 | H54: 0 | I54: 1 | J54: =ROUND(G54/F54*100,0) -> 97 | K54: Good | L54: Kitaptech University
A55: ATT-0054 | B55: KT-2022-0007 | C55: Hamza Zidane | D55: KT-FT201 | E55: Principles of Financial Technology | F55: 30 | G55: 29 | H55: 0 | I55: 1 | J55: =ROUND(G55/F55*100,0) -> 97 | K55: Good | L55: Kitaptech University
A56: ATT-0055 | B56: KT-2020-0008 | C56: Noor Al-Amin | D56: KT-SE201 | E56: Object-Oriented Software Design | F56: 27 | G56: 26 | H56: 0 | I56: 1 | J56: =ROUND(G56/F56*100,0) -> 96 | K56: Good | L56: Kitaptech University
A57: ATT-0056 | B57: KT-2021-0009 | C57: Bilal Qureshi | D57: KT-DS201 | E57: Statistics & Probability for Data Science | F57: 29 | G57: 28 | H57: 0 | I57: 1 | J57: =ROUND(G57/F57*100,0) -> 97 | K57: Good | L57: Kitaptech University
A58: ATT-0057 | B58: KT-2023-0010 | C58: Sami Hijazi | D58: KT-IT201 | E58: Networks & Systems Administration | F58: 29 | G58: 28 | H58: 0 | I58: 1 | J58: =ROUND(G58/F58*100,0) -> 97 | K58: Good | L58: Kitaptech University
A59: ATT-0058 | B59: KT-2022-0011 | C59: Dalia Abdullah | D59: KT-CS101 | E59: Introduction to Programming | F59: 28 | G59: 27 | H59: 0 | I59: 1 | J59: =ROUND(G59/F59*100,0) -> 96 | K59: Good | L59: Kitaptech University
A60: ATT-0059 | B60: KT-2020-0012 | C60: Tariq Al-Otaibi | D60: KT-SE201 | E60: Object-Oriented Software Design | F60: 26 | G60: 25 | H60: 0 | I60: 1 | J60: =ROUND(G60/F60*100,0) -> 96 | K60: Good | L60: Kitaptech University
... A219: ATT-0218 | B219: TU-PG-2025-0081 | C219: Given Mthembu | D219: MBA602 | E219: Advanced Financial Management | F219: 27 | G219: 16 | H219: 10 | I219: 1 | J219: =ROUND(G219/F219*100,0) -> 59 | K219: At Risk | L219: Templumis University

Sheet Fee Records
A1: Templumis University — Student Fee Records
A2: Academic Year 2023/24 · Semester 1 | All amounts in KES
A4: Fee Record ID | B4: Student ID | C4: Student Name | D4: Programme | E4: Department | F4: Student Type | G4: Current Semester | H4: Sem Fee (KES) | I4: Reg Fee (KES) | J4: Total Billed (KES) | K4: Amount Paid (KES) | L4: Balance (KES) | M4: Fee Status | N4: Institution
A5: FR-0001 | B5: TU-2021-0001 | C5: Amelia Odhiambo | D5: BSc | E5: School of Computing | F5: Undergraduate | G5: Sem 6 | H5: 75000 | I5: 5000 | J5: =H5+I5 -> 80000 | K5: 80000 | L5: =J5-K5 -> 0 | M5: Paid | N5: Templumis University
A6: FR-0002 | B6: TU-2022-0002 | C6: Brian Mwangi | D6: BA | E6: School of Business | F6: Undergraduate | G6: Sem 4 | H6: 65000 | I6: 5000 | J6: =H6+I6 -> 70000 | K6: 70000 | L6: =J6-K6 -> 0 | M6: Paid | N6: Templumis University
A7: FR-0003 | B7: TU-2020-0003 | C7: Claire Nakato | D7: BSc | E7: School of Engineering | F7: Undergraduate | G7: Sem 8 | H7: 75000 | I7: 5000 | J7: =H7+I7 -> 80000 | K7: 80000 | L7: =J7-K7 -> 0 | M7: Paid | N7: Templumis University
A8: FR-0004 | B8: TU-2019-0004 | C8: David Mensah | D8: BSc | E8: School of Health Sciences | F8: Undergraduate | G8: Completed | H8: 75000 | I8: 5000 | J8: =H8+I8 -> 80000 | K8: 80000 | L8: =J8-K8 -> 0 | M8: Paid | N8: Templumis University
A9: FR-0005 | B9: TU-2023-0005 | C9: Esther Wanjiku | D9: BSc | E9: School of Science | F9: Undergraduate | G9: Sem 2 | H9: 75000 | I9: 5000 | J9: =H9+I9 -> 80000 | K9: 45000 | L9: =J9-K9 -> 35000 | M9: Partial | N9: Templumis University
A10: FR-0006 | B10: TU-2021-0006 | C10: Felix Otieno | D10: BEd | E10: School of Education | F10: Undergraduate | G10: Sem 6 | H10: 60000 | I10: 5000 | J10: =H10+I10 -> 65000 | K10: 65000 | L10: =J10-K10 -> 0 | M10: Paid | N10: Templumis University
A11: FR-0007 | B11: TU-2022-0007 | C11: Grace Auma | D11: BSc | E11: School of Science | F11: Undergraduate | G11: Sem 4 | H11: 75000 | I11: 5000 | J11: =H11+I11 -> 80000 | K11: 80000 | L11: =J11-K11 -> 0 | M11: Paid | N11: Templumis University
A12: FR-0008 | B12: TU-2020-0008 | C12: Hassan Abdi | D12: LLB | E12: School of Law | F12: Undergraduate | G12: Sem 8 | H12: 70000 | I12: 5000 | J12: =H12+I12 -> 75000 | K12: 75000 | L12: =J12-K12 -> 0 | M12: Paid | N12: Templumis University
A13: FR-0009 | B13: TU-2021-0009 | C13: Ivy Njeri | D13: BComm | E13: School of Business | F13: Undergraduate | G13: Sem 6 | H13: 65000 | I13: 5000 | J13: =H13+I13 -> 70000 | K13: 0 | L13: =J13-K13 -> 70000 | M13: Deferred | N13: Templumis University
A14: FR-0010 | B14: TU-2023-0010 | C14: James Kibaki | D14: BSc | E14: School of Computing | F14: Undergraduate | G14: Sem 2 | H14: 75000 | I14: 5000 | J14: =H14+I14 -> 80000 | K14: 80000 | L14: =J14-K14 -> 0 | M14: Paid | N14: Templumis University
A15: FR-0011 | B15: TU-2022-0011 | C15: Kezia Moraa | D15: BSc | E15: School of Science | F15: Undergraduate | G15: Sem 4 | H15: 75000 | I15: 5000 | J15: =H15+I15 -> 80000 | K15: 80000 | L15: =J15-K15 -> 0 | M15: Paid | N15: Templumis University
A16: FR-0012 | B16: TU-2019-0012 | C16: Liam Okonkwo | D16: BSc | E16: School of Engineering | F16: Undergraduate | G16: Completed | H16: 75000 | I16: 5000 | J16: =H16+I16 -> 80000 | K16: 80000 | L16: =J16-K16 -> 0 | M16: Paid | N16: Templumis University
... A41: FR-0037 | B41: TU-PG-2023-0037 | C41: Moses Waweru | D41: MSc by Research | E41: School of Computing | F41: Postgraduate | G41: Research Year 1 | H41: 80000 | I41: 5000 | J41: =H41+I41 -> 85000 | K41: 85000 | L41: =J41-K41 -> 0 | M41: Paid | N41: Templumis University
A42: FR-0038 | B42: TU-PHD-2021-0038 | C42: Amina Osei | D42: PhD (Research) | E42: School of Computing | F42: Postgraduate | G42: Research Year 3 | H42: 180000 | I42: 5000 | J42: 185000 | K42: 185000 | L42: 0 | M42: Paid | N42: Templumis University
A43: FR-0039 | B43: TU-PHD-2020-0039 | C43: Samuel Odhiambo | D43: PhD (Research) | E43: School of Health Sciences | F43: Postgraduate | G43: Research Year 4 | H43: 180000 | I43: 5000 | J43: 185000 | K43: 185000 | L43: 0 | M43: Paid | N43: Templumis University
A44: FR-0040 | B44: TU-PHD-2023-0040 | C44: Fatima Al-Rashid | D44: PhD (Research) | E44: School of Business | F44: Postgraduate | G44: Research Year 1 | H44: 180000 | I44: 5000 | J44: 185000 | K44: 185000 | L44: 0 | M44: Paid | N44: Templumis University
A45: FR-0041 | B45: TU-PHD-2022-0041 | C45: Peter Kamau Njeru | D45: PhD (Research) | E45: School of Science | F45: Postgraduate | G45: Research Year 2 | H45: 180000 | I45: 5000 | J45: 185000 | K45: 185000 | L45: 0 | M45: Paid | N45: Templumis University
A46: FR-0042 | B46: KT-2021-0001 | C46: Yusuf Al-Farsi | D46: BSc | E46: School of Computer Science | F46: Undergraduate | G46: Sem 6 | H46: 75000 | I46: 5000 | J46: =H46+I46 -> 80000 | K46: 80000 | L46: =J46-K46 -> 0 | M46: Paid | N46: Kitaptech University
A47: FR-0043 | B47: KT-2022-0002 | C47: Fatima Al-Sayed | D47: BSc | E47: School of Software Engineering | F47: Undergraduate | G47: Sem 4 | H47: 75000 | I47: 5000 | J47: =H47+I47 -> 80000 | K47: 80000 | L47: =J47-K47 -> 0 | M47: Paid | N47: Kitaptech University
A48: FR-0044 | B48: KT-2020-0003 | C48: Omar Haddad | D48: BSc | E48: School of Information Technology & Cybersecurity | F48: Undergraduate | G48: Sem 8 | H48: 75000 | I48: 5000 | J48: =H48+I48 -> 80000 | K48: 80000 | L48: =J48-K48 -> 0 | M48: Paid | N48: Kitaptech University
A49: FR-0045 | B49: KT-2020-0004 | C49: Layla Mansour | D49: BSc | E49: School of Data Science & Artificial Intelligence | F49: Undergraduate | G49: Completed | H49: 75000 | I49: 5000 | J49: =H49+I49 -> 80000 | K49: 80000 | L49: =J49-K49 -> 0 | M49: Cleared | N49: Kitaptech University
A50: FR-0046 | B50: KT-2023-0005 | C50: Khalid Nasser | D50: BSc | E50: School of Information Technology & Cybersecurity | F50: Undergraduate | G50: Sem 2 | H50: 75000 | I50: 5000 | J50: =H50+I50 -> 80000 | K50: 41250 | L50: =J50-K50 -> 38750 | M50: Partial | N50: Kitaptech University
A51: FR-0047 | B51: KT-2021-0006 | C51: Rania Saleh | D51: BSc | E51: School of Computer Science | F51: Undergraduate | G51: Sem 6 | H51: 75000 | I51: 5000 | J51: =H51+I51 -> 80000 | K51: 80000 | L51: =J51-K51 -> 0 | M51: Paid | N51: Kitaptech University
A52: FR-0048 | B52: KT-2022-0007 | C52: Hamza Zidane | D52: BSc | E52: School of Digital Business & Financial Technology | F52: Undergraduate | G52: Sem 4 | H52: 75000 | I52: 5000 | J52: =H52+I52 -> 80000 | K52: 80000 | L52: =J52-K52 -> 0 | M52: Paid | N52: Kitaptech University
A53: FR-0049 | B53: KT-2020-0008 | C53: Noor Al-Amin | D53: BSc | E53: School of Software Engineering | F53: Undergraduate | G53: Sem 8 | H53: 75000 | I53: 5000 | J53: =H53+I53 -> 80000 | K53: 80000 | L53: =J53-K53 -> 0 | M53: Paid | N53: Kitaptech University
A54: FR-0050 | B54: KT-2021-0009 | C54: Bilal Qureshi | D54: BSc | E54: School of Data Science & Artificial Intelligence | F54: Undergraduate | G54: Sem 6 | H54: 75000 | I54: 5000 | J54: =H54+I54 -> 80000 | K54: 0 | L54: =J54-K54 -> 80000 | M54: Deferred | N54: Kitaptech University
A55: FR-0051 | B55: KT-2023-0010 | C55: Sami Hijazi | D55: BSc | E55: School of Information Technology & Cybersecurity | F55: Undergraduate | G55: Sem 2 | H55: 75000 | I55: 5000 | J55: =H55+I55 -> 80000 | K55: 80000 | L55: =J55-K55 -> 0 | M55: Paid | N55: Kitaptech University
A56: FR-0052 | B56: KT-2022-0011 | C56: Dalia Abdullah | D56: BSc | E56: School of Computer Science | F56: Undergraduate | G56: Sem 4 | H56: 75000 | I56: 5000 | J56: =H56+I56 -> 80000 | K56: 80000 | L56: =J56-K56 -> 0 | M56: Paid | N56: Kitaptech University
A57: FR-0053 | B57: KT-2020-0012 | C57: Tariq Al-Otaibi | D57: BSc | E57: School of Software Engineering | F57: Undergraduate | G57: Completed | H57: 75000 | I57: 5000 | J57: =H57+I57 -> 80000 | K57: 80000 | L57: =J57-K57 -> 0 | M57: Cleared | N57: Kitaptech University
... A176: FR-0172 | B176: TU-PG-2025-0081 | C176: Given Mthembu | D176: MA | E176: School of Business | F176: Postgraduate | G176: Sem 2 | H176: 95000 | I176: 7000 | J176: =H176+I176 -> 102000 | K176: 20000 | L176: =J176-K176 -> 82000 | M176: In Arrears | N176: Templumis University
A177: TOTALS | H177: =SUM(H5:H176) -> 14775000 | I177: =SUM(I5:I176) -> 876000 | J177: =SUM(J5:J176) -> 15651000 | K177: =SUM(K5:K176) -> 13146500 | L177: =SUM(L5:L176) -> 2504500

Sheet Payments
A1: Templumis University — Payment Transactions
A2: Academic Year 2023/24 · Semester 1 | All amounts in KES
A4: Payment ID | B4: Fee Record ID | C4: Student ID | D4: Student Name | E4: Payment Date | F4: Payment Method | G4: Reference No. | H4: Amount (KES) | I4: Payment Type | J4: Processed By | K4: Receipt No. | L4: Status | M4: Institution
A5: PAY-0001 | B5: FR-0001 | C5: TU-2021-0001 | D5: Amelia Odhiambo | E5: 2023-09-08 | F5: M-Pesa | G5: REF529696 | H5: 80000 | I5: Tuition & Registration | J5: Bursar | K5: RCT-0001 | L5: Confirmed | M5: Templumis University
A6: PAY-0002 | B6: FR-0002 | C6: TU-2022-0002 | D6: Brian Mwangi | E6: 2023-09-11 | F6: M-Pesa | G6: REF184441 | H6: 70000 | I6: Tuition & Registration | J6: Finance Office | K6: RCT-0002 | L6: Confirmed | M6: Templumis University
A7: PAY-0003 | B7: FR-0003 | C7: TU-2020-0003 | D7: Claire Nakato | E7: 2023-09-04 | F7: Bank Transfer | G7: REF600208 | H7: 80000 | I7: Tuition & Registration | J7: Bursar | K7: RCT-0003 | L7: Confirmed | M7: Templumis University
A8: PAY-0004 | B8: FR-0004 | C8: TU-2019-0004 | D8: David Mensah | E8: 2023-09-13 | F8: Bank Transfer | G8: REF749605 | H8: 80000 | I8: Tuition & Registration | J8: Finance Office | K8: RCT-0004 | L8: Confirmed | M8: Templumis University
A9: PAY-0005 | B9: FR-0005 | C9: TU-2023-0005 | D9: Esther Wanjiku | E9: 2023-09-02 | F9: M-Pesa | G9: REF404242 | H9: 45000 | I9: Partial Tuition | J9: Finance Office | K9: RCT-0005 | L9: Confirmed | M9: Templumis University
A10: PAY-0006 | B10: FR-0006 | C10: TU-2021-0006 | D10: Felix Otieno | E10: 2023-09-07 | F10: Bank Transfer | G10: REF432622 | H10: 65000 | I10: Tuition & Registration | J10: Bursar | K10: RCT-0006 | L10: Confirmed | M10: Templumis University
A11: PAY-0007 | B11: FR-0007 | C11: TU-2022-0007 | D11: Grace Auma | E11: 2023-09-02 | F11: Bank Transfer | G11: REF503029 | H11: 80000 | I11: Tuition & Registration | J11: Bursar | K11: RCT-0007 | L11: Confirmed | M11: Templumis University
A12: PAY-0008 | B12: FR-0008 | C12: TU-2020-0008 | D12: Hassan Abdi | E12: 2023-09-14 | F12: M-Pesa | G12: REF650659 | H12: 75000 | I12: Tuition & Registration | J12: Finance Office | K12: RCT-0008 | L12: Confirmed | M12: Templumis University
A13: PAY-0009 | B13: FR-0009 | C13: TU-2021-0009 | D13: Ivy Njeri | E13: 2023-09-02 | F13: — | G13: — | H13: 0 | I13: Deferred — Leave of Absence | J13: Registrar | K13: RCT-0009 | L13: Deferred | M13: Templumis University
A14: PAY-0010 | B14: FR-0010 | C14: TU-2023-0010 | D14: James Kibaki | E14: 2023-09-04 | F14: Bank Transfer | G14: REF890008 | H14: 80000 | I14: Tuition & Registration | J14: Bursar | K14: RCT-0010 | L14: Confirmed | M14: Templumis University
A15: PAY-0011 | B15: FR-0011 | C15: TU-2022-0011 | D15: Kezia Moraa | E15: 2023-09-10 | F15: Bank Transfer | G15: REF723142 | H15: 80000 | I15: Tuition & Registration | J15: Bursar | K15: RCT-0011 | L15: Confirmed | M15: Templumis University
A16: PAY-0012 | B16: FR-0012 | C16: TU-2019-0012 | D16: Liam Okonkwo | E16: 2023-09-11 | F16: Bank Transfer | G16: REF746509 | H16: 80000 | I16: Tuition & Registration | J16: Bursar | K16: RCT-0012 | L16: Confirmed | M16: Templumis University
... A41: PAY-0037 | B41: FR-0037 | C41: TU-PG-2023-0037 | D41: Moses Waweru | E41: 2023-09-02 | F41: Bank Transfer | G41: REF361964 | H41: 85000 | I41: Tuition & Registration | J41: Finance Office | K41: RCT-0037 | L41: Confirmed | M41: Templumis University
A42: PAY-0038 | B42: FR-0038 | C42: TU-PHD-2021-0038 | D42: Amina Osei | E42: 45177 | F42: Bank Transfer | G42: REF821034 | H42: 185000 | I42: Tuition & Registration | J42: Finance Office | K42: RCT-0038 | L42: Confirmed | M42: Templumis University
A43: PAY-0039 | B43: FR-0039 | C43: TU-PHD-2020-0039 | D43: Samuel Odhiambo | E43: 45179 | F43: M-Pesa | G43: REF672891 | H43: 185000 | I43: Tuition & Registration | J43: Bursar | K43: RCT-0039 | L43: Confirmed | M43: Templumis University
A44: PAY-0040 | B44: FR-0040 | C44: TU-PHD-2023-0040 | D44: Fatima Al-Rashid | E44: 45175 | F44: Bank Transfer | G44: REF543217 | H44: 185000 | I44: Tuition & Registration | J44: Finance Office | K44: RCT-0040 | L44: Confirmed | M44: Templumis University
A45: PAY-0041 | B45: FR-0041 | C45: TU-PHD-2022-0041 | D45: Peter Kamau Njeru | E45: 45542 | F45: Bank Transfer | G45: REF309845 | H45: 185000 | I45: Tuition & Registration | J45: Finance Office | K45: RCT-0041 | L45: Confirmed | M45: Templumis University
A46: PAY-0042 | B46: FR-0042 | C46: KT-2021-0001 | D46: Yusuf Al-Farsi | E46: 2023-09-08 | F46: M-Pesa | G46: REF600001 | H46: 80000 | I46: Tuition & Registration | J46: Bursar | K46: RCT-0042 | L46: Confirmed | M46: Kitaptech University
A47: PAY-0043 | B47: FR-0043 | C47: KT-2022-0002 | D47: Fatima Al-Sayed | E47: 2023-09-08 | F47: Bank Transfer | G47: REF600002 | H47: 80000 | I47: Tuition & Registration | J47: Finance Office | K47: RCT-0043 | L47: Confirmed | M47: Kitaptech University
A48: PAY-0044 | B48: FR-0044 | C48: KT-2020-0003 | D48: Omar Haddad | E48: 2023-09-08 | F48: M-Pesa | G48: REF600003 | H48: 80000 | I48: Tuition & Registration | J48: Bursar | K48: RCT-0044 | L48: Confirmed | M48: Kitaptech University
A49: PAY-0045 | B49: FR-0045 | C49: KT-2020-0004 | D49: Layla Mansour | E49: 2023-09-08 | F49: Bank Transfer | G49: REF600004 | H49: 80000 | I49: Tuition & Registration | J49: Finance Office | K49: RCT-0045 | L49: Confirmed | M49: Kitaptech University
A50: PAY-0046 | B50: FR-0046 | C50: KT-2023-0005 | D50: Khalid Nasser | E50: 2023-09-08 | F50: M-Pesa | G50: REF600005 | H50: 41250 | I50: Partial Tuition | J50: Bursar | K50: RCT-0046 | L50: Confirmed | M50: Kitaptech University
A51: PAY-0047 | B51: FR-0047 | C51: KT-2021-0006 | D51: Rania Saleh | E51: 2023-09-08 | F51: Bank Transfer | G51: REF600006 | H51: 80000 | I51: Tuition & Registration | J51: Finance Office | K51: RCT-0047 | L51: Confirmed | M51: Kitaptech University
A52: PAY-0048 | B52: FR-0048 | C52: KT-2022-0007 | D52: Hamza Zidane | E52: 2023-09-08 | F52: M-Pesa | G52: REF600007 | H52: 80000 | I52: Tuition & Registration | J52: Bursar | K52: RCT-0048 | L52: Confirmed | M52: Kitaptech University
A53: PAY-0049 | B53: FR-0049 | C53: KT-2020-0008 | D53: Noor Al-Amin | E53: 2023-09-08 | F53: Bank Transfer | G53: REF600008 | H53: 80000 | I53: Tuition & Registration | J53: Finance Office | K53: RCT-0049 | L53: Confirmed | M53: Kitaptech University
A54: PAY-0050 | B54: FR-0050 | C54: KT-2021-0009 | D54: Bilal Qureshi | E54: 2023-09-08 | F54: — | G54: — | H54: 0 | I54: Deferred — Leave of Absence | J54: Registrar | K54: RCT-0050 | L54: Deferred | M54: Kitaptech University
A55: PAY-0051 | B55: FR-0051 | C55: KT-2023-0010 | D55: Sami Hijazi | E55: 2023-09-08 | F55: Bank Transfer | G55: REF600010 | H55: 80000 | I55: Tuition & Registration | J55: Finance Office | K55: RCT-0051 | L55: Confirmed | M55: Kitaptech University
A56: PAY-0052 | B56: FR-0052 | C56: KT-2022-0011 | D56: Dalia Abdullah | E56: 2023-09-08 | F56: M-Pesa | G56: REF600011 | H56: 80000 | I56: Tuition & Registration | J56: Bursar | K56: RCT-0052 | L56: Confirmed | M56: Kitaptech University
A57: PAY-0053 | B57: FR-0053 | C57: KT-2020-0012 | D57: Tariq Al-Otaibi | E57: 2023-09-08 | F57: Bank Transfer | G57: REF600012 | H57: 80000 | I57: Tuition & Registration | J57: Finance Office | K57: RCT-0053 | L57: Confirmed | M57: Kitaptech University
... A176: PAY-0172 | B176: FR-0172 | C176: TU-PG-2025-0081 | D176: Given Mthembu | E176: 2025-09-01 | F176: M-Pesa | G176: REF700091 | H176: 20000 | I176: Family Contribution — Partial (NSFAS Funding Discontinued) | J176: Bursar | K176: RCT-0172 | L176: Partial — Balance KES 82,000 (Funding Discontinued) | M176: Templumis University
A177: TOTAL PAYMENTS RECEIVED | H177: =SUM(H5:H176) -> 13146500

Sheet Scholarships
A1: Templumis University — Scholarship Programmes
A2: Active & Available Scholarships · Academic Year 2023/24
A4: Scholarship ID | B4: Scholarship Name | C4: Type | D4: Criteria | E4: Value (KES) | F4: Coverage | G4: Slots Available | H4: Slots Filled | I4: Status | J4: Institution
A5: SCH-001 | B5: Vice Chancellor's Merit Award | C5: Merit | D5: Top 5% GPA; minimum GPA 3.80 | E5: 100000 | F5: Full Tuition | G5: 5 | H5: 2 | I5: Active | J5: Templumis University
A6: SCH-002 | B6: Dean's Excellence Bursary | C6: Merit | D6: GPA 3.50–3.79; Good Standing | E6: 50000 | F6: 50% Tuition | G6: 10 | H6: 4 | I6: Active | J6: Templumis University
A7: SCH-003 | B7: STEM Advancement Fund | C7: Merit + Need | D7: BSc/MSc programmes; GPA ≥ 3.20 | E7: 40000 | F7: 40% Tuition | G7: 8 | H7: 3 | I7: Active | J7: Templumis University
A8: SCH-004 | B8: Pan-African Diversity Grant | C8: Diversity | D8: Non-Kenyan international students | E8: 30000 | F8: Partial Tuition | G8: 15 | H8: 7 | I8: Active | J8: Templumis University
A9: SCH-005 | B9: Women in Science Scholarship | C9: Equity | D9: Female students in Science/Engineering | E9: 35000 | F9: Partial Tuition | G9: 6 | H9: 2 | I9: Active | J9: Templumis University
A10: SCH-006 | B10: Bursary for Needy Students | C10: Need-Based | D10: Demonstrated financial hardship; GPA ≥ 2.50 | E10: 25000 | F10: Partial Tuition | G10: 10 | H10: 3 | I10: Active | J10: Templumis University
A11: SCH-007 | B11: Postgraduate Research Fellowship | C11: Research | D11: MSc/MA by Research students; supervisor endorsement | E11: 60000 | F11: Full Tuition + Stipend | G11: 4 | H11: 2 | I11: Active | J11: Templumis University
A12: SCH-008 | B12: Community Leaders Award | C12: Leadership | D12: Community engagement evidence; essay required | E12: 20000 | F12: Flat Grant | G12: 5 | H12: 1 | I12: Active | J12: Templumis University
A13: SCH-009 | B13: Health Sciences Sponsorship | C13: Sectoral | D13: BSc Nursing / BPharm / BSc Nutrition students | E13: 45000 | F13: 50% Tuition | G13: 4 | H13: 2 | I13: Active | J13: Templumis University
A14: SCH-010 | B14: Law & Justice Fund | C14: Sectoral | D14: LLB students; moot court participation | E14: 30000 | F14: 40% Tuition | G14: 4 | H14: 1 | I14: Active | J14: Templumis University
A15: SCH-011 | B15: Financial Hardship Emergency Bursary | C15: Need-Based | D15: Documented fee arrears; household income statement; GPA ≥ 2.50; active enrolment | E15: 75000 | F15: Outstanding Tuition Balance (up to KES 75,000) | G15: 5 | H15: 0 | I15: Active | J15: Templumis University
A16: SCH-012 | B16: Founder's Merit Scholarship | C16: Merit | D16: Top 5% GPA; minimum GPA 3.80 | E16: 100000 | F16: Full Tuition | G16: 5 | H16: 2 | I16: Active | J16: Kitaptech University
... A37: SCH-033 | B37: Financial Hardship Emergency Bursary | C37: Need-Based | D37: Documented fee arrears; household income statement; GPA ≥ 2.50; active enrolment | E37: 75000 | F37: Outstanding Tuition Balance (up to KES 75,000) | G37: 5 | H37: 1 | I37: Active | J37: Rongo University
A38: SCH-034 | B38: NSFAS Bursary Programme (National Student Financial Aid Scheme) | C38: Need-Based (Government) | D38: South African-model means-tested aid, adapted for Templumis University; household income threshold and full academic-progress rules apply — see 'NSFAS Student Tracking' sheet | E38: Varies by allowance category (Tuition, Accommodation/Transport, Living, Learning Materials, Disability Top-up) | F38: Full Tuition + Allowances | G38: 40 | H38: 40 | I38: Active | J38: Templumis University

Sheet Dashboard
A1: Multi-Institution LMS & SIS Dashboard
A2: Academic Year 2023/24 · Semester 1
A3: Templumis University — Institution Detail (below) | See "All Institutions — Comparative Overview" further down for Kitaptech University & Rongo University
A4: Students | C4: Courses & Enrolments
A5: Total Students | B5: 41 | C5: Total Courses | D5: 32
A6: Active | B6: 29 | C6: Active Courses | D6: 31
A7: On Probation | B7: 3 | C7: Total Enrolments | D7: 124
A8: Graduated | B8: 5 | C8: Currently Enrolled | D8: 114
A9: Suspended | B9: 1 | C9: Completed | D9: =COUNTIF(Enrolments!G2:G1000,"Completed") -> 27
A10: On Leave | B10: 3 | C10: Dropped | D10: =COUNTIF(Enrolments!G2:G1000,"Dropped") -> 16
A11: Average GPA | B11: 3.35 | C11: Avg Current Grade | D11: =ROUND(AVERAGE(Enrolments!I2:I1000),1)&"%" -> 81.8%
A12: Total Credit Hours | B12: 2502 | C12: Grade A Count | D12: =COUNTIF(Grades!J2:J1000,"A") -> 86
A14: ── Postgraduate Summary ── | C14: Student Lookup
A15: PG Students | B15: 16 | C15: Enter Student ID → | D15: TU-2023-0025
A16: MSc Coursework | B16: 6 | C16: Name | D16: =IFERROR(VLOOKUP(D15,Students!A:B,2,0),"-") -> Stephen Gaita Gaikia
A17: MSc by Research | B17: 6 | C17: Program | D17: =IFERROR(VLOOKUP(D15,Students!A:H,8,0),"-") -> Computer Science
A18: PhD by Research | B18: 4 | C18: GPA | D18: =IFERROR(VLOOKUP(D15,Students!A:K,11,0),"-") -> 3.65
A19: Avg Attendance % | B19: =ROUND(AVERAGE(Attendance!J2:J1000),0)&"%" -> 88% | C19: Status | D19: =IFERROR(VLOOKUP(D15,Students!A:M,13,0),"-") -> Active
A21: ALL INSTITUTIONS — COMPARATIVE OVERVIEW
A22: Institution | B22: Total Students | C22: Active | D22: UG | E22: PG (Masters) | F22: PhD | G22: Avg GPA | H22: Avg Attendance %
A23: Templumis University | B23: =COUNTIF(Students!$AJ:$AJ,"Templumis University") -> 84 | C23: =COUNTIFS(Students!$AJ:$AJ,"Templumis University",Students!$M:$M,"Active") -> 62 | D23: =COUNTIFS(Students!$AJ:$AJ,"Templumis University",Students!$Q:$Q,"Undergraduate") -> 58 | E23: =COUNTIFS(Students!$AJ:$AJ,"Templumis University",Students!$Q:$Q,"Postgraduate")-COUNTIFS(Students!$AJ:$AJ,"Templumis University",Students!$R:$R,"PhD by Research") -> 19 | F23: =COUNTIFS(Students!$AJ:$AJ,"Templumis University",Students!$R:$R,"PhD by Research") -> 7 | G23: =ROUND(AVERAGEIFS(Students!$K:$K,Students!$AJ:$AJ,"Templumis University"),2) -> 3.23 | H23: =ROUND(AVERAGEIFS(Attendance!$J:$J,Attendance!$L:$L,"Templumis University"),0)&"%" -> 82%
A24: Kitaptech University | B24: =COUNTIF(Students!$AJ:$AJ,"Kitaptech University") -> 44 | C24: =COUNTIFS(Students!$AJ:$AJ,"Kitaptech University",Students!$M:$M,"Active") -> 33 | D24: =COUNTIFS(Students!$AJ:$AJ,"Kitaptech University",Students!$Q:$Q,"Undergraduate") -> 26 | E24: =COUNTIFS(Students!$AJ:$AJ,"Kitaptech University",Students!$Q:$Q,"Postgraduate")-COUNTIFS(Students!$AJ:$AJ,"Kitaptech University",Students!$R:$R,"PhD by Research") -> 13 | F24: =COUNTIFS(Students!$AJ:$AJ,"Kitaptech University",Students!$R:$R,"PhD by Research") -> 5 | G24: =ROUND(AVERAGEIFS(Students!$K:$K,Students!$AJ:$AJ,"Kitaptech University"),2) -> 3.34 | H24: =ROUND(AVERAGEIFS(Attendance!$J:$J,Attendance!$L:$L,"Kitaptech University"),0)&"%" -> 96%
A25: Rongo University | B25: =COUNTIF(Students!$AJ:$AJ,"Rongo University") -> 44 | C25: =COUNTIFS(Students!$AJ:$AJ,"Rongo University",Students!$M:$M,"Active") -> 33 | D25: =COUNTIFS(Students!$AJ:$AJ,"Rongo University",Students!$Q:$Q,"Undergraduate") -> 26 | E25: =COUNTIFS(Students!$AJ:$AJ,"Rongo University",Students!$Q:$Q,"Postgraduate")-COUNTIFS(Students!$AJ:$AJ,"Rongo University",Students!$R:$R,"PhD by Research") -> 13 | F25: =COUNTIFS(Students!$AJ:$AJ,"Rongo University",Students!$R:$R,"PhD by Research") -> 5 | G25: =ROUND(AVERAGEIFS(Students!$K:$K,Students!$AJ:$AJ,"Rongo University"),2) -> 3.3 | H25: =ROUND(AVERAGEIFS(Attendance!$J:$J,Attendance!$L:$L,"Rongo University"),0)&"%" -> 96%
A26: ALL INSTITUTIONS | B26: =SUM(B23:B25) -> 172 | C26: =SUM(C23:C25) -> 128 | D26: =SUM(D23:D25) -> 110 | E26: =SUM(E23:E25) -> 45 | F26: =SUM(F23:F25) -> 17 | G26: =ROUND(AVERAGE(G23:G25),2) -> 3.29 | H26: =ROUND(AVERAGE(Attendance!$J:$J),0)&"%" -> 88%

Sheet Journey Tracker
A1: A. STUDENT PROFILE | G1: B. ACADEMIC PROGRESSION | L1: C. ACADEMIC STANDING | O1: D. FINANCIAL CLEARANCE | R1: E. RESEARCH / THESIS | V1: F. GRADUATION
A2: Student ID | B2: Full Name | C2: Student Type | D2: Programme Level | E2: Department | F2: Enrolment Date | G2: Current Year/Sem | H2: Sem 1 Status | I2: Sem 2 Status | J2: Year 2 Progression | K2: Year 3+ Progression | L2: GPA | M2: Academic Standing | N2: Last Review Date | O2: Fees — Sem 1 | P2: Fees — Sem 2 | Q2: Fees Balance (KES) | R2: Proposal Status | S2: Data/Coursework Phase | T2: Thesis Submission | U2: Thesis Defence | V2: Graduation Clearance | W2: Clearance Date | X2: Graduation Date | Y2: Journey Stage | Z2: Institution
A3: TU-2021-0001 | B3: Amelia Odhiambo | C3: Undergraduate | D3: BSc | E3: School of Computing | F3: 2021-09-05 | G3: Sem 6 | H3: Complete | I3: Complete | J3: Complete | K3: In Progress | L3: 3.78 | M3: Good Standing | N3: 2024-01-15 | O3: Paid | P3: Paid | Q3: 0 | R3: N/A | S3: Sem Year 3 | T3: N/A | U3: N/A | V3: Not Yet | Y3: 3. Progressing — Year 3 | Z3: Templumis University
A4: TU-2022-0002 | B4: Brian Mwangi | C4: Undergraduate | D4: BA | E4: School of Business | F4: 2022-09-05 | G4: Sem 4 | H4: Complete | I4: Complete | J4: In Progress | K4: Pending | L4: 3.12 | M4: Good Standing | N4: 2024-01-15 | O4: Paid | P4: Paid | Q4: 0 | R4: N/A | S4: Sem Year 2 | T4: N/A | U4: N/A | V4: Not Yet | Y4: 2. Progressing — Year 2 | Z4: Templumis University
A5: TU-2020-0003 | B5: Claire Nakato | C5: Undergraduate | D5: BSc | E5: School of Engineering | F5: 2020-09-07 | G5: Sem 8 | H5: Complete | I5: Complete | J5: Complete | K5: Complete | L5: 3.55 | M5: Good Standing | N5: 2024-01-15 | O5: Paid | P5: Paid | Q5: 0 | R5: N/A | S5: Sem Year 4 | T5: N/A | U5: N/A | V5: In Progress | Y5: 4. Final Year — Pre-Clearance | Z5: Templumis University
A6: TU-2019-0004 | B6: David Mensah | C6: Undergraduate | D6: BSc | E6: School of Health Sciences | F6: 2019-09-02 | G6: Completed | H6: Complete | I6: Complete | J6: Complete | K6: Complete | L6: 3.9 | M6: Cleared | N6: 2024-01-15 | O6: Paid | P6: Cleared | Q6: 0 | R6: N/A | S6: Sem Year 4 | T6: N/A | U6: N/A | V6: Approved | W6: 2024-01-15 | X6: 2023-11-10 | Y6: 6. Graduated ✓ | Z6: Templumis University
A7: TU-2023-0005 | B7: Esther Wanjiku | C7: Undergraduate | D7: BSc | E7: School of Science | F7: 2023-09-04 | G7: Sem 2 | H7: In Progress | I7: In Progress | J7: Pending | K7: Pending | L7: 2.45 | M7: Probation | N7: 2023-12-01 | O7: Partial | P7: Partial | Q7: 35000 | R7: N/A | S7: Sem Year 1 | T7: N/A | U7: N/A | V7: Blocked | Y7: ⚠ Academic Review — Probation | Z7: Templumis University
A8: TU-2021-0006 | B8: Felix Otieno | C8: Undergraduate | D8: BEd | E8: School of Education | F8: 2021-09-05 | G8: Sem 6 | H8: Complete | I8: Complete | J8: Complete | K8: In Progress | L8: 3.22 | M8: Good Standing | N8: 2024-01-15 | O8: Paid | P8: Paid | Q8: 0 | R8: N/A | S8: Sem Year 3 | T8: N/A | U8: N/A | V8: Not Yet | Y8: 3. Progressing — Year 3 | Z8: Templumis University
A9: TU-2022-0007 | B9: Grace Auma | C9: Undergraduate | D9: BSc | E9: School of Science | F9: 2022-09-06 | G9: Sem 4 | H9: Complete | I9: Complete | J9: In Progress | K9: Pending | L9: 3.68 | M9: Good Standing | N9: 2024-01-15 | O9: Paid | P9: Paid | Q9: 0 | R9: N/A | S9: Sem Year 2 | T9: N/A | U9: N/A | V9: Not Yet | Y9: 2. Progressing — Year 2 | Z9: Templumis University
A10: TU-2020-0008 | B10: Hassan Abdi | C10: Undergraduate | D10: LLB | E10: School of Law | F10: 2020-09-07 | G10: Sem 8 | H10: Complete | I10: Complete | J10: Complete | K10: Complete | L10: 3.1 | M10: Good Standing | N10: 2024-01-15 | O10: Paid | P10: Paid | Q10: 0 | R10: N/A | S10: Sem Year 4 | T10: N/A | U10: N/A | V10: In Progress | Y10: 4. Final Year — Pre-Clearance | Z10: Templumis University
A11: TU-2021-0009 | B11: Ivy Njeri | C11: Undergraduate | D11: BComm | E11: School of Business | F11: 2021-09-05 | G11: Sem 6 | H11: Complete | I11: Complete | J11: Complete | K11: In Progress | L11: 2.8 | M11: Good Standing | N11: 2024-01-15 | O11: Deferred | P11: Deferred | Q11: 0 | R11: N/A | S11: Sem Year 3 | T11: N/A | U11: N/A | V11: Not Yet | Y11: ⏸ Deferred — On Leave | Z11: Templumis University
A12: TU-2023-0010 | B12: James Kibaki | C12: Undergraduate | D12: BSc | E12: School of Computing | F12: 2023-09-04 | G12: Sem 2 | H12: In Progress | I12: In Progress | J12: Pending | K12: Pending | L12: 3.4 | M12: Good Standing | N12: 2024-01-15 | O12: Paid | P12: Paid | Q12: 0 | R12: N/A | S12: Sem Year 1 | T12: N/A | U12: N/A | V12: Not Yet | Y12: 1. Enrolled & Orientated | Z12: Templumis University
A13: TU-2022-0011 | B13: Kezia Moraa | C13: Undergraduate | D13: BSc | E13: School of Science | F13: 2022-09-06 | G13: Sem 4 | H13: Complete | I13: Complete | J13: In Progress | K13: Pending | L13: 3.05 | M13: Good Standing | N13: 2024-01-15 | O13: Paid | P13: Paid | Q13: 0 | R13: N/A | S13: Sem Year 2 | T13: N/A | U13: N/A | V13: Not Yet | Y13: 2. Progressing — Year 2 | Z13: Templumis University
A14: TU-2019-0012 | B14: Liam Okonkwo | C14: Undergraduate | D14: BSc | E14: School of Engineering | F14: 2019-09-02 | G14: Completed | H14: Complete | I14: Complete | J14: Complete | K14: Complete | L14: 2.6 | M14: Cleared | N14: 2024-01-15 | O14: Paid | P14: Cleared | Q14: 0 | R14: N/A | S14: Sem Year 4 | T14: N/A | U14: N/A | V14: Approved | W14: 2024-01-15 | X14: 2023-11-10 | Y14: 6. Graduated ✓ | Z14: Templumis University
A15: TU-2021-0013 | B15: Mary Adhiambo | C15: Undergraduate | D15: BA | E15: School of Social Sciences | F15: 2021-09-05 | G15: Sem 6 | H15: Complete | I15: Complete | J15: Complete | K15: In Progress | L15: 3.5 | M15: Good Standing | N15: 2024-01-15 | O15: Paid | P15: Paid | Q15: 0 | R15: N/A | S15: Sem Year 3 | T15: N/A | U15: N/A | V15: Not Yet | Y15: 3. Progressing — Year 3 | Z15: Templumis University
A16: TU-2020-0014 | B16: Noel Kiprotich | C16: Undergraduate | D16: BPharm | E16: School of Health Sciences | F16: 2020-09-07 | G16: Sem 8 | H16: Complete | I16: Complete | J16: Complete | K16: Complete | L16: 1.9 | M16: Suspended | N16: 2023-12-01 | O16: Overdue | P16: Overdue | Q16: 75000 | R16: N/A | S16: Sem Year 4 | T16: N/A | U16: N/A | V16: Blocked | Y16: ⚠ Academic Hold — Suspended | Z16: Templumis University
A17: TU-2023-0015 | B17: Olivia Achieng | C17: Undergraduate | D17: BA | E17: School of Arts | F17: 2023-09-04 | G17: Sem 2 | H17: In Progress | I17: In Progress | J17: Pending | K17: Pending | L17: 3.82 | M17: Good Standing | N17: 2024-01-15 | O17: Paid | P17: Paid | Q17: 0 | R17: N/A | S17: Sem Year 1 | T17: N/A | U17: N/A | V17: Not Yet | Y17: 1. Enrolled & Orientated | Z17: Templumis University
A18: TU-2022-0016 | B18: Patrick Owino | C18: Undergraduate | D18: BSc | E18: School of Science | F18: 2022-09-06 | G18: Sem 4 | H18: Complete | I18: Complete | J18: In Progress | K18: Pending | L18: 2.95 | M18: Good Standing | N18: 2024-01-15 | O18: Paid | P18: Paid | Q18: 0 | R18: N/A | S18: Sem Year 2 | T18: N/A | U18: N/A | V18: Not Yet | Y18: 2. Progressing — Year 2 | Z18: Templumis University
A19: TU-2021-0017 | B19: Queenie Mugo | C19: Undergraduate | D19: BSc | E19: School of Computing | F19: 2021-09-05 | G19: Sem 6 | H19: Complete | I19: Complete | J19: Complete | K19: In Progress | L19: 3.95 | M19: Good Standing | N19: 2024-01-15 | O19: Paid | P19: Paid | Q19: 0 | R19: N/A | S19: Sem Year 3 | T19: N/A | U19: N/A | V19: Not Yet | Y19: 3. Progressing — Year 3 | Z19: Templumis University
A20: TU-2020-0018 | B20: Robert Dlamini | C20: Undergraduate | D20: BEd | E20: School of Education | F20: 2020-09-07 | G20: Sem 8 | H20: Complete | I20: Complete | J20: Complete | K20: Complete | L20: 3.3 | M20: Good Standing | N20: 2024-01-15 | O20: Paid | P20: Paid | Q20: 0 | R20: N/A | S20: Sem Year 4 | T20: N/A | U20: N/A | V20: In Progress | Y20: 4. Final Year — Pre-Clearance | Z20: Templumis University
A21: TU-2023-0019 | B21: Sandra Chebet | C21: Undergraduate | D21: BSc | E21: School of Health Sciences | F21: 2023-09-04 | G21: Sem 2 | H21: In Progress | I21: In Progress | J21: Pending | K21: Pending | L21: 3.15 | M21: Good Standing | N21: 2024-01-15 | O21: Paid | P21: Paid | Q21: 0 | R21: N/A | S21: Sem Year 1 | T21: N/A | U21: N/A | V21: Not Yet | Y21: 1. Enrolled & Orientated | Z21: Templumis University
A22: TU-2022-0020 | B22: Tunde Adeyemi | C22: Undergraduate | D22: LLB | E22: School of Law | F22: 2022-09-06 | G22: Sem 4 | H22: Complete | I22: Complete | J22: In Progress | K22: Pending | L22: 3.6 | M22: Good Standing | N22: 2024-01-15 | O22: Paid | P22: Paid | Q22: 0 | R22: N/A | S22: Sem Year 2 | T22: N/A | U22: N/A | V22: Not Yet | Y22: 2. Progressing — Year 2 | Z22: Templumis University
A23: TU-2021-0021 | B23: Uchenna Eze | C23: Undergraduate | D23: BA | E23: School of Social Sciences | F23: 2021-09-05 | G23: Sem 6 | H23: Complete | I23: Complete | J23: Complete | K23: In Progress | L23: 2.75 | M23: Good Standing | N23: 2024-01-15 | O23: Deferred | P23: Deferred | Q23: 0 | R23: N/A | S23: Sem Year 3 | T23: N/A | U23: N/A | V23: Not Yet | Y23: ⏸ Deferred — On Leave | Z23: Templumis University
A24: TU-2019-0022 | B24: Vivian Kamau | C24: Undergraduate | D24: BSc | E24: School of Science | F24: 2019-09-02 | G24: Completed | H24: Complete | I24: Complete | J24: Complete | K24: Complete | L24: 3.88 | M24: Cleared | N24: 2024-01-15 | O24: Paid | P24: Cleared | Q24: 0 | R24: N/A | S24: Sem Year 4 | T24: N/A | U24: N/A | V24: Approved | W24: 2024-01-15 | X24: 2023-11-10 | Y24: 6. Graduated ✓ | Z24: Templumis University
A25: TU-2023-0023 | B25: William Barasa | C25: Undergraduate | D25: BComm | E25: School of Business | F25: 2023-09-04 | G25: Sem 2 | H25: In Progress | I25: In Progress | J25: Pending | K25: Pending | L25: 2.2 | M25: Probation | N25: 2023-12-01 | O25: Partial | P25: Partial | Q25: 35000 | R25: N/A | S25: Sem Year 1 | T25: N/A | U25: N/A | V25: Blocked | Y25: ⚠ Academic Review — Probation | Z25: Templumis University
A26: TU-2022-0024 | B26: Xena Mutua | C26: Undergraduate | D26: BSc | E26: School of Computing | F26: 2022-09-06 | G26: Sem 4 | H26: Complete | I26: Complete | J26: In Progress | K26: Pending | L26: 3.42 | M26: Good Standing | N26: 2024-01-15 | O26: Paid | P26: Paid | Q26: 0 | R26: N/A | S26: Sem Year 2 | T26: N/A | U26: N/A | V26: Not Yet | Y26: 2. Progressing — Year 2 | Z26: Templumis University
A27: TU-2023-0025 | B27: Stephen Gaita Gaikia | C27: Undergraduate | D27: BSc | E27: School of Computing | F27: 2023-09-04 | G27: Sem 2 | H27: In Progress | I27: In Progress | J27: Pending | K27: Pending | L27: 3.65 | M27: Good Standing | N27: 2024-01-15 | O27: Paid (Reg. Only) | P27: Arrears — KES 75,000 | Q27: 75000 | R27: N/A | S27: Sem Year 1 | T27: N/A | U27: N/A | V27: Not Yet | Y27: 1. Enrolled & Orientated | Z27: Templumis University
A28: TU-PG-2022-0026 | B28: Amara Diallo | C28: Postgraduate | D28: MSc (Coursework) | E28: School of Computing | F28: 2022-09-05 | G28: Sem 4 | H28: Complete | I28: Complete | J28: In Progress | K28: Pending | L28: 3.72 | M28: Good Standing | N28: 2024-01-15 | O28: Paid | P28: Paid | Q28: 0 | R28: N/A | S28: Sem 4 | T28: N/A | U28: N/A | V28: In Progress | Y28: 3. PG Final Semester — Pre-Graduation | Z28: Templumis University
A29: TU-PG-2023-0027 | B29: Benjamin Kamto | C29: Postgraduate | D29: MBA (Coursework) | E29: School of Business | F29: 2023-09-04 | G29: Sem 2 | H29: In Progress | I29: In Progress | J29: Pending | K29: Pending | L29: 3.41 | M29: Good Standing | N29: 2024-01-15 | O29: Paid | P29: Paid | Q29: 0 | R29: N/A | S29: Sem 2 | T29: N/A | U29: N/A | V29: Not Yet | Y29: 1. PG Enrolled — Coursework Phase | Z29: Templumis University
A30: TU-PG-2022-0028 | B30: Celestine Awino | C30: Postgraduate | D30: MA (Coursework) | E30: School of Business | F30: 2022-09-05 | G30: Completed | H30: Complete | I30: Complete | J30: Complete | K30: Complete | L30: 3.55 | M30: Cleared | N30: 2023-11-01 | O30: Paid | P30: Cleared | Q30: 0 | R30: N/A | S30: Completed | T30: N/A | U30: N/A | V30: Approved | W30: 2023-11-01 | X30: 2023-11-10 | Y30: 4. Graduated ✓ | Z30: Templumis University
A31: TU-PG-2023-0029 | B31: Derrick Ssempa | C31: Postgraduate | D31: MSc (Coursework) | E31: School of Science | F31: 2023-09-04 | G31: Sem 2 | H31: In Progress | I31: In Progress | J31: Pending | K31: Pending | L31: 2.81 | M31: Probation | N31: 2023-12-01 | O31: Partial | P31: Partial | Q31: 35000 | R31: N/A | S31: Sem 2 | T31: N/A | U31: N/A | V31: Blocked | Y31: ⚠ Academic Review — Probation | Z31: Templumis University
A32: TU-PG-2022-0030 | B32: Faith Onyango | C32: Postgraduate | D32: MA (Coursework) | E32: School of Arts | F32: 2022-09-05 | G32: Sem 4 | H32: Complete | I32: Complete | J32: In Progress | K32: Pending | L32: 3.65 | M32: Good Standing | N32: 2024-01-15 | O32: Paid | P32: Paid | Q32: 0 | R32: N/A | S32: Sem 4 | T32: N/A | U32: N/A | V32: In Progress | Y32: 3. PG Final Semester — Pre-Graduation | Z32: Templumis University
A33: TU-PG-2023-0031 | B33: George Nkosi | C33: Postgraduate | D33: MBA (Coursework) | E33: School of Business | F33: 2023-09-04 | G33: Sem 2 | H33: In Progress | I33: In Progress | J33: Pending | K33: Pending | L33: 3.22 | M33: Good Standing | N33: 2024-01-15 | O33: Paid | P33: Paid | Q33: 0 | R33: N/A | S33: Sem 2 | T33: N/A | U33: N/A | V33: Not Yet | Y33: 1. PG Enrolled — Coursework Phase | Z33: Templumis University
A34: TU-PG-2021-0032 | B34: Helen Mutuku | C34: Postgraduate | D34: MSc by Research | E34: School of Science | F34: 2021-09-06 | G34: Research Year 3 | H34: Complete | I34: Complete | J34: Complete | K34: Complete | L34: 3.82 | M34: Good Standing | N34: 2024-01-15 | O34: Paid | P34: Paid | Q34: 0 | R34: Writing | S34: Writing | T34: In Progress | U34: Not Yet | V34: Not Yet | Y34: 4. Thesis Writing Phase | Z34: Templumis University
A35: TU-PG-2022-0033 | B35: Ibrahim Hassan | C35: Postgraduate | D35: MSc by Research | E35: School of Computing | F35: 2022-09-05 | G35: Research Year 2 | H35: Complete | I35: Complete | J35: Complete | K35: In Progress | L35: 3.61 | M35: Good Standing | N35: 2024-01-15 | O35: Paid | P35: Paid | Q35: 0 | R35: Data Collection | S35: Data Collection | T35: Not Yet | U35: Not Yet | V35: Not Yet | Y35: 3. Data Collection & Analysis Phase | Z35: Templumis University
A36: TU-PG-2021-0034 | B36: Janet Akinyi | C36: Postgraduate | D36: MA by Research | E36: School of Education | F36: 2021-09-06 | G36: Research Year 3 | H36: Complete | I36: Complete | J36: Complete | K36: Complete | L36: 3.48 | M36: Good Standing | N36: 2024-01-15 | O36: Paid | P36: Paid | Q36: 0 | R36: Writing | S36: Writing | T36: In Progress | U36: Not Yet | V36: Not Yet | Y36: 4. Thesis Writing Phase | Z36: Templumis University
A37: TU-PG-2022-0035 | B37: Kenneth Osei | C37: Postgraduate | D37: MSc by Research | E37: School of Engineering | F37: 2022-09-05 | G37: Research Year 2 | H37: Complete | I37: Complete | J37: Complete | K37: In Progress | L37: 3.31 | M37: Good Standing | N37: 2024-01-15 | O37: Deferred | P37: Deferred | Q37: 0 | R37: Proposal Approved | S37: Proposal Approved | T37: Not Yet | U37: Not Yet | V37: Not Yet | Y37: ⏸ Deferred — On Leave (Research) | Z37: Templumis University
A38: TU-PG-2020-0036 | B38: Lydia Cheptoo | C38: Postgraduate | D38: MSc by Research | E38: School of Health Sciences | F38: 2020-09-07 | G38: Completed | H38: Complete | I38: Complete | J38: Complete | K38: Complete | L38: 3.91 | M38: Cleared | N38: 2023-11-01 | O38: Paid | P38: Cleared | Q38: 0 | R38: Defended & Approved | S38: Defended & Approved | T38: Submitted | U38: Passed | V38: Approved | W38: 2023-11-01 | X38: 2023-11-10 | Y38: 6. Graduated ✓ (Research) | Z38: Templumis University
A39: TU-PG-2023-0037 | B39: Moses Waweru | C39: Postgraduate | D39: MSc by Research | E39: School of Computing | F39: 2023-09-04 | G39: Research Year 1 | H39: Complete | I39: In Progress | J39: Pending | K39: Pending | L39: 3.52 | M39: Good Standing | N39: 2024-01-15 | O39: Paid | P39: Paid | Q39: 0 | R39: Proposal Submitted | S39: Proposal Submitted | T39: Submitted | U39: Not Yet | V39: Not Yet | Y39: 2. Research Proposal Phase | Z39: Templumis University
A40: TU-PHD-2021-0038 | B40: Amina Osei | C40: Postgraduate | D40: PhD by Research | E40: School of Computing | F40: 45175 | G40: Research Year 3 | H40: Complete ✓ | I40: Complete ✓ | J40: Complete ✓ | K40: In Progress | L40: 3.88 | M40: Good Standing | N40: 45306 | O40: Paid | P40: Paid | Q40: 0 | R40: Proposal Defended ✓ — Candidacy Confirmed | S40: Data Collection Active (Year 3) | T40: Not Yet | U40: Not Yet | V40: Not Yet | Y40: 5. Candidacy Confirmed — Data Collection Phase | Z40: Templumis University
A41: TU-PHD-2020-0039 | B41: Samuel Odhiambo | C41: Postgraduate | D41: PhD by Research | E41: School of Health Sciences | F41: 45176 | G41: Research Year 4 | H41: Complete ✓ | I41: Complete ✓ | J41: Complete ✓ | K41: Complete ✓ | L41: 3.71 | M41: Good Standing | N41: 45306 | O41: Paid | P41: Paid | Q41: 0 | R41: Proposal Defended ✓ — Candidacy Confirmed | S41: Data Collection Complete ✓ | T41: In Progress — Writing | U41: Not Yet | V41: Not Yet | Y41: 6. Thesis Writing Phase (Final) | Z41: Templumis University
A42: TU-PHD-2023-0040 | B42: Fatima Al-Rashid | C42: Postgraduate | D42: PhD by Research | E42: School of Business | F42: 45173 | G42: Research Year 1 | H42: Complete ✓ | I42: In Progress | J42: Pending | K42: Pending | L42: 3.65 | M42: Good Standing | N42: 45306 | O42: Paid | P42: Paid | Q42: 0 | R42: In Progress — Draft Proposal Stage | S42: Foundation Coursework (Year 1) | T42: Not Yet | U42: Not Yet | V42: Not Yet | Y42: 2. Research Proposal Writing | Z42: Templumis University
A43: TU-PHD-2022-0041 | B43: Peter Kamau Njeru | C43: Postgraduate | D43: PhD by Research | E43: School of Science | F43: 45540 | G43: Research Year 2 | H43: Complete ✓ | I43: Complete ✓ | J43: In Progress | K43: Pending | L43: 3.42 | M43: Good Standing | N43: 45306 | O43: Paid | P43: Paid | Q43: 0 | R43: Submitted — Awaiting Proposal Defense | S43: Pre-Candidacy Phase (Year 2) | T43: Not Yet | U43: Not Yet | V43: Not Yet | Y43: 3. Proposal Defense — Pre-Candidacy Phase | Z43: Templumis University
A44: KT-2021-0001 | B44: Yusuf Al-Farsi | C44: Undergraduate | D44: BSc | E44: School of Computer Science | F44: 2021-09-02 | G44: Sem 6 | H44: Complete | I44: Complete | J44: Complete | K44: In Progress | L44: 3.71 | M44: Good Standing | N44: 2024-01-15 | O44: Paid | P44: Paid | Q44: 0 | R44: N/A | S44: Sem Year 3 | T44: N/A | U44: N/A | V44: Not Yet | Y44: 3. Progressing — Year 3 | Z44: Kitaptech University
A45: KT-2022-0002 | B45: Fatima Al-Sayed | C45: Undergraduate | D45: BSc | E45: School of Software Engineering | F45: 2022-09-04 | G45: Sem 4 | H45: Complete | I45: Complete | J45: Complete | K45: Pending | L45: 3.18 | M45: Good Standing | N45: 2024-01-15 | O45: Paid | P45: Paid | Q45: 0 | R45: N/A | S45: Sem Year 2 | T45: N/A | U45: N/A | V45: Not Yet | Y45: 2. Progressing — Year 2 | Z45: Kitaptech University
A46: KT-2020-0003 | B46: Omar Haddad | C46: Undergraduate | D46: BSc | E46: School of Information Technology & Cybersecurity | F46: 2020-09-05 | G46: Sem 8 | H46: Complete | I46: Complete | J46: Complete | K46: Complete | L46: 3.49 | M46: Good Standing | N46: 2024-01-15 | O46: Paid | P46: Paid | Q46: 0 | R46: N/A | S46: Sem Year 4 | T46: N/A | U46: N/A | V46: In Progress | Y46: 4. Final Year — Pre-Clearance | Z46: Kitaptech University
A47: KT-2020-0004 | B47: Layla Mansour | C47: Undergraduate | D47: BSc | E47: School of Data Science & Artificial Intelligence | F47: 2020-09-06 | G47: Completed | H47: Complete | I47: Complete | J47: Complete | K47: Complete | L47: 3.92 | M47: Cleared | N47: 2024-01-15 | O47: Paid | P47: Cleared | Q47: 0 | R47: N/A | S47: Sem Year 4 | T47: N/A | U47: N/A | V47: Approved | W47: 2024-01-15 | X47: 2023-11-10 | Y47: 6. Graduated ✓ | Z47: Kitaptech University
A48: KT-2023-0005 | B48: Khalid Nasser | C48: Undergraduate | D48: BSc | E48: School of Information Technology & Cybersecurity | F48: 2023-09-07 | G48: Sem 2 | H48: In Progress | I48: In Progress | J48: Pending | K48: Pending | L48: 2.38 | M48: Probation | N48: 2023-12-01 | O48: Partial | P48: Partial | Q48: 35000 | R48: N/A | S48: Sem Year 1 | T48: N/A | U48: N/A | V48: Blocked | Y48: ⚠ Academic Review — Probation | Z48: Kitaptech University
A49: KT-2021-0006 | B49: Rania Saleh | C49: Undergraduate | D49: BSc | E49: School of Computer Science | F49: 2021-09-02 | G49: Sem 6 | H49: Complete | I49: Complete | J49: Complete | K49: In Progress | L49: 3.27 | M49: Good Standing | N49: 2024-01-15 | O49: Paid | P49: Paid | Q49: 0 | R49: N/A | S49: Sem Year 3 | T49: N/A | U49: N/A | V49: Not Yet | Y49: 3. Progressing — Year 3 | Z49: Kitaptech University
A50: KT-2022-0007 | B50: Hamza Zidane | C50: Undergraduate | D50: BSc | E50: School of Digital Business & Financial Technology | F50: 2022-09-04 | G50: Sem 4 | H50: Complete | I50: Complete | J50: Complete | K50: Pending | L50: 3.61 | M50: Good Standing | N50: 2024-01-15 | O50: Paid | P50: Paid | Q50: 0 | R50: N/A | S50: Sem Year 2 | T50: N/A | U50: N/A | V50: Not Yet | Y50: 2. Progressing — Year 2 | Z50: Kitaptech University
A51: KT-2020-0008 | B51: Noor Al-Amin | C51: Undergraduate | D51: BSc | E51: School of Software Engineering | F51: 2020-09-05 | G51: Sem 8 | H51: Complete | I51: Complete | J51: Complete | K51: Complete | L51: 3.15 | M51: Good Standing | N51: 2024-01-15 | O51: Paid | P51: Paid | Q51: 0 | R51: N/A | S51: Sem Year 4 | T51: N/A | U51: N/A | V51: In Progress | Y51: 4. Final Year — Pre-Clearance | Z51: Kitaptech University
A52: KT-2021-0009 | B52: Bilal Qureshi | C52: Undergraduate | D52: BSc | E52: School of Data Science & Artificial Intelligence | F52: 2021-09-06 | G52: Sem 6 | H52: Complete | I52: Complete | J52: Complete | K52: In Progress | L52: 2.73 | M52: Good Standing | N52: 2024-01-15 | O52: Deferred | P52: Deferred | Q52: 0 | R52: N/A | S52: Sem Year 3 | T52: N/A | U52: N/A | V52: Not Yet | Y52: ⏸ Deferred — On Leave | Z52: Kitaptech University
A53: KT-2023-0010 | B53: Sami Hijazi | C53: Undergraduate | D53: BSc | E53: School of Information Technology & Cybersecurity | F53: 2023-09-07 | G53: Sem 2 | H53: In Progress | I53: In Progress | J53: Pending | K53: Pending | L53: 3.38 | M53: Good Standing | N53: 2024-01-15 | O53: Paid | P53: Paid | Q53: 0 | R53: N/A | S53: Sem Year 1 | T53: N/A | U53: N/A | V53: Not Yet | Y53: 1. Enrolled & Orientated | Z53: Kitaptech University
A54: KT-2022-0011 | B54: Dalia Abdullah | C54: Undergraduate | D54: BSc | E54: School of Computer Science | F54: 2022-09-02 | G54: Sem 4 | H54: Complete | I54: Complete | J54: Complete | K54: Pending | L54: 3.02 | M54: Good Standing | N54: 2024-01-15 | O54: Paid | P54: Paid | Q54: 0 | R54: N/A | S54: Sem Year 2 | T54: N/A | U54: N/A | V54: Not Yet | Y54: 2. Progressing — Year 2 | Z54: Kitaptech University
A55: KT-2020-0012 | B55: Tariq Al-Otaibi | C55: Undergraduate | D55: BSc | E55: School of Software Engineering | F55: 2020-09-04 | G55: Completed | H55: Complete | I55: Complete | J55: Complete | K55: Complete | L55: 2.58 | M55: Cleared | N55: 2024-01-15 | O55: Paid | P55: Cleared | Q55: 0 | R55: N/A | S55: Sem Year 4 | T55: N/A | U55: N/A | V55: Approved | W55: 2024-01-15 | X55: 2023-11-10 | Y55: 6. Graduated ✓ | Z55: Kitaptech University
A56: KT-2021-0013 | B56: Maryam Karam | C56: Undergraduate | D56: BSc | E56: School of Information Technology & Cybersecurity | F56: 2021-09-05 | G56: Sem 6 | H56: Complete | I56: Complete | J56: Complete | K56: In Progress | L56: 3.55 | M56: Good Standing | N56: 2024-01-15 | O56: Paid | P56: Paid | Q56: 0 | R56: N/A | S56: Sem Year 3 | T56: N/A | U56: N/A | V56: Not Yet | Y56: 3. Progressing — Year 3 | Z56: Kitaptech University
A57: KT-2020-0014 | B57: Faisal Al-Mutairi | C57: Undergraduate | D57: BSc | E57: School of Digital Business & Financial Technology | F57: 2020-09-06 | G57: Sem 8 | H57: Complete | I57: Complete | J57: Complete | K57: Complete | L57: 1.92 | M57: Suspended | N57: 2023-12-01 | O57: Overdue | P57: Overdue | Q57: 75000 | R57: N/A | S57: Sem Year 4 | T57: N/A | U57: N/A | V57: Blocked | Y57: ⚠ Academic Hold — Suspended | Z57: Kitaptech University
A58: KT-2023-0015 | B58: Huda Shammari | C58: Undergraduate | D58: BSc | E58: School of Data Science & Artificial Intelligence | F58: 2023-09-07 | G58: Sem 2 | H58: In Progress | I58: In Progress | J58: Pending | K58: Pending | L58: 3.79 | M58: Good Standing | N58: 2024-01-15 | O58: Paid | P58: Paid | Q58: 0 | R58: N/A | S58: Sem Year 1 | T58: N/A | U58: N/A | V58: Not Yet | Y58: 1. Enrolled & Orientated | Z58: Kitaptech University
A59: KT-2021-0016 | B59: Ahmed Al-Masri | C59: Undergraduate | D59: BSc | E59: School of Computer Science | F59: 2021-09-02 | G59: Sem 6 | H59: Complete | I59: Complete | J59: Complete | K59: In Progress | L59: 3.11 | M59: Good Standing | N59: 2024-01-15 | O59: Paid | P59: Paid | Q59: 0 | R59: N/A | S59: Sem Year 3 | T59: N/A | U59: N/A | V59: Not Yet | Y59: 3. Progressing — Year 3 | Z59: Kitaptech University
A60: KT-2022-0017 | B60: Yasmin Qasim | C60: Undergraduate | D60: BSc | E60: School of Information Technology & Cybersecurity | F60: 2022-09-04 | G60: Sem 4 | H60: Complete | I60: Complete | J60: Complete | K60: Pending | L60: 3.64 | M60: Good Standing | N60: 2024-01-15 | O60: Paid | P60: Paid | Q60: 0 | R60: N/A | S60: Sem Year 2 | T60: N/A | U60: N/A | V60: Not Yet | Y60: 2. Progressing — Year 2 | Z60: Kitaptech University
A61: KT-2020-0018 | B61: Karim Hamdan | C61: Undergraduate | D61: BSc | E61: School of Software Engineering | F61: 2020-09-05 | G61: Sem 8 | H61: Complete | I61: Complete | J61: Complete | K61: Complete | L61: 3.05 | M61: Good Standing | N61: 2024-01-15 | O61: Paid | P61: Paid | Q61: 0 | R61: N/A | S61: Sem Year 4 | T61: N/A | U61: N/A | V61: In Progress | Y61: 4. Final Year — Pre-Clearance | Z61: Kitaptech University
A62: KT-2021-0019 | B62: Zainab Al-Rashid | C62: Undergraduate | D62: BSc | E62: School of Digital Business & Financial Technology | F62: 2021-09-06 | G62: Sem 6 | H62: Complete | I62: Complete | J62: Complete | K62: In Progress | L62: 3.44 | M62: Good Standing | N62: 2024-01-15 | O62: Paid | P62: Paid | Q62: 0 | R62: N/A | S62: Sem Year 3 | T62: N/A | U62: N/A | V62: Not Yet | Y62: 3. Progressing — Year 3 | Z62: Kitaptech University
A63: KT-2023-0020 | B63: Hassan Mansour | C63: Undergraduate | D63: BSc | E63: School of Computer Science | F63: 2023-09-07 | G63: Sem 2 | H63: In Progress | I63: In Progress | J63: Pending | K63: Pending | L63: 2.21 | M63: Probation | N63: 2023-12-01 | O63: Partial | P63: Partial | Q63: 35000 | R63: N/A | S63: Sem Year 1 | T63: N/A | U63: N/A | V63: Blocked | Y63: ⚠ Academic Review — Probation | Z63: Kitaptech University
A64: KT-2022-0021 | B64: Salma Nasser | C64: Undergraduate | D64: BSc | E64: School of Information Technology & Cybersecurity | F64: 2022-09-02 | G64: Sem 4 | H64: Complete | I64: Complete | J64: Complete | K64: Pending | L64: 3.59 | M64: Good Standing | N64: 2024-01-15 | O64: Paid | P64: Paid | Q64: 0 | R64: N/A | S64: Sem Year 2 | T64: N/A | U64: N/A | V64: Not Yet | Y64: 2. Progressing — Year 2 | Z64: Kitaptech University
A65: KT-2020-0022 | B65: Ali Abdullah | C65: Undergraduate | D65: BSc | E65: School of Data Science & Artificial Intelligence | F65: 2020-09-04 | G65: Sem 8 | H65: Complete | I65: Complete | J65: Complete | K65: Complete | L65: 3.67 | M65: Good Standing | N65: 2024-01-15 | O65: Paid | P65: Paid | Q65: 0 | R65: N/A | S65: Sem Year 4 | T65: N/A | U65: N/A | V65: In Progress | Y65: 4. Final Year — Pre-Clearance | Z65: Kitaptech University
A66: KT-2021-0023 | B66: Reem Al-Farsi | C66: Undergraduate | D66: BSc | E66: School of Software Engineering | F66: 2021-09-05 | G66: Sem 6 | H66: Complete | I66: Complete | J66: Complete | K66: In Progress | L66: 2.84 | M66: Good Standing | N66: 2024-01-15 | O66: Deferred | P66: Deferred | Q66: 0 | R66: N/A | S66: Sem Year 3 | T66: N/A | U66: N/A | V66: Not Yet | Y66: ⏸ Deferred — On Leave | Z66: Kitaptech University
A67: KT-2022-0024 | B67: Mohammed Khalil | C67: Undergraduate | D67: BSc | E67: School of Information Technology & Cybersecurity | F67: 2022-09-06 | G67: Sem 4 | H67: Complete | I67: Complete | J67: Complete | K67: Pending | L67: 3.36 | M67: Good Standing | N67: 2024-01-15 | O67: Paid | P67: Paid | Q67: 0 | R67: N/A | S67: Sem Year 2 | T67: N/A | U67: N/A | V67: Not Yet | Y67: 2. Progressing — Year 2 | Z67: Kitaptech University
... A70: KT-PG-2023-0027 | B70: Rashid Al-Amin | C70: Postgraduate | D70: MBA (Coursework) | E70: School of Digital Business & Financial Technology | F70: 2023-09-04 | G70: Sem 2 | H70: Complete | I70: In Progress | J70: Pending | K70: Pending | L70: 3.35 | M70: Good Standing | N70: 2024-01-15 | O70: Paid | P70: Paid | Q70: 0 | R70: N/A | S70: Sem 2 | T70: N/A | U70: N/A | V70: Not Yet | Y70: 1. PG Enrolled — Coursework Phase | Z70: Kitaptech University
A71: KT-PG-2022-0028 | B71: Dina Khalil | C71: Postgraduate | D71: MSc (Coursework) | E71: School of Information Technology & Cybersecurity | F71: 2022-09-05 | G71: Completed | H71: Complete | I71: Complete | J71: Complete | K71: Complete | L71: 3.58 | M71: Cleared | N71: 2023-11-01 | O71: Paid | P71: Cleared | Q71: 0 | R71: N/A | S71: Completed | T71: N/A | U71: N/A | V71: Approved | W71: 2023-11-01 | X71: 2023-11-10 | Y71: 4. Graduated ✓ | Z71: Kitaptech University
A72: KT-PG-2023-0029 | B72: Waleed Hamdan | C72: Postgraduate | D72: MSc (Coursework) | E72: School of Software Engineering | F72: 2023-09-06 | G72: Sem 2 | H72: Complete | I72: In Progress | J72: Pending | K72: Pending | L72: 2.77 | M72: Probation | N72: 2023-12-01 | O72: Partial | P72: Partial | Q72: 35000 | R72: N/A | S72: Sem 2 | T72: N/A | U72: N/A | V72: Blocked | Y72: ⚠ Academic Review — Probation | Z72: Kitaptech University
A73: KT-PG-2022-0030 | B73: Amal Qasim | C73: Postgraduate | D73: MSc (Coursework) | E73: School of Data Science & Artificial Intelligence | F73: 2022-09-07 | G73: Sem 4 | H73: Complete | I73: Complete | J73: In Progress | K73: Pending | L73: 3.62 | M73: Good Standing | N73: 2024-01-15 | O73: Paid | P73: Paid | Q73: 0 | R73: N/A | S73: Sem 4 | T73: N/A | U73: N/A | V73: In Progress | Y73: 3. PG Final Semester — Pre-Graduation | Z73: Kitaptech University
A74: KT-PG-2023-0031 | B74: Jamal Al-Otaibi | C74: Postgraduate | D74: MBA (Coursework) | E74: School of Digital Business & Financial Technology | F74: 2023-09-02 | G74: Sem 2 | H74: Complete | I74: In Progress | J74: Pending | K74: Pending | L74: 3.24 | M74: Good Standing | N74: 2024-01-15 | O74: Paid | P74: Paid | Q74: 0 | R74: N/A | S74: Sem 2 | T74: N/A | U74: N/A | V74: Not Yet | Y74: 1. PG Enrolled — Coursework Phase | Z74: Kitaptech University
A75: KT-PG-2021-0032 | B75: Samira Haddad | C75: Postgraduate | D75: MSc by Research | E75: School of Data Science & Artificial Intelligence | F75: 2021-09-02 | G75: Research Year 3 | H75: Complete | I75: Complete | J75: Complete | K75: In Progress | L75: 3.84 | M75: Good Standing | N75: 2024-01-15 | O75: Paid | P75: Paid | Q75: 0 | R75: Writing | S75: Writing | T75: In Progress | U75: Not Yet | V75: Not Yet | Y75: 4. Thesis Writing Phase | Z75: Kitaptech University
A76: KT-PG-2022-0033 | B76: Anwar Mutairi | C76: Postgraduate | D76: MSc by Research | E76: School of Computer Science | F76: 2022-09-04 | G76: Research Year 2 | H76: Complete | I76: Complete | J76: Complete | K76: In Progress | L76: 3.47 | M76: Good Standing | N76: 2024-01-15 | O76: Paid | P76: Paid | Q76: 0 | R76: Data Collection | S76: Data Collection | T76: Not Yet | U76: Not Yet | V76: Not Yet | Y76: 3. Data Collection & Analysis Phase | Z76: Kitaptech University
A77: KT-PG-2021-0034 | B77: Samar Odeh | C77: Postgraduate | D77: MA by Research | E77: School of Information Technology & Cybersecurity | F77: 2021-09-05 | G77: Research Year 3 | H77: Complete | I77: Complete | J77: Complete | K77: In Progress | L77: 3.51 | M77: Good Standing | N77: 2024-01-15 | O77: Paid | P77: Paid | Q77: 0 | R77: Writing | S77: Writing | T77: In Progress | U77: Not Yet | V77: Not Yet | Y77: 4. Thesis Writing Phase | Z77: Kitaptech University
A78: KT-PG-2022-0035 | B78: Bassam Najjar | C78: Postgraduate | D78: MSc by Research | E78: School of Information Technology & Cybersecurity | F78: 2022-09-06 | G78: Research Year 2 | H78: Complete | I78: Complete | J78: Complete | K78: In Progress | L78: 3.29 | M78: Good Standing | N78: 2024-01-15 | O78: Deferred | P78: Deferred | Q78: 0 | R78: Data Collection | S78: Data Collection | T78: Not Yet | U78: Not Yet | V78: Not Yet | Y78: ⏸ Deferred — On Leave (Research) | Z78: Kitaptech University
A79: KT-PG-2020-0036 | B79: Hanan Zahran | C79: Postgraduate | D79: MSc by Research | E79: School of Data Science & Artificial Intelligence | F79: 2020-09-07 | G79: Completed | H79: Complete | I79: Complete | J79: Complete | K79: Complete | L79: 3.88 | M79: Cleared | N79: 2023-11-01 | O79: Paid | P79: Cleared | Q79: 0 | R79: Defended & Approved | S79: Defended & Approved | T79: Approved | U79: Approved | V79: Approved | W79: 2023-11-01 | X79: 2023-11-10 | Y79: 6. Graduated ✓ (Research) | Z79: Kitaptech University
A80: KT-PG-2023-0037 | B80: Marwan Saad | C80: Postgraduate | D80: MSc by Research | E80: School of Computer Science | F80: 2023-09-02 | G80: Research Year 1 | H80: Complete | I80: Complete | J80: Complete | K80: In Progress | L80: 3.49 | M80: Good Standing | N80: 2024-01-15 | O80: Paid | P80: Paid | Q80: 0 | R80: Proposal Submitted | S80: Proposal Submitted | T80: Not Yet | U80: Not Yet | V80: Not Yet | Y80: 2. Research Proposal Phase | Z80: Kitaptech University
A81: KT-PHD-2021-0038 | B81: Nabil Farouk | C81: Postgraduate | D81: PhD by Research | E81: School of Computer Science | F81: 2021-09-02 | G81: Research Year 3 | H81: Complete | I81: Complete | J81: Complete | K81: In Progress | L81: 3.81 | M81: Good Standing | N81: 2024-01-15 | O81: Paid | P81: Paid | Q81: 0 | R81: Data Collection | S81: Data Collection | T81: Not Yet | U81: Not Yet | V81: Not Yet | Y81: 5. Candidacy Confirmed — Data Collection Phase | Z81: Kitaptech University
A82: KT-PHD-2020-0039 | B82: Soraya Bint Nasser | C82: Postgraduate | D82: PhD by Research | E82: School of Data Science & Artificial Intelligence | F82: 2020-09-04 | G82: Research Year 4 | H82: Complete | I82: Complete | J82: Complete | K82: In Progress | L82: 3.73 | M82: Good Standing | N82: 2024-01-15 | O82: Paid | P82: Paid | Q82: 0 | R82: Writing | S82: Writing | T82: In Progress | U82: Not Yet | V82: Not Yet | Y82: 6. Thesis Writing Phase (Final) | Z82: Kitaptech University
A83: KT-PHD-2023-0040 | B83: Karam Abu Zaid | C83: Postgraduate | D83: PhD by Research | E83: School of Information Technology & Cybersecurity | F83: 2023-09-05 | G83: Research Year 1 | H83: Complete | I83: Complete | J83: Complete | K83: In Progress | L83: 3.55 | M83: Good Standing | N83: 2024-01-15 | O83: Paid | P83: Paid | Q83: 0 | R83: Proposal Writing | S83: Proposal Writing | T83: Not Yet | U83: Not Yet | V83: Not Yet | Y83: 2. Research Proposal Writing | Z83: Kitaptech University
A84: KT-PHD-2022-0041 | B84: Widad El-Amrani | C84: Postgraduate | D84: PhD by Research | E84: School of Software Engineering | F84: 2022-09-06 | G84: Research Year 2 | H84: Complete | I84: Complete | J84: Complete | K84: In Progress | L84: 3.38 | M84: Good Standing | N84: 2024-01-15 | O84: Paid | P84: Paid | Q84: 0 | R84: Proposal Submitted — Awaiting Defense | S84: Proposal Submitted — Awaiting Defense | T84: Not Yet | U84: Not Yet | V84: Not Yet | Y84: 3. Proposal Defense — Pre-Candidacy Phase | Z84: Kitaptech University
A85: RU-2021-0001 | B85: Dennis Otieno | C85: Undergraduate | D85: BEd | E85: School of Education | F85: 2021-09-02 | G85: Sem 6 | H85: Complete | I85: Complete | J85: Complete | K85: In Progress | L85: 3.41 | M85: Good Standing | N85: 2024-01-15 | O85: Paid | P85: Paid | Q85: 0 | R85: N/A | S85: Sem Year 3 | T85: N/A | U85: N/A | V85: Not Yet | Y85: 3. Progressing — Year 3 | Z85: Rongo University
A86: RU-2022-0002 | B86: Sharon Achieng | C86: Undergraduate | D86: BCom | E86: School of Business and Human Resource Management | F86: 2022-09-04 | G86: Sem 4 | H86: Complete | I86: Complete | J86: Complete | K86: Pending | L86: 3.09 | M86: Good Standing | N86: 2024-01-15 | O86: Paid | P86: Paid | Q86: 0 | R86: N/A | S86: Sem Year 2 | T86: N/A | U86: N/A | V86: Not Yet | Y86: 2. Progressing — Year 2 | Z86: Rongo University
A87: RU-2020-0003 | B87: Collins Onyango | C87: Undergraduate | D87: BA | E87: School of Information, Communication and Media Studies | F87: 2020-09-05 | G87: Sem 8 | H87: Complete | I87: Complete | J87: Complete | K87: Complete | L87: 3.52 | M87: Good Standing | N87: 2024-01-15 | O87: Paid | P87: Paid | Q87: 0 | R87: N/A | S87: Sem Year 4 | T87: N/A | U87: N/A | V87: In Progress | Y87: 4. Final Year — Pre-Clearance | Z87: Rongo University
A88: RU-2020-0004 | B88: Brenda Adhiambo | C88: Undergraduate | D88: BSc | E88: School of Science, Technology and Engineering | F88: 2020-09-06 | G88: Completed | H88: Complete | I88: Complete | J88: Complete | K88: Complete | L88: 3.87 | M88: Cleared | N88: 2024-01-15 | O88: Paid | P88: Cleared | Q88: 0 | R88: N/A | S88: Sem Year 4 | T88: N/A | U88: N/A | V88: Approved | W88: 2024-01-15 | X88: 2023-11-10 | Y88: 6. Graduated ✓ | Z88: Rongo University
A89: RU-2023-0005 | B89: Kevin Owino | C89: Undergraduate | D89: BA | E89: School of Arts and Social Sciences | F89: 2023-09-07 | G89: Sem 2 | H89: In Progress | I89: In Progress | J89: Pending | K89: Pending | L89: 2.31 | M89: Probation | N89: 2023-12-01 | O89: Partial | P89: Partial | Q89: 35000 | R89: N/A | S89: Sem Year 1 | T89: N/A | U89: N/A | V89: Blocked | Y89: ⚠ Academic Review — Probation | Z89: Rongo University
A90: RU-2021-0006 | B90: Mercy Akinyi | C90: Undergraduate | D90: BSc | E90: School of Agriculture, Natural Resources and Environmental Studies | F90: 2021-09-02 | G90: Sem 6 | H90: Complete | I90: Complete | J90: Complete | K90: In Progress | L90: 3.22 | M90: Good Standing | N90: 2024-01-15 | O90: Paid | P90: Paid | Q90: 0 | R90: N/A | S90: Sem Year 3 | T90: N/A | U90: N/A | V90: Not Yet | Y90: 3. Progressing — Year 3 | Z90: Rongo University
A91: RU-2022-0007 | B91: Elvis Opiyo | C91: Undergraduate | D91: BCom | E91: School of Business and Human Resource Management | F91: 2022-09-04 | G91: Sem 4 | H91: Complete | I91: Complete | J91: Complete | K91: Pending | L91: 3.64 | M91: Good Standing | N91: 2024-01-15 | O91: Paid | P91: Paid | Q91: 0 | R91: N/A | S91: Sem Year 2 | T91: N/A | U91: N/A | V91: Not Yet | Y91: 2. Progressing — Year 2 | Z91: Rongo University
A92: RU-2020-0008 | B92: Joy Anyango | C92: Undergraduate | D92: BEd | E92: School of Education | F92: 2020-09-05 | G92: Sem 8 | H92: Complete | I92: Complete | J92: Complete | K92: Complete | L92: 3.17 | M92: Good Standing | N92: 2024-01-15 | O92: Paid | P92: Paid | Q92: 0 | R92: N/A | S92: Sem Year 4 | T92: N/A | U92: N/A | V92: In Progress | Y92: 4. Final Year — Pre-Clearance | Z92: Rongo University
A93: RU-2021-0009 | B93: Moses Ochieng | C93: Undergraduate | D93: BSc | E93: School of Agriculture, Natural Resources and Environmental Studies | F93: 2021-09-06 | G93: Sem 6 | H93: Complete | I93: Complete | J93: Complete | K93: In Progress | L93: 2.78 | M93: Good Standing | N93: 2024-01-15 | O93: Deferred | P93: Deferred | Q93: 0 | R93: N/A | S93: Sem Year 3 | T93: N/A | U93: N/A | V93: Not Yet | Y93: ⏸ Deferred — On Leave | Z93: Rongo University
A94: RU-2023-0010 | B94: Lilian Auma | C94: Undergraduate | D94: BA | E94: School of Information, Communication and Media Studies | F94: 2023-09-07 | G94: Sem 2 | H94: In Progress | I94: In Progress | J94: Pending | K94: Pending | L94: 3.45 | M94: Good Standing | N94: 2024-01-15 | O94: Paid | P94: Paid | Q94: 0 | R94: N/A | S94: Sem Year 1 | T94: N/A | U94: N/A | V94: Not Yet | Y94: 1. Enrolled & Orientated | Z94: Rongo University
A95: RU-2022-0011 | B95: Paul Oduya | C95: Undergraduate | D95: BSc | E95: School of Science, Technology and Engineering | F95: 2022-09-02 | G95: Sem 4 | H95: Complete | I95: Complete | J95: Complete | K95: Pending | L95: 3.06 | M95: Good Standing | N95: 2024-01-15 | O95: Paid | P95: Paid | Q95: 0 | R95: N/A | S95: Sem Year 2 | T95: N/A | U95: N/A | V95: Not Yet | Y95: 2. Progressing — Year 2 | Z95: Rongo University
A96: RU-2020-0012 | B96: Janet Nyambura | C96: Undergraduate | D96: BEd | E96: School of Education | F96: 2020-09-04 | G96: Completed | H96: Complete | I96: Complete | J96: Complete | K96: Complete | L96: 2.61 | M96: Cleared | N96: 2024-01-15 | O96: Paid | P96: Cleared | Q96: 0 | R96: N/A | S96: Sem Year 4 | T96: N/A | U96: N/A | V96: Approved | W96: 2024-01-15 | X96: 2023-11-10 | Y96: 6. Graduated ✓ | Z96: Rongo University
A97: RU-2021-0013 | B97: Brian Omondi | C97: Undergraduate | D97: BA | E97: School of Arts and Social Sciences | F97: 2021-09-05 | G97: Sem 6 | H97: Complete | I97: Complete | J97: Complete | K97: In Progress | L97: 3.48 | M97: Good Standing | N97: 2024-01-15 | O97: Paid | P97: Paid | Q97: 0 | R97: N/A | S97: Sem Year 3 | T97: N/A | U97: N/A | V97: Not Yet | Y97: 3. Progressing — Year 3 | Z97: Rongo University
A98: RU-2020-0014 | B98: Beatrice Atieno | C98: Undergraduate | D98: BSc | E98: School of Agriculture, Natural Resources and Environmental Studies | F98: 2020-09-06 | G98: Sem 8 | H98: Complete | I98: Complete | J98: Complete | K98: Complete | L98: 1.96 | M98: Suspended | N98: 2023-12-01 | O98: Overdue | P98: Overdue | Q98: 75000 | R98: N/A | S98: Sem Year 4 | T98: N/A | U98: N/A | V98: Blocked | Y98: ⚠ Academic Hold — Suspended | Z98: Rongo University
A99: RU-2023-0015 | B99: Michael Wafula | C99: Undergraduate | D99: BSc | E99: School of Science, Technology and Engineering | F99: 2023-09-07 | G99: Sem 2 | H99: In Progress | I99: In Progress | J99: Pending | K99: Pending | L99: 3.71 | M99: Good Standing | N99: 2024-01-15 | O99: Paid | P99: Paid | Q99: 0 | R99: N/A | S99: Sem Year 1 | T99: N/A | U99: N/A | V99: Not Yet | Y99: 1. Enrolled & Orientated | Z99: Rongo University
A100: RU-2021-0016 | B100: Christine Achola | C100: Undergraduate | D100: BCom | E100: School of Business and Human Resource Management | F100: 2021-09-02 | G100: Sem 6 | H100: Complete | I100: Complete | J100: Complete | K100: In Progress | L100: 3.13 | M100: Good Standing | N100: 2024-01-15 | O100: Paid | P100: Paid | Q100: 0 | R100: N/A | S100: Sem Year 3 | T100: N/A | U100: N/A | V100: Not Yet | Y100: 3. Progressing — Year 3 | Z100: Rongo University
A101: RU-2022-0017 | B101: Steve Okoth | C101: Undergraduate | D101: BSc | E101: School of Science, Technology and Engineering | F101: 2022-09-04 | G101: Sem 4 | H101: Complete | I101: Complete | J101: Complete | K101: Pending | L101: 3.59 | M101: Good Standing | N101: 2024-01-15 | O101: Paid | P101: Paid | Q101: 0 | R101: N/A | S101: Sem Year 2 | T101: N/A | U101: N/A | V101: Not Yet | Y101: 2. Progressing — Year 2 | Z101: Rongo University
A102: RU-2020-0018 | B102: Vivian Nyakundi | C102: Undergraduate | D102: BA | E102: School of Arts and Social Sciences | F102: 2020-09-05 | G102: Sem 8 | H102: Complete | I102: Complete | J102: Complete | K102: Complete | L102: 2.97 | M102: Good Standing | N102: 2024-01-15 | O102: Paid | P102: Paid | Q102: 0 | R102: N/A | S102: Sem Year 4 | T102: N/A | U102: N/A | V102: In Progress | Y102: 4. Final Year — Pre-Clearance | Z102: Rongo University
...

Sheet Rankings Dashboard
A1: TemplumIS University — Global Ranking Indicators Dashboard (Templumis University Deep-Dive)
A2: Academic Year 2023/24 · Semester 1 | Data sourced from LMS/SIS institutional records
A4: INSTITUTIONAL SUMMARY
A5: Total Students | B5: 37 | C5: Avg GPA | D5: 3.32 / 4.0 | E5: International Students | F5: 35.1% | G5: Female Ratio | H5: 48.6%
A6: UG Students | B6: 25 | C6: Active Students | D6: 25 | E6: Research Students | F6: 6 | G6: Nationalities | H6: 10
A7: PG Students | B7: 12 | C7: Graduates | D7: 5 | E7: Student:Faculty Ratio | F7: 2.5 : 1 | G7: Schools / Faculties | H7: 9
A8: Faculty (Instructors) | B8: 15 | C8: Active Courses | D8: 19 | E8: Avg Attendance | F8: 83% | G8: Avg Grade | H8: 77.6%
A10: WEBOMETRICS Ranking of World Universities
A11: Focus: Web presence, openness & academic output
A12: Indicator | B12: Weight | C12: Score Estimate | D12: Notes / TemplumIS Evidence | E12: Status
A13: Visibility / Impact (Web links) | B13: 50% | C13: ~20% | D13: Institutional website not indexed in dataset; no inlink data available | E13: ⚠
A14: Openness / Transparency (OA repos) | B14: 10% | C14: ~25% | D14: 6 research dissertations in progress; no open access repository evidenced | E14: ⚠
A15: Excellence (Google Scholar output) | B15: 10% | C15: ~15% | D15: Research topics active (malaria, AI, NLP) but publications not yet confirmed | E15: ✗
A16: Presence (indexed web pages) | B16: 5% | C16: ~30% | D16: Domain @templumis.ac confirmed; web footprint/page count unknown | E16: ⚠
A17: OVERALL DATA READINESS | B17: — | C17: ~22% | D17: Weighted estimate based on available institutional data
A19: THE World University Rankings
A20: Focus: Teaching, research, citations & international outlook
A21: Indicator | B21: Weight | C21: Score Estimate | D21: Notes / TemplumIS Evidence | E21: Status
A22: Teaching — Learning Environment | B22: 29.5% | C22: ~62% | D22: SFR 2.5:1 (excellent); avg GPA 3.32; 9 schools; 20 active courses; reputation survey data N/A | E22: ✓
A23: Research — Environment & Productivity | B23: 29% | C23: ~18% | D23: 6 research students; dissertations in health, CS, engineering; research income data unavailable | E23: ✗
A24: Citations — Research Influence (Scopus) | B24: 30% | C24: ~5% | D24: No citation records in institutional data; requires Scopus indexing | E24: ✗
A25: International Outlook | B25: 7.5% | C25: ~58% | D25: 35.1% international students; 10 nationalities; strong Pan-African diversity | E25: ✓
A26: Industry Income per Academic | B26: 4% | C26: ~5% | D26: No industry partnership or income data recorded in dataset | E26: ✗
A27: OVERALL DATA READINESS | B27: — | C27: ~26% | D27: Weighted estimate based on available institutional data
A29: THE Sub-Saharan Africa Rankings (SSA)
A30: Focus: Regionally adapted THE criteria for African universities
A31: Indicator | B31: Weight | C31: Score Estimate | D31: Notes / TemplumIS Evidence | E31: Status
A32: Teaching & Learning | B32: 25% | C32: ~70% | D32: SFR 2.5:1; 20 courses; 5 graduates; avg grade 77.6%; strong student support systems | E32: ✓
A33: Research | B33: 30% | C33: ~35% | D33: 6 active research students (16.2%); applied African topics; no citation data | E33: ⚠
A34: Knowledge Transfer to Society | B34: 20% | C34: ~40% | D34: Dissertations on maternal health, Swahili NLP, solar desalination — locally relevant | E34: ⚠
A35: International Outlook | B35: 15% | C35: ~65% | D35: 10 nationalities; 35.1% international; Pan-African student mix across 10 countries | E35: ✓
A36: Access & Inclusion | B36: 10% | C36: ~68% | D36: 48.6% female; academic support processes (probation, standing review) evidenced | E36: ✓
A37: OVERALL DATA READINESS | B37: — | C37: ~50% | D37: Weighted estimate based on available institutional data
A39: Shanghai ARWU (Academic Ranking of World Universities)
A40: Focus: Research output, Nobel laureates & high-impact publications
A41: Indicator | B41: Weight | C41: Score Estimate | D41: Notes / TemplumIS Evidence | E41: Status
A42: Alumni — Nobel / Fields Medal winners | B42: 10% | C42: ~0% | D42: 5 graduates confirmed; no Nobel/Fields alumni data applicable at this stage | E42: ✗
A43: Staff — Nobel / Fields Medal winners | B43: 20% | C43: ~0% | D43: No data on faculty international awards of this calibre | E43: ✗
A44: Highly Cited Researchers (Clarivate HiCi) | B44: 20% | C44: ~0% | D44: No citation records; Clarivate HiCi designation not evidenced | E44: ✗
A45: Papers in Nature & Science | B45: 20% | C45: ~0% | D45: Research in dissertation phase; no Nature/Science publications confirmed | E45: ✗
A46: Papers in SCI / SSCI (Web of Science) | B46: 20% | C46: ~5% | D46: 6 research dissertations underway; journal publishing pipeline not recorded | E46: ⚠
A47: Per capita academic performance (PCP) | B47: 10% | C47: ~8% | D47: 15 faculty; small institution could score relatively if output begins | E47: ⚠
A48: OVERALL DATA READINESS | B48: — | C48: ~5% | D48: Weighted estimate based on available institutional data
A50: QS World University Rankings
A51: Focus: Reputation, faculty ratio, citations & international diversity
A52: Indicator | B52: Weight | C52: Score Estimate | D52: Notes / TemplumIS Evidence | E52: Status
A53: Academic Reputation (survey) | B53: 30% | C53: ~10% | D53: No global survey presence; institution not yet globally known | E53: ✗
A54: Employer Reputation (survey) | B54: 15% | C54: ~10% | D54: 5 graduates; no employment tracking or employer survey data available | E54: ✗
A55: Faculty/Student Ratio | B55: 10% | C55: ~88% | D55: 2.5:1 ratio — exceptional; well within global top-tier benchmarks (<10:1) | E55: ✓
A56: Citations per Faculty (Scopus) | B56: 20% | C56: ~5% | D56: No Scopus citation records in dataset; requires active publication base | E56: ✗
A57: International Faculty Ratio | B57: 5% | C57: ~25% | D57: All 15 instructors appear local; international faculty not distinguishable from data | E57: ⚠
A58: International Student Ratio | B58: 5% | C58: ~72% | D58: 35.1% international students — strong; 13 students from 9 non-Kenyan countries | E58: ✓
A59: Sustainability (ESG metrics) | B59: 5% | C59: ~20% | D59: Community-focused research topics noted; formal sustainability reporting not evidenced | E59: ⚠
A60: Employment Outcomes | B60: 10% | C60: ~20% | D60: 5 confirmed graduates; no employment rate or alumni outcomes tracking data | E60: ⚠
A61: OVERALL DATA READINESS | B61: — | C61: ~32% | D61: Weighted estimate based on available institutional data
A63: CWTS Leiden Ranking
A64: Focus: Bibliometric research performance (Web of Science)
A65: Indicator | B65: Weight | C65: Score Estimate | D65: Notes / TemplumIS Evidence | E65: Status
A66: P — Scientific output (WoS papers) | B66: Core | C66: ~8% | D66: 6 research theses in progress; malaria, AI/UAV, NLP topics; none confirmed indexed | E66: ⚠
A67: PP(top 10%) — Citation impact | B67: Core | C67: ~3% | D67: No Web of Science citation records available; requires published indexed output | E67: ✗
A68: MCS — Mean citation score (normalised) | B68: Core | C68: ~3% | D68: Citation tracking requires published and indexed output in WoS | E68: ✗
A69: PP(collab) — International co-authorship | B69: Core | C69: ~10% | D69: Multi-national student body; potential for collaboration; no co-authorship data recorded | E69: ⚠
A70: PP(gender) — Female authorship | B70: Supplementary | C70: ~45% | D70: 48.6% female students; 3 of 6 research students are female — strong potential | E70: ⚠
A71: PP(OA) — Open Access publications | B71: Supplementary | C71: ~10% | D71: No open access repository or infrastructure evidenced in institutional data | E71: ✗
A72: OVERALL DATA READINESS | B72: — | C72: ~8% | D72: Weighted estimate based on available institutional data
A74: METHODOLOGY NOTE
A75: Score estimates are proxies derived from institutional LMS/SIS data available in the TemplumIS dataset. Indicators requiring external data (Scopus, Web of Science, employer surveys, academic reputation surveys, Clarivate HiCi lists) cannot be fully evaluated from internal records alone. Status symbols: ✓ = Performing well, ⚠ = Limited/partial data, ✗ = No data or not applicable. Scores represent current data readiness relative to each ranking's criteria, not projected global ranking positions.
A79: ALL INSTITUTIONS — INSTITUTIONAL SUMMARY COMPARISON
A80: Snapshot across Templumis University, Kitaptech University & Rongo University — sourced from current LMS/SIS institutional records
A81: Metric | B81: Templumis University | C81: Kitaptech University | D81: Rongo University
A82: Total Students | B82: 41 | C82: 41 | D82: 41
A83: Active Students | B83: 29 | C83: 30 | D83: 30
A84: Graduates (to date) | B84: 5 | C84: 4 | D84: 4
A85: UG / PG (Masters) / PhD | B85: 25 / 12 / 4 | C85: 25 / 12 / 4 | D85: 25 / 12 / 4
A86: Research Students (MSc/MA/PhD by Research) | B86: 10 | C86: 10 | D86: 10
A87: Female Ratio | B87: 48.8% | C87: 48.8% | D87: 48.8%
A88: Nationalities Represented | B88: 11 | C88: 16 (Pan-Regional GCC/MENA) | D88: 3 (predominantly Kenyan)
A89: Avg GPA | B89: 3.35 | C89: 3.33 | D89: 3.29
A90: Avg Attendance | B90: 88% | C90: 96% | D90: 96%
A91: Schools / Faculties | B91: 9 | C91: 5 (tech-focused) | D91: 6 (per rongovarsity.ac.ke)
A92: Faculty (Instructors) | B92: 16 | C92: 7 | D92: 12
... A95: Domain | B95: templumis.ac | C95: kitaptech.com | D95: rongovarsity.ac.ke
A97: Note: Kitaptech University's student body spans the GCC/MENA region with no single dominant home nationality, so "international %" is not a meaningful metric there — diversity is instead expressed as the count of nationalities represented. Rongo University figures are grounded in its real academic structure (rongovarsity.ac.ke); Kitaptech University's tech-focused schools and Templumis University's general catalogue are both illustrative. All other ranking-framework tables above (WEBOMETRICS, THE, THE SSA, ARWU, QS, CWTS Leiden) remain Templumis University-specific deep dives.

Sheet PG Research Tracker
A1: Templumis University — Postgraduate Research Tracker
A2: Academic Years 2023/24–2025/26 | All Active & Graduated Postgraduate Students | SIS — Research Management Module
A4: Student ID | B4: Student Name | C4: Programme Level | D4: Department | E4: Supervisor | F4: Co-Supervisor | G4: Research / Capstone Title | H4: Research Area / Specialisation | I4: Programme Status | J4: Current Stage | K4: Stage Reference | L4: M1: Enrolment & Orientation | M4: M2: Proposal / Yr 1 Coursework | N4: M3: Lit Review / Yr 2 Coursework | O4: M4: Data Collection / Capstone | P4: M5: Analysis & Writing | Q4: M6: Thesis / Report Submission | R4: M7: Defence / Viva / Presentation | S4: Overall Progress (%) | T4: Expected Completion | U4: Research / Capstone Output | V4: Next Review Date | W4: Stage Notes | X4: Institution
A5: TU-PG-2022-0026 | B5: Amara Diallo | C5: MSc (Coursework) | D5: School of Computing | E5: Ms. Cynthia Aluoch | F5: Dr. Kevin Otiato (JKUAT, External) | G5: Predictive Modeling for Urban Traffic Flow Optimization in Nairobi | H5: Data Science — Urban Mobility & Smart City Analytics | I5: Active | J5: Capstone Writing Phase | K5: 3. PG Final Semester — Pre-Graduation | L5: Complete ✓ | M5: Complete ✓ | N5: Complete ✓ | O5: Complete ✓ | P5: In Progress | Q5: Pending | R5: N/A (Coursework) | S5: 80 | T5: 45473 | U5: N/A (Coursework Track) | V5: 45366 | W5: On track for June 2024 graduation; data analysis complete; capstone writing in progress | X5: Templumis University
A6: TU-PG-2023-0027 | B6: Benjamin Kamto | C6: MBA (Coursework) | D6: School of Business | E6: Prof. Wambua Simiyu | F6: N/A | G6: TBD — Capstone topic selection due Semester 3 | H6: Business Administration — Marketing Analytics & Consumer Strategy | I6: Active | J6: Coursework Phase — Semester 2 | K6: 1. PG Enrolled — Coursework Phase | L6: Complete ✓ | M6: In Progress | N6: Pending | O6: Pending | P6: Pending | Q6: Pending | R6: N/A (Coursework) | S6: 30 | T6: 45838 | U6: N/A (Coursework Phase) | V6: 45473 | W6: GPA 3.41 in Sem 1; performing well in Sem 2; capstone topic selection due Sem 3 | X6: Templumis University
A7: TU-PG-2022-0028 | B7: Celestine Awino | C7: MA (Coursework) | D7: School of Business | E7: Prof. Wambua Simiyu | F7: N/A | G7: Kenya's Export Diversification: The Role of Regional Trade Agreements in the EAC | H7: Economics — International Trade, Regional Integration & Development Policy | I7: Graduated | J7: Graduated ✓ | K7: 4. Graduated ✓ | L7: Complete ✓ | M7: Complete ✓ | N7: Complete ✓ | O7: Complete ✓ | P7: Complete ✓ | Q7: Complete ✓ | R7: Complete ✓ | S7: 100 | T7: 45971 | U7: Capstone: Kenya's Export Diversification & EAC Trade Agreements (2024) | W7: Graduated Good Standing; GPA 3.55; capstone commended by panel; alumni network active | X7: Templumis University
A8: TU-PG-2023-0029 | B8: Derrick Ssempa | C8: MSc (Coursework) | D8: School of Science | E8: Dr. Sasha Mutinda | F8: N/A | G8: N/A — Academic Review; Capstone phase not yet reached | H8: Environmental Science — Climate Change Adaptation & Sustainability | I8: Probation | J8: Academic Review — Probation | K8: ⚠ Academic Review — Probation | L8: Complete ✓ | M8: In Progress (Below Standard) | N8: Pending | O8: Pending | P8: Pending | Q8: Pending | R8: N/A (Coursework) | S8: 15 | T8: 46022 | U8: N/A — Academic Review | V8: 45473 | W8: GPA 2.81 — must attain ≥ 3.00 in Sem 2; academic support plan & counselling in place | X8: Templumis University
A9: TU-PG-2022-0030 | B9: Faith Onyango | C9: MA (Coursework) | D9: School of Arts | E9: Ms. Abigael Ndungu | F9: Dr. Zawadi Amani (School of Social Sciences) | G9: Social Media Influence on Political Participation Among Youth in East Africa | H9: Communication Studies — Digital Media, Civic Engagement & Political Discourse | I9: Active | J9: Capstone Writing Phase | K9: 3. PG Final Semester — Pre-Graduation | L9: Complete ✓ | M9: Complete ✓ | N9: Complete ✓ | O9: Complete ✓ | P9: In Progress | Q9: Pending | R9: N/A (Coursework) | S9: 78 | T9: 45473 | U9: N/A (Coursework Track) | V9: 45371 | W9: On track for June 2024; survey data (n=650 youth, 6 countries) collected & analysed; draft introduction submitted | X9: Templumis University
A10: TU-PG-2023-0031 | B10: George Nkosi | C10: MBA (Coursework) | D10: School of Business | E10: Prof. Wambua Simiyu | F10: N/A | G10: TBD — Capstone topic selection due Semester 3 | H10: Business Administration — Strategic Management & Organisational Leadership | I10: Active | J10: Coursework Phase — Semester 2 | K10: 1. PG Enrolled — Coursework Phase | L10: Complete ✓ | M10: In Progress | N10: Pending | O10: Pending | P10: Pending | Q10: Pending | R10: N/A (Coursework) | S10: 28 | T10: 45838 | U10: N/A (Coursework Phase) | V10: 45473 | W10: GPA 3.22; Pan-African Diversity Grant awarded; strong Sem 1; capstone topic selection due Sem 3 | X10: Templumis University
A11: TU-PG-2021-0032 | B11: Helen Mutuku | C11: MSc by Research | D11: School of Science | E11: Prof. Margaret Wangari | F11: Dr. Daniel Njomo (KEMRI, External) | G11: Novel Enzyme Inhibitors in Malaria Parasite Metabolism | H11: Biochemistry — Antimalarial Drug Discovery, Enzyme Kinetics & Parasitology | I11: Active | J11: ⚠ Thesis Writing — CHALLENGE: Ch.3 Major Revision Required | K11: 4. Thesis Writing Phase | L11: Complete ✓ | M11: Complete ✓ | N11: Complete ✓ | O11: Complete ✓ | P11: ⚠ Revision Required — Kinetic Model Error Identified | Q11: Pending | R11: Pending | S11: 62 | T11: 45580 | U11: Conference Paper: East Africa Biochem Symposium 2024 | V11: 45350 | W11: ⚠ CASE-PG-001 ACTIVE | Supervisor returned Ch.3 (48pp): enzyme kinetics must use Hill equation not Michaelis-Menten for cooperative binding system. All QA reanalysis needed (8–10 wks). Co-supervisor Dr. Njomo on WHO field duty until Apr 2024 — Dr. Ouma appointed interim. LC-MS/MS booked March 4–8 2024. Viva rescheduled: Oct 2024. | X11: Templumis University
A12: TU-PG-2022-0033 | B12: Ibrahim Hassan | C12: MSc by Research | D12: School of Computing | E12: Dr. Kamande Njoroge | F12: Prof. James Mwema (School of Engineering) | G12: AI-Based Crop Disease Detection Using UAV Imagery | H12: Computer Science — Computer Vision, Deep Learning & Precision Agriculture | I12: Active | J12: ⚠ Data Collection — CHALLENGE: Dataset Crisis + Paper Revisions | K12: 3. Data Collection & Analysis Phase | L12: Complete ✓ | M12: Complete ✓ | N12: Complete ✓ | O12: ⚠ Dataset Rebuild Required (31% images unusable — ethics amendment filed) | P12: Not Yet | Q12: Not Yet | R12: Not Yet | S12: 38 | T12: 45991 | U12: Paper submitted — AAAI Africa 2025 Workshop on AI for Agriculture | V12: 45422 | W12: ⚠ CASE-PG-002 ACTIVE | Dataset audit: 155/500 UAV images unusable (motion blur, overexposure, obstruction). Ethics amendment for 2 new counties filed (6–8 wk approval). AAAI paper: Major Revisions — add 3 baselines, ablation study, significance tests. Supervisor on sabbatical Jan–Feb 2024. Revised completion: Nov 2025. | X12: Templumis University
A13: TU-PG-2021-0034 | B13: Janet Akinyi | C13: MA by Research | D13: School of Education | E13: Mr. Barasa Wekesa | F13: Prof. Agnes Njeru (Ministry of Education, External) | G13: Digital Pedagogy & Learning Outcomes in Kenyan Secondary Schools | H13: Education Studies — EdTech, Instructional Design & Learning Outcomes in SSA | I13: Active | J13: Thesis Writing Phase — Research Year 3 | K13: 4. Thesis Writing Phase | L13: Complete ✓ | M13: Complete ✓ | N13: Complete ✓ | O13: Complete ✓ | P13: In Progress | Q13: Pending | R13: Pending | S13: 80 | T13: 45534 | U13: Policy Brief submitted to Kenya Ministry of Education (February 2024) | V13: 45356 | W13: Fieldwork: 12 secondary schools, n=480 students surveyed; full analysis complete; Chapters 1–4 approved; Ch 5 in progress | X13: Templumis University
A14: TU-PG-2022-0035 | B14: Kenneth Osei | C14: MSc by Research | D14: School of Engineering | E14: Dr. Oloo Otiende | F14: Dr. Marcus Kipande (University of Nairobi, External) | G14: Low-Cost Solar Desalination for Rural East Africa | H14: Mechanical Engineering — Renewable Energy Systems & Rural Water Security | I14: On Leave | J14: On Leave — Proposal Approved (Research Year 2) | K14: ⏸ Deferred — On Leave (Research) | L14: Complete ✓ | M14: Complete ✓ | N14: Complete ✓ | O14: Pending — On Leave | P14: Not Yet | Q14: Not Yet | R14: Not Yet | S14: 35 | T14: 46203 | U14: N/A — On Leave; No Research Output Yet | V14: 45536 | W14: Proposal approved with commendation; prototype design ready; fieldwork paused; expected return: Sem 1 2024/25 | X14: Templumis University
A15: TU-PG-2020-0036 | B15: Lydia Cheptoo | C15: MSc by Research | D15: School of Health Sciences | E15: Dr. Atieno Ouma | F15: Prof. Grace Adhola (WHO Kenya, External) | G15: Community-Based Interventions for Maternal Health in Western Kenya | H15: Public Health — Maternal & Child Health, Community Medicine & Health Systems | I15: Graduated | J15: Graduated ✓ (Research) | K15: 6. Graduated ✓ (Research) | L15: Complete ✓ | M15: Complete ✓ | N15: Complete ✓ | O15: Complete ✓ | P15: Complete ✓ | Q15: Complete ✓ | R15: Complete ✓ | S15: 100 | T15: 45915 | U15: Published: East African Medical Journal, 2025 (Vol. 102, Issue 3) | W15: Graduated highest distinction; thesis commended by external examiners; publication peer-reviewed & indexed in Scopus; Postgraduate Research Fellowship holder | X15: Templumis University
A16: TU-PG-2023-0037 | B16: Moses Waweru | C16: MSc by Research | D16: School of Computing | E16: Dr. Kamande Njoroge | F16: Ms. Cynthia Aluoch | G16: Machine Learning for Swahili NLP Applications | H16: Computer Science — Natural Language Processing & African Language AI | I16: Active | J16: Research Proposal Phase — Research Year 1 | K16: 2. Research Proposal Phase | L16: Complete ✓ | M16: In Progress | N16: Pending | O16: Not Yet | P16: Not Yet | Q16: Not Yet | R16: Not Yet | S16: 20 | T16: 46203 | U16: N/A — Early Stage Research (Year 1) | V16: 45397 | W16: Proposal submitted to dept committee; ethics clearance pending; background literature review in progress; dataset scoping begun | X16: Templumis University
A17: TU-PHD-2021-0038 | B17: Amina Osei | C17: PhD by Research | D17: School of Computing | E17: Dr. Kamande Njoroge | F17: Prof. Ruth Mutua (Strathmore University, External) | G17: Federated Learning for Privacy-Preserving Health Data Analytics in Sub-Saharan Africa | H17: Computer Science — Federated Learning, Privacy-Preserving ML & mHealth | I17: Active | J17: Data Collection Phase — Research Year 3 | K17: 5. Candidacy Confirmed — Data Collection | L17: Complete ✓ | M17: Complete ✓ | N17: Complete ✓ | O17: In Progress | P17: Not Yet | Q17: Not Yet | R17: Not Yet | S17: 55 | T17: 46142 | U17: Poster: African AI Summit 2024 | Working Paper: IEEE Trans. Medical Informatics (under review) | V17: 45458 | W17: FL model architecture designed; 4 hospital sites IRB-approved; 2 hospitals onboarded; data collection ongoing | X17: Templumis University
A18: TU-PHD-2020-0039 | B18: Samuel Odhiambo | C18: PhD by Research | D18: School of Health Sciences | E18: Dr. Atieno Ouma | F18: Dr. Rebecca Adero (WHO Kenya, External) | G18: Impact of Community Health Worker Integration on Under-5 Mortality Rates in Rural Kenya | H18: Public Health — Community Health Systems, Child Survival & Health Systems Strengthening | I18: Active | J18: Thesis Writing Phase — Research Year 4 | K18: 6. Thesis Writing Phase (Final) | L18: Complete ✓ | M18: Complete ✓ | N18: Complete ✓ | O18: Complete ✓ | P18: In Progress | Q18: Pending | R18: Not Yet | S18: 78 | T18: 45930 | U18: Published: African J. Primary Health Care (2024) | Under Review: PLOS Global Health | V18: 45371 | W18: 14 counties fieldwork complete; n=2,400 CHW interviews analysed; Chapters 1–4 approved; writing Chapter 5 | X18: Templumis University
A19: TU-PHD-2023-0040 | B19: Fatima Al-Rashid | C19: PhD by Research | D19: School of Business | E19: Prof. Wambua Simiyu | F19: Dr. Emmanuel Kiprotich (IMF Africa Division, External) | G19: FDI, Structural Transformation & Inclusive Growth in East Africa: A Panel Data Analysis | H19: Economics — International Economics, Structural Change & Panel Econometrics | I19: Active | J19: Research Proposal Writing — Year 1 | K19: 2. Research Proposal Writing | L19: Complete ✓ | M19: In Progress | N19: Pending | O19: Not Yet | P19: Not Yet | Q19: Not Yet | R19: Not Yet | S19: 20 | T19: 46203 | U19: N/A — Foundation Phase Year 1 | V19: 45412 | W19: Foundation CW complete; lit review 60% done; World Bank/UNCTAD panel dataset identified; proposal draft 40% written | X19: Templumis University
A20: TU-PHD-2022-0041 | B20: Peter Kamau Njeru | C20: PhD by Research | D20: School of Science | E20: Dr. Sasha Mutinda | F20: Dr. Osei Kwame (UNEP Kenya, External) | G20: Carbon Sequestration Potential of Afromontane Forests: Evidence from Central Kenya | H20: Environmental Science — Carbon Cycling, Forest Ecology & Climate Change Mitigation | I20: Active | J20: Proposal Defense — Pre-Candidacy Phase — Year 2 | K20: 3. Proposal Defense — Pre-Candidacy | L20: Complete ✓ | M20: Complete ✓ | N20: In Progress | O20: Not Yet | P20: Not Yet | Q20: Not Yet | R20: Not Yet | S20: 38 | T20: 46387 | U20: N/A — Pre-Candidacy Phase | V20: 45361 | W20: Systematic lit review complete; pilot site confirmed (Aberdares Forest, 500ha); proposal submitted to dept; UNEP partnership confirmed; awaiting defense date | X20: Templumis University
A21: KT-PG-2022-0026 | B21: Nadia Saleh | C21: MSc (Coursework) | D21: School of Data Science & Artificial Intelligence | E21: Dr. Samir Al-Balawi | F21: N/A | G21: AI — Applied Machine Learning for Arabic NLP | H21: AI — Applied Machine Learning for Arabic NLP | I21: Active | J21: Capstone Writing Phase | K21: 3. PG Final Semester — Pre-Graduation | L21: Complete ✓ | M21: Complete ✓ | N21: Complete ✓ | O21: In Progress | P21: Pending | Q21: Pending | R21: Pending | S21: 78 | T21: 2024-06-30 | U21: N/A (Coursework Track) | V21: 2024-01-15 | W21: Final Capstone Report Submission | X21: Kitaptech University
A22: KT-PG-2023-0027 | B22: Rashid Al-Amin | C22: MBA (Coursework) | D22: School of Digital Business & Financial Technology | E22: Dr. Huda Ibrahim | F22: N/A | G22: Tech Management — Digital Transformation & FinTech Strategy | H22: Tech Management — Digital Transformation & FinTech Strategy | I22: Active | J22: Coursework Phase — Semester 2 | K22: 1. PG Enrolled — Coursework Phase | L22: Complete ✓ | M22: In Progress | N22: Pending | O22: Pending | P22: Pending | Q22: Pending | R22: Pending | S22: 28 | T22: 2025-06-30 | U22: N/A (Coursework Phase) | V22: 2024-01-15 | W22: Semester 2 Coursework Completion | X22: Kitaptech University
A23: KT-PG-2022-0028 | B23: Dina Khalil | C23: MSc (Coursework) | D23: School of Information Technology & Cybersecurity | E23: Dr. Adel Karam | F23: N/A | G23: Cybersecurity — Critical Infrastructure Protection | H23: Cybersecurity — Critical Infrastructure Protection | I23: Graduated | J23: Graduated ✓ | K23: 4. Graduated ✓ | L23: Complete ✓ | M23: Complete ✓ | N23: Complete ✓ | O23: Complete ✓ | P23: Complete ✓ | Q23: Complete ✓ | R23: Complete ✓ | S23: 100 | T23: 2024-06-30 | U23: Capstone: Critical Infrastructure Protection (Completed) | V23: 2023-11-01 | W23: N/A — Graduated | X23: Kitaptech University
A24: KT-PG-2023-0029 | B24: Waleed Hamdan | C24: MSc (Coursework) | D24: School of Software Engineering | E24: Dr. Samar Odeh | F24: N/A | G24: Software Engineering — DevSecOps & Cloud-Native Architectures | H24: Software Engineering — DevSecOps & Cloud-Native Architectures | I24: Probation | J24: Academic Review — Probation | K24: ⚠ Academic Review — Probation | L24: Complete ✓ | M24: In Progress | N24: Pending | O24: Pending | P24: Pending | Q24: Pending | R24: Pending | S24: 15 | T24: 2025-06-30 | U24: N/A — Academic Review Phase | V24: 2023-12-01 | W24: Semester 2 — Achieve GPA ≥ 3.00 to Continue (MSc Software Engineering) | X24: Kitaptech University
A25: KT-PG-2022-0030 | B25: Amal Qasim | C25: MSc (Coursework) | D25: School of Data Science & Artificial Intelligence | E25: Dr. Samir Al-Balawi | F25: Prof. Nour Kassem (School of Digital Business & FinTech) | G25: Data Science — Predictive Analytics for Fintech Risk Scoring | H25: Data Science — Predictive Analytics for Fintech Risk Scoring | I25: Active | J25: Capstone Writing Phase | K25: 3. PG Final Semester — Pre-Graduation | L25: Complete ✓ | M25: Complete ✓ | N25: Complete ✓ | O25: In Progress | P25: Pending | Q25: Pending | R25: Pending | S25: 78 | T25: 2024-06-30 | U25: N/A (Coursework Track) | V25: 2024-01-15 | W25: Final Capstone Report Submission | X25: Kitaptech University
A26: KT-PG-2023-0031 | B26: Jamal Al-Otaibi | C26: MBA (Coursework) | D26: School of Digital Business & Financial Technology | E26: Dr. Huda Ibrahim | F26: N/A | G26: Tech Management — AI Adoption in Gulf Banking Sector | H26: Tech Management — AI Adoption in Gulf Banking Sector | I26: Active | J26: Coursework Phase — Semester 2 | K26: 1. PG Enrolled — Coursework Phase | L26: Complete ✓ | M26: In Progress | N26: Pending | O26: Pending | P26: Pending | Q26: Pending | R26: Pending | S26: 28 | T26: 2025-06-30 | U26: N/A (Coursework Phase) | V26: 2024-01-15 | W26: Semester 2 Coursework Completion | X26: Kitaptech University
A27: KT-PG-2021-0032 | B27: Samira Haddad | C27: MSc by Research | D27: School of Data Science & Artificial Intelligence | E27: Prof. Nour Kassem | F27: Dr. Leila Sabbagh (KAUST, External) | G27: Arabic Dialect Identification Using Transformer-Based Deep Learning | H27: Data Science — Arabic NLP & Dialectal Speech Processing | I27: Active | J27: Thesis Writing Phase | K27: 4. Thesis Writing Phase | L27: Complete ✓ | M27: Complete ✓ | N27: Complete ✓ | O27: Complete ✓ | P27: In Progress | Q27: Pending | R27: Pending | S27: 70 | T27: 2024-06-30 | U27: Working paper in preparation — Arabic NLP & Dialectal Speech Processing | V27: 2024-01-15 | W27: Complete Analysis & Begin Thesis Writing | X27: Kitaptech University
A28: KT-PG-2022-0033 | B28: Anwar Mutairi | C28: MSc by Research | D28: School of Computer Science | E28: Dr. Karim Badawi | F28: Dr. Rafiq Qadri (MBZUAI, External) | G28: Edge-Computing Architectures for Real-Time Fraud Detection in Mobile Payments | H28: Computer Science — Edge AI & FinTech Security | I28: Active | J28: Data Collection & Analysis Phase | K28: 3. Data Collection & Analysis Phase | L28: Complete ✓ | M28: Complete ✓ | N28: Complete ✓ | O28: In Progress | P28: Pending | Q28: Pending | R28: Pending | S28: 42 | T28: 2025-06-30 | U28: Working paper in preparation — Edge AI & FinTech Security | V28: 2024-01-15 | W28: Complete Data Collection & Begin Analysis | X28: Kitaptech University
A29: KT-PG-2021-0034 | B29: Samar Odeh | C29: MA by Research | D29: School of Information Technology & Cybersecurity | E29: Dr. Adel Karam | F29: Prof. Yasir Mansoor (Qatar University, External) | G29: Digital Inclusion & E-Government Adoption Among Arab Youth | H29: Information Systems — Digital Government & Youth Digital Inclusion | I29: Active | J29: Thesis Writing Phase | K29: 4. Thesis Writing Phase | L29: Complete ✓ | M29: Complete ✓ | N29: Complete ✓ | O29: Complete ✓ | P29: In Progress | Q29: Pending | R29: Pending | S29: 70 | T29: 2024-06-30 | U29: Working paper in preparation — Digital Government & Youth Digital Inclusion | V29: 2024-01-15 | W29: Complete Analysis & Begin Thesis Writing | X29: Kitaptech University
